Workbook

Sheet Client Books
A1: [ENTITY NAME]
A2: EIN: [XX-XXXXXXX] | Tax Year: [Start] - [End] | [Accrual/Cash] Basis | [#] Partners ([Split])
A4: Acct # | B4: Account Name | C4: Debit | D4: Credit
A5: ASSETS
A6: 1000 | B6: Cash - Operating
A7: 1010 | B7: Cash - Savings
A8: 1050 | B8: Petty Cash
A9: 1100 | B9: Accounts Receivable
A10: 1110 | B10: Allowance for Doubtful Accounts
A11: 1150 | B11: Notes Receivable - Current
A12: 1200 | B12: Inventory (MUST = PY Ending Inventory)
A13: 1250 | B13: Prepaid Insurance
A14: 1260 | B14: Prepaid Rent
A15: 1300 | B15: Investments - Stocks (Short-term)
A16: 1310 | B16: Investments - Municipal Bonds
A17: 1320 | B17: Investments - Corporate Bonds
... A35: 1800 | B35: Investment in Sub-Partnership (K-1 received)
A36: LIABILITIES
A37: 2000 | B37: Accounts Payable
A38: 2050 | B38: Accrued Expenses
A39: 2060 | B39: Accrued Payroll & Payroll Taxes
A40: 2070 | B40: Accrued Bonuses - Related Party (>2.5 mo unpaid)
A41: 2080 | B41: Sales Tax Payable
A42: 2100 | B42: Unearned Revenue / Deferred Revenue
A43: 2200 | B43: Line of Credit
A44: 2300 | B44: Note Payable - Bank (Current Portion)
A45: 2400 | B45: Mortgage Payable - Building
A46: 2410 | B46: Mortgage Payable - Nonrecourse portion
A47: 2500 | B47: Loans from Partners
A48: 2600 | B48: Other Long-term Liabilities
A49: PARTNERS' EQUITY
A50: 3000 | B50: Partner A - Capital Account (Beg Bal - MUST = PY Ending)
A51: 3010 | B51: Partner B - Capital Account (Beg Bal - MUST = PY Ending)
A52: 3100 | B52: Partner A - Draws/Distributions
A53: 3110 | B53: Partner B - Draws/Distributions
A54: 3200 | B54: Partner A - Contributions
A55: 3210 | B55: Partner B - Contributions
A56: REVENUE
A57: 4000 | B57: Gross Sales / Revenue
A58: 4010 | B58: Sales Returns & Allowances
A59: 4100 | B59: Rental Income - Real Estate (Form 8825)
A60: 4110 | B60: Rental Income - Equipment
A61: 4200 | B61: Interest Income - Bank
A62: 4210 | B62: Interest Income - Municipal Bonds (Tax-Exempt)
A63: 4220 | B63: Interest Income - Corporate Bonds
A64: 4300 | B64: Dividend Income - Ordinary
A65: 4310 | B65: Dividend Income - Qualified
A66: 4400 | B66: Royalty Income
A67: 4500 | B67: Gain on Sale of Equipment (Sec 1231 - held >1yr)
A68: 4510 | B68: Gain on Sale of Stock - Short-term
... A74: 4800 | B74: Other Miscellaneous Income
A75: COST OF GOODS SOLD
A76: 5000 | B76: Beginning Inventory (MUST = PY Ending Inventory)
A77: 5010 | B77: Purchases
A78: 5020 | B78: Direct Labor
A79: 5030 | B79: Freight-In
A80: 5040 | B80: Depreciation in COGS (manufacturing equip)
A81: 5050 | B81: Other Manufacturing Overhead
A82: 5090 | B82: Less: Ending Inventory
A83: OPERATING EXPENSES
A84: 6000 | B84: Salaries & Wages (W-2 employees)
A85: 6010 | B85: Guaranteed Payments - Partner A (services)
A86: 6015 | B86: Guaranteed Payments - Partner B (services)
A87: 6020 | B87: Guaranteed Payments - Use of Capital
A88: 6050 | B88: Payroll Taxes (employer portion)
A89: 6060 | B89: Employee Health Insurance
A90: 6065 | B90: Partner Health Insurance (Partner A)
A91: 6066 | B91: Partner Health Insurance (Partner B)
A92: 6070 | B92: 401(k) Employer Match
A93: 6080 | B93: Workers Compensation Insurance
A94: 6100 | B94: Rent - Office Space
A95: 6110 | B95: Rent - Equipment
... A128: 7900 | B128: Miscellaneous Expense
A129: RENTAL PROPERTY EXPENSES (Form 8825)
A130: 8000 | B130: Rental Property - Depreciation (Book)
A131: 8010 | B131: Rental Property - Insurance
A132: 8020 | B132: Rental Property - Repairs & Maintenance
A133: 8030 | B133: Rental Property - Property Taxes
A134: 8040 | B134: Rental Property - Mortgage Interest
A135: 8050 | B135: Rental Property - Utilities
A136: 8060 | B136: Rental Property - Management Fees
B138: TOTAL TRIAL BALANCE | C138: =SUM(C5:C136) | D138: =SUM(D5:D136)
B139: DIFFERENCE (should be zero) | C139: =C138-D138

Sheet Working Trial Balance
A1: [ENTITY NAME] - WORKING TRIAL BALANCE
A2: EIN: [XX-XXXXXXX] | Tax Year Ended: [MM/DD/YYYY] | [Accrual/Cash] Basis | [#] Partners
A3: LEGEND: | B3: Gold = Linked to Client Books | C3: Blue font = Manual input | D3: Green = Auto-balanced formula | F3: RED = MANUALLY ENTER FROM PY RETURN
A5: # | B5: 1065 Line | C5: Description | D5: Book Amount | E5: Adj# | F5: Adj (+) | G5: Adj (-) | H5: Tax Amount | I5: M-1 / K Category | J5: Adjustment Memo / Notes
A6: BALANCE SHEET — ASSETS
A7: 1 | B7: L Lines 1-2 | C7: Cash + Accounts Receivable (net of allowance) | D7: ='Client Books'!C6+'Client Books'!C7+'Client Books'!C8+'Client Books'!C9-'Client Books'!D10+'Client Books'!C11 | E7: AJE-11 | G7: 0 | H7: =D7+IF(F7,F7,0)-IF(G7,G7,0) | J7: [Enter adjustment notes here]
A8: 2 | B8: L Lines 3-5 | C8: Inventory + Prepaid + Other Current Assets | D8: ='Client Books'!C12+'Client Books'!C13+'Client Books'!C14+'Client Books'!C15+'Client Books'!C16+'Client Books'!C17 | E8: AJE-06 | G8: 0 | H8: =D8+IF(F8,F8,0)-IF(G8,G8,0) | J8: [Enter adjustment notes here]
A9: 3 | B9: L Lines 6-8 | C9: Loans to Partners + Investment in Sub-Partnership | D9: ='Client Books'!C18+'Client Books'!C35 | F9: 0 | G9: 0 | H9: =D9+IF(F9,F9,0)-IF(G9,G9,0) | J9: [Enter adjustment notes here]
A10: 4 | B10: L Lines 9-10 | C10: Fixed Assets (net of accumulated depreciation) | D10: ='Client Books'!C19+'Client Books'!C20-'Client Books'!D21+'Client Books'!C22-'Client Books'!D23+'Client Books'!C24-'Client Books'!D25+'Client Books'!C26-'Client Books'!D27+'Client Books'!C28-'Client Books'!D29 | E10: AJE-01,02 | H10: =D10+IF(F10,F10,0)-IF(G10,G10,0) | J10: [Enter adjustment notes here]
A11: 5 | B11: L Lines 11-14 | C11: Intangibles (net) + Other Assets | D11: ='Client Books'!C30-'Client Books'!D31+'Client Books'!C32-'Client Books'!D33+'Client Books'!C34 | E11: AJE-25 | G11: 0 | H11: =D11+IF(F11,F11,0)-IF(G11,G11,0) | J11: [Enter adjustment notes here]
C12: TOTAL ASSETS | D12: =D7+D8+D9+D10+D11 | H12: =H7+H8+H9+H10+H11
A14: BALANCE SHEET — LIABILITIES
A15: 6 | B15: L Lines 15-21 | C15: Total Liabilities | D15: ='Client Books'!D37+'Client Books'!D38+'Client Books'!D39+'Client Books'!D40+'Client Books'!D41+'Client Books'!D42+'Client Books'!D43+'Client Books'!D44+'Client Books'!D45+'Client Books'!D46+'Client Books'!D47+'Client Books'!D48 | F15: 0 | G15: 0 | H15: =D15+IF(F15,F15,0)-IF(G15,G15,0) | J15: [Enter adjustment notes here]
A17: BALANCE SHEET — PARTNERS' EQUITY / CAPITAL
A18: 7 | B18: L/M-2 Line 1 | C18: Beginning Capital (= PY Ending Capital) | D18: ='Client Books'!D50+'Client Books'!D51 | F18: 0 | G18: 0 | H18: =D18+IF(F18,F18,0)-IF(G18,G18,0) | J18: [Enter adjustment notes here]
A19: 8 | B19: L/M-2 Line 2 | C19: Capital Contributed During Year | D19: ='Client Books'!D54+'Client Books'!D55 | F19: 0 | G19: 0 | H19: =D19+IF(F19,F19,0)-IF(G19,G19,0) | J19: [Enter adjustment notes here]
A20: 9 | B20: L/M-2 | C20: Partner Draws / Distributions | D20: ='Client Books'!C52+'Client Books'!C53 | F20: 0 | G20: 0 | H20: =D20+IF(F20,F20,0)-IF(G20,G20,0) | J20: [Enter adjustment notes here]
A21: 10 | B21: L/M-2 | C21: Current Year Net Income (Per Books) | D21: =D94 | F21: 0 | G21: 0 | H21: =H94 | J21: Auto-tied to M-1 Line 1 (book net income). This makes BS proof work.
C22: ENDING CAPITAL (Beg + Contrib + NI - Draws) | D22: =D18+D19+D21-D20 | H22: =H18+H19+H21-H20 | J22: Book ending capital. Tax capital computed via M-2 below.
B23: CHECK | C23: Book BS Proof: Assets - Liabilities - Ending Capital (should be ZERO) | D23: =D12-D15-D22 | H23: =H12-H15-H22 | J23: BOOK col should = 0. TAX col: any nonzero amount = cumulative book-tax basis difference not yet reflected in beginning tax capital.
A25: PAGE 1 — INCOME
A26: 11 | B26: P1 Line 1a | C26: Gross Receipts or Sales | D26: ='Client Books'!D57 | F26: 0 | G26: 0 | H26: =D26+IF(F26,F26,0)-IF(G26,G26,0) | J26: [Enter adjustment notes here]
A27: 12 | B27: P1 Line 1b | C27: Returns and Allowances | D27: ='Client Books'!C58 | F27: 0 | G27: 0 | H27: =D27+IF(F27,F27,0)-IF(G27,G27,0) | J27: From Acct 4010 debit. Verify supported by credit memos.
A28: 13 | B28: P1 Line 1c | C28: Net Receipts (1a - 1b) | D28: =D26-D27 | H28: =H26-H27 | J28: Calculated.
A29: 14 | B29: P1 Line 2 | C29: Cost of Goods Sold (Schedule A) | D29: ='Client Books'!C76+'Client Books'!C77+'Client Books'!C78+'Client Books'!C79+'Client Books'!C80+'Client Books'!C81-'Client Books'!D82 | F29: 0 | G29: 0 | H29: =D29+IF(F29,F29,0)-IF(G29,G29,0) | J29: Book COGS. Sec 263A UNICAP adj handled via M-1 (not on this line). Verify beg inv = PY ending inv.
A30: 15 | B30: P1 Line 3 | C30: Gross Profit (1c - 2) | D30: =D28-D29 | H30: =H28-H29 | J30: Calculated.
A31: 16 | B31: P1 Line 4 | C31: Ordinary Income from Other Partnerships (K-1) | D31: ='Client Books'!D71 | F31: 0 | G31: 0 | H31: =D31+IF(F31,F31,0)-IF(G31,G31,0) | J31: [Enter adjustment notes here]
A32: 17 | B32: P1 Line 5 | C32: Net Farm Profit (Loss) | D32: 0 | F32: 0 | G32: 0 | H32: =D32+IF(F32,F32,0)-IF(G32,G32,0) | J32: N/A - hide if not applicable.
A33: 18 | B33: P1 Line 6 | C33: Net Gain (Loss) from Form 4797 (ordinary recapture) | D33: 0 | E33: AJE-03 | G33: 0 | H33: =D33+IF(F33,F33,0)-IF(G33,G33,0) | I33: M-1 Line 2 | J33: [Enter adjustment notes here]
A34: 19 | B34: P1 Line 7 | C34: Other Income (Loss) | D34: ='Client Books'!D73+'Client Books'!D74 | E34: AJE-04 | F34: 0 | H34: =D34+IF(F34,F34,0)-IF(G34,G34,0) | I34: M-1 Line 6 (Sec 108) | J34: [Enter adjustment notes here]
A35: 20 | B35: P1 Line 8 | C35: TOTAL INCOME (Lines 3-7) | D35: =D30+D31+D32+D33+D34 | H35: =H30+H31+H32+H33+H34 | J35: Sum of Lines 3-7.
A36: PAGE 1 — DEDUCTIONS
A37: 21 | B37: P1 Line 9 | C37: Salaries and Wages (not to partners) | D37: ='Client Books'!C84 | E37: AJE-07 | F37: 0 | H37: =D37+IF(F37,F37,0)-IF(G37,G37,0) | I37: M-1 4c (Sec 267) | J37: [Enter adjustment notes here]
A38: 22 | B38: P1 Line 10 | C38: Guaranteed Payments to Partners | D38: ='Client Books'!C85+'Client Books'!C86+'Client Books'!C87 | F38: 0 | G38: 0 | H38: =D38+IF(F38,F38,0)-IF(G38,G38,0) | J38: [Enter adjustment notes here]
A39: 23 | B39: P1 Line 11 | C39: Repairs and Maintenance | D39: ='Client Books'!C96 | F39: 0 | G39: 0 | H39: =D39+IF(F39,F39,0)-IF(G39,G39,0) | J39: [Enter adjustment notes here]
A40: 24 | B40: P1 Line 12 | C40: Bad Debts | D40: ='Client Books'!C124 | E40: AJE-08 | F40: 0 | H40: =D40+IF(F40,F40,0)-IF(G40,G40,0) | I40: M-1 4c (Reserve) | J40: [Enter adjustment notes here]
A41: 25 | B41: P1 Line 13 | C41: Rent | D41: ='Client Books'!C94+'Client Books'!C95 | F41: 0 | G41: 0 | H41: =D41+IF(F41,F41,0)-IF(G41,G41,0) | J41: [Enter adjustment notes here]
A42: 26 | B42: P1 Line 14 | C42: Taxes and Licenses | D42: ='Client Books'!C121+'Client Books'!C123 | F42: 0 | G42: 0 | H42: =D42+IF(F42,F42,0)-IF(G42,G42,0) | J42: [Enter adjustment notes here]
A43: 27 | B43: P1 Line 15 | C43: Interest (trade/business) | D43: ='Client Books'!C118+'Client Books'!C119 | F43: 0 | G43: 0 | H43: =D43+IF(F43,F43,0)-IF(G43,G43,0) | J43: [Enter adjustment notes here]
A44: 28 | B44: P1 Line 16a | C44: Tax Depreciation (MACRS, excl Sch A and Sec 179) | D44: ='Client Books'!C98 | E44: AJE-01 | G44: 0 | H44: =D44+IF(F44,F44,0)-IF(G44,G44,0) | I44: M-1 Lines 4a/7 | J44: [Enter adjustment notes here]
A45: 29 | B45: P1 Line 16b | C45: Less: Depreciation in COGS | D45: ='Client Books'!C80 | F45: 0 | G45: 0 | H45: =D45+IF(F45,F45,0)-IF(G45,G45,0) | J45: [Enter adjustment notes here]
A46: 30 | B46: P1 Line 16c | C46: Net Depreciation (16a - 16b) | D46: =D44-D45 | H46: =H44-H45 | J46: Calculated.
A47: 31 | B47: P1 Line 17 | C47: Depletion | D47: 0 | F47: 0 | G47: 0 | H47: =D47+IF(F47,F47,0)-IF(G47,G47,0) | J47: N/A.
A48: 32 | B48: P1 Line 18 | C48: Retirement Plans | D48: ='Client Books'!C92 | F48: 0 | G48: 0 | H48: =D48+IF(F48,F48,0)-IF(G48,G48,0) | J48: [Enter adjustment notes here]
A49: 33 | B49: P1 Line 19 | C49: Employee Benefit Programs | D49: ='Client Books'!C89+'Client Books'!C93 | F49: 0 | G49: 0 | H49: =D49+IF(F49,F49,0)-IF(G49,G49,0) | J49: [Enter adjustment notes here]
A50: 34 | B50: P1 Line 20 | C50: Other Deductions (attach statement) | D50: ='Client Books'!C88+'Client Books'!C101+'Client Books'!C102+'Client Books'!C103+'Client Books'!C104+'Client Books'!C105+'Client Books'!C106+'Client Books'!C107+'Client Books'!C108+'Client Books'!C109+'Client Books'!C110+'Client Books'!C114+'Client Books'!C128 | F50: 0 | G50: 0 | H50: =D50+IF(F50,F50,0)-IF(G50,G50,0) | J50: Payroll taxes, utilities, phone, supplies, postage, insurance, professional fees, advertising, travel, auto, misc.
C51: > Meals (50% deductible) | D51: ='Client Books'!C111 | E51: AJE-14 | F51: 0 | H51: =D51+IF(F51,F51,0)-IF(G51,G51,0) | I51: M-1 4b / K 18c | J51: [Enter adjustment notes here]
C52: > Entertainment (100% nondeductible) | D52: ='Client Books'!C112 | E52: AJE-15 | F52: 0 | H52: =D52+IF(F52,F52,0)-IF(G52,G52,0) | I52: M-1 4b / K 18c | J52: [Enter adjustment notes here]
C53: > Club Dues (100% nondeductible) | D53: ='Client Books'!C113 | E53: AJE-16 | F53: 0 | H53: =D53+IF(F53,F53,0)-IF(G53,G53,0) | I53: M-1 4c / K 18c | J53: [Enter adjustment notes here]
C54: > Penalties & Fines (nondeductible Sec 162(f)) | D54: ='Client Books'!C116 | E54: AJE-17 | F54: 0 | H54: =D54+IF(F54,F54,0)-IF(G54,G54,0) | I54: M-1 4c / K 18c | J54: [Enter adjustment notes here]
C55: > Political Contributions (nondeductible) | D55: ='Client Books'!C117 | E55: AJE-18 | F55: 0 | H55: =D55+IF(F55,F55,0)-IF(G55,G55,0) | I55: M-1 4c / K 18c | J55: [Enter adjustment notes here]
C56: > Life Insurance (partnership beneficiary - nondeductible) | D56: ='Client Books'!C127 | E56: AJE-19 | F56: 0 | H56: =D56+IF(F56,F56,0)-IF(G56,G56,0) | I56: M-1 4c / K 18c | J56: [Enter adjustment notes here]
C57: > State Income/Franchise Tax (nondeductible federal) | D57: ='Client Books'!C122 | E57: AJE-20 | F57: 0 | H57: =D57+IF(F57,F57,0)-IF(G57,G57,0) | I57: M-1 4c / K 18c | J57: [Enter adjustment notes here]
C58: > Warranty Reserve (not deductible until paid) | D58: ='Client Books'!C125 | E58: AJE-09 | F58: 0 | H58: =D58+IF(F58,F58,0)-IF(G58,G58,0) | I58: M-1 4c | J58: [Enter adjustment notes here]
C59: > Litigation Reserve (not deductible until settled) | D59: ='Client Books'!C126 | E59: AJE-10 | F59: 0 | H59: =D59+IF(F59,F59,0)-IF(G59,G59,0) | I59: M-1 4c | J59: [Enter adjustment notes here]
C60: > Partner Health Ins (to K-1 Line 13 Code M) | D60: ='Client Books'!C90+'Client Books'!C91 | E60: AJE-22 | F60: 0 | H60: =D60+IF(F60,F60,0)-IF(G60,G60,0) | I60: K-1 Line 13M | J60: [Enter adjustment notes here]
C61: > Capital Improvement (reclassed to asset, Sec 179) | D61: ='Client Books'!C97 | E61: AJE-02 | F61: 0 | H61: =D61+IF(F61,F61,0)-IF(G61,G61,0) | I61: M-1 Line 7 (Sec 179) | J61: [Enter adjustment notes here]
C62: > Goodwill Amort (book 10yr vs tax Sec 197 15yr) | D62: ='Client Books'!C99 | E62: AJE-12 | F62: 0 | H62: =D62+IF(F62,F62,0)-IF(G62,G62,0) | I62: M-1 4a/7 | J62: [Enter adjustment notes here]
C63: > Patent Amort (book 10yr vs tax Sec 197 15yr) | D63: ='Client Books'!C100 | E63: AJE-13 | F63: 0 | H63: =D63+IF(F63,F63,0)-IF(G63,G63,0) | I63: M-1 4a/7 | J63: [Enter adjustment notes here]
C64: > Charitable Contributions (separately stated, K 13a) | D64: ='Client Books'!C115 | E64: AJE-23 | F64: 0 | H64: =D64+IF(F64,F64,0)-IF(G64,G64,0) | I64: K Line 13a | J64: [Enter adjustment notes here]
C65: > Investment Interest (separately stated, K 13b) | D65: ='Client Books'!C120 | E65: AJE-24 | F65: 0 | H65: =D65+IF(F65,F65,0)-IF(G65,G65,0) | I65: K Line 13b | J65: [Enter adjustment notes here]
A66: 35 | B66: P1 Line 21 | C66: TOTAL DEDUCTIONS (Lines 9-20) | D66: =D37+D38+D39+D40+D41+D42+D43+D46+D47+D48+D49+D50+D51+D52+D53+D54+D55+D56+D57+D58+D59+D60+D61+D62+D63+D64+D65 | H66: =H37+H38+H39+H40+H41+H42+H43+H46+H47+H48+H49+H50+H51+H52+H53+H54+H55+H56+H57+H58+H59+H60+H61+H62+H63+H64+H65 | J66: Sum of all P1 deduction tax amounts.
A67: 36 | B67: P1 Line 22 | C67: ORDINARY BUSINESS INCOME (LOSS) = Line 8 - Line 21 | D67: =D35-D66 | H67: =H35-H66 | J67: Equals K Line 1 and each K-1 Line 1. QBI starting point.
A69: SCHEDULE K — SEPARATELY STATED ITEMS
A70: 37 | B70: K Line 1 | C70: Ordinary Business Income (Loss) = P1 Line 22 | D70: =D67 | H70: =H67 | J70: Auto-tied from P1 Line 22.
A71: 38 | B71: K Line 2 | C71: Net Rental Real Estate Income (Form 8825) | D71: ='Client Books'!D59-('Client Books'!C130+'Client Books'!C131+'Client Books'!C132+'Client Books'!C133+'Client Books'!C134+'Client Books'!C135+'Client Books'!C136) | E71: AJE-05 | G71: 0 | H71: =D71+IF(F71,F71,0)-IF(G71,G71,0) | J71: [Enter adjustment notes here]
A72: 39 | B72: K Line 3c | C72: Net Other Rental Income (Equipment) | D72: ='Client Books'!D60 | F72: 0 | G72: 0 | H72: =D72+IF(F72,F72,0)-IF(G72,G72,0) | J72: [Enter adjustment notes here]
A73: 40 | B73: K Lines 4a-4c | C73: Guaranteed Payments (total) | D73: =D38 | H73: =H38 | J73: [Enter adjustment notes here]
A74: 41 | B74: K Line 5 | C74: Interest Income (portfolio) | D74: ='Client Books'!D61+'Client Books'!D63 | F74: 0 | G74: 0 | H74: =D74+IF(F74,F74,0)-IF(G74,G74,0) | J74: [Enter adjustment notes here]
A75: 42 | B75: K Lines 6a-6b | C75: Dividends (ordinary $13.7K / qualified $8.2K) | D75: ='Client Books'!D64+'Client Books'!D65 | F75: 0 | G75: 0 | H75: =D75+IF(F75,F75,0)-IF(G75,G75,0) | J75: [Enter adjustment notes here]
A76: 43 | B76: K Line 7 | C76: Royalties | D76: ='Client Books'!D66 | F76: 0 | G76: 0 | H76: =D76+IF(F76,F76,0)-IF(G76,G76,0) | J76: [Enter adjustment notes here]
A77: 44 | B77: K Line 8 | C77: Net Short-Term Capital Gain | D77: ='Client Books'!D68 | F77: 0 | G77: 0 | H77: =D77+IF(F77,F77,0)-IF(G77,G77,0) | J77: [Enter adjustment notes here]
A78: 45 | B78: K Line 9a | C78: Net Long-Term Capital Gain | D78: ='Client Books'!D69+'Client Books'!D72 | F78: 0 | G78: 0 | H78: =D78+IF(F78,F78,0)-IF(G78,G78,0) | J78: [Enter adjustment notes here]
A79: 46 | B79: K Line 9b | C79: Collectibles (28%) Gain | D79: ='Client Books'!D70 | F79: 0 | G79: 0 | H79: =D79+IF(F79,F79,0)-IF(G79,G79,0) | J79: [Enter adjustment notes here]
A80: 47 | B80: K Line 10 | C80: Net Sec 1231 Gain (Loss) | D80: ='Client Books'!D67 | E80: AJE-03 | F80: 0 | H80: =D80+IF(F80,F80,0)-IF(G80,G80,0) | J80: [Enter adjustment notes here]
A81: 48 | B81: K Line 11 | C81: Other Income (Loss) | D81: 0 | F81: 0 | G81: 0 | H81: =D81+IF(F81,F81,0)-IF(G81,G81,0) | J81: Catch-all.
C82: SCHEDULE K INCOME TOTAL (Lines 1-11) = must match M-1 Line 9 | D82: =D70+D71+D72+D73+D74+D75+D76+D77+D78+D79+D80+D81 | H82: =H70+H71+H72+H73+H74+H75+H76+H77+H78+H79+H80+H81 | J82: CRITICAL TIE-OUT.
A84: 49 | B84: K Line 12 | C84: Sec 179 Deduction | D84: 0 | E84: AJE-02 | G84: 0 | H84: =D84+IF(F84,F84,0)-IF(G84,G84,0) | I84: M-1 Line 7 | J84: [Enter adjustment notes here]
A85: 50 | B85: K Line 13a | C85: Charitable Contributions | D85: ='Client Books'!C115 | H85: ='Client Books'!C115 | J85: [Enter adjustment notes here]
A86: 51 | B86: K Line 13b | C86: Investment Interest Expense | D86: ='Client Books'!C120 | H86: ='Client Books'!C120 | J86: [Enter adjustment notes here]
A87: 52 | B87: K Line 14a | C87: Net Earnings from Self-Employment | H87: =H70+H73 | J87: Ordinary + GP for services. General partners.
A88: 53 | B88: K Line 18a | C88: Tax-Exempt Interest Income | D88: ='Client Books'!D62 | E88: AJE-21 | F88: 0 | G88: 0 | H88: =D88+IF(F88,F88,0)-IF(G88,G88,0) | I88: M-1 Line 6 | J88: [Enter adjustment notes here]
A89: 54 | B89: K Line 18c | C89: Nondeductible Expenses (total) | D89: =G51+G52+G53+G54+G55+G56+G57 | H89: =G51+G52+G53+G54+G55+G56+G57 | I89: M-1 Line 4 | J89: Sum of all nondeductible Adj(-) amounts. Decreases partner basis.
A90: 55 | B90: K Line 19a | C90: Distributions - Cash | D90: ='Client Books'!C52+'Client Books'!C53 | F90: 0 | G90: 0 | H90: =D90+IF(F90,F90,0)-IF(G90,G90,0) | J90: [Enter adjustment notes here]
A91: 56 | B91: K Line 20 | C91: Other Information (Sec 199A, etc.) | H91: 0 | J91: Sec 199A QBI, W-2 wages, UBIA. Enter codes in UltraTax.
A93: SCHEDULE M-1 — BOOK TO TAX RECONCILIATION
A94: 57 | B94: M-1 Line 1 | C94: Net Income (Loss) Per Books | D94: ='Client Books'!D57+'Client Books'!D59+'Client Books'!D60+'Client Books'!D61+'Client Books'!D62+'Client Books'!D63+'Client Books'!D64+'Client Books'!D65+'Client Books'!D66+'Client Books'!D67+'Client Books'!D68+'Client Books'!D69+'Client Books'!D70+'Client Books'!D71+'Client Books'!D72+'Client Books'!D73+'Client Books'!D74-'Client Books'!C58-('Client Books'!C76+'Client Books'!C77+'Client Books'!C78+'Client Books'!C79+'Client Books'!C80+'Client Books'!C81-'Client Books'!D82)-('Client Books'!C84+'Client Books'!C85+'Client Books'!C86+'Client Books'!C87+'Client Books'!C88+'Client Books'!C89+'Client Books'!C90+'Client Books'!C91+'Client Books'!C92+'Client Books'!C93+'Client Books'!C94+'Client Books'!C95+'Client Books'!C96+'Client Books'!C97+'Client Books'!C98+'Client Books'!C99+'Client Books'!C100+'Client Books'!C101+'Client Books'!C102+'Client Books'!C103+'Client Books'!C104+'Client Books'!C105+'Client Books'!C106+'Client Books'!C107+'Client Books'!C108+'Client Books'!C109+'Client Books'!C110+'Client Books'!C111+'Client Books'!C112+'Client Books'!C113+'Client Books'!C114+'Client Books'!C115+'Client Books'!C116+'Client Books'!C117+'Client Books'!C118+'Client Books'!C119+'Client Books'!C120+'Client Books'!C121+'Client Books'!C122+'Client Books'!C123+'Client Books'!C124+'Client Books'!C125+'Client Books'!C126+'Client Books'!C127+'Client Books'!C128)-('Client Books'!C130+'Client Books'!C131+'Client Books'!C132+'Client Books'!C133+'Client Books'!C134+'Client Books'!C135+'Client Books'!C136) | H94: ='Client Books'!D57+'Client Books'!D59+'Client Books'!D60+'Client Books'!D61+'Client Books'!D62+'Client Books'!D63+'Client Books'!D64+'Client Books'!D65+'Client Books'!D66+'Client Books'!D67+'Client Books'!D68+'Client Books'!D69+'Client Books'!D70+'Client Books'!D71+'Client Books'!D72+'Client Books'!D73+'Client Books'!D74-'Client Books'!C58-('Client Books'!C76+'Client Books'!C77+'Client Books'!C78+'Client Books'!C79+'Client Books'!C80+'Client Books'!C81-'Client Books'!D82)-('Client Books'!C84+'Client Books'!C85+'Client Books'!C86+'Client Books'!C87+'Client Books'!C88+'Client Books'!C89+'Client Books'!C90+'Client Books'!C91+'Client Books'!C92+'Client Books'!C93+'Client Books'!C94+'Client Books'!C95+'Client Books'!C96+'Client Books'!C97+'Client Books'!C98+'Client Books'!C99+'Client Books'!C100+'Client Books'!C101+'Client Books'!C102+'Client Books'!C103+'Client Books'!C104+'Client Books'!C105+'Client Books'!C106+'Client Books'!C107+'Client Books'!C108+'Client Books'!C109+'Client Books'!C110+'Client Books'!C111+'Client Books'!C112+'Client Books'!C113+'Client Books'!C114+'Client Books'!C115+'Client Books'!C116+'Client Books'!C117+'Client Books'!C118+'Client Books'!C119+'Client Books'!C120+'Client Books'!C121+'Client Books'!C122+'Client Books'!C123+'Client Books'!C124+'Client Books'!C125+'Client Books'!C126+'Client Books'!C127+'Client Books'!C128)-('Client Books'!C130+'Client Books'!C131+'Client Books'!C132+'Client Books'!C133+'Client Books'!C134+'Client Books'!C135+'Client Books'!C136) | J94: STARTING POINT. Must tie to Client Books P&L bottom line.
A95: 58 | B95: M-1 Line 2 | C95: Income on Sch K not recorded on books | D95: 0 | I95: Sec 1245 recapture | J95: [Enter adjustment notes here]
A96: 59 | B96: M-1 Line 3 | C96: Guaranteed Payments (K Line 4c) | D96: =H73 | H96: =H73 | J96: Auto-tied from K Line 4c.
A97: 62 | B97: M-1 Line 6 | C97: Income on books NOT on Sch K | J97: [Enter adjustment notes here]
A98: 63 | B98: M-1 Line 7 | C98: Deductions on return NOT on books | J98: [Enter adjustment notes here]
A99: 60 | B99: M-1 Line 4 | C99: Expenses on books NOT deducted on return (AUTO-BALANCED) | D99: =D82-D94-D95-D96+D97+D98 | H99: =H82-H94-H95-H96+H97+H98 | I99: Self-balancing | J99: AUTO-BALANCED FORMULA: backs into amount so M-1 Line 9 = K Total. Components: Sec 263A, Sec 267, bad debt reserve, 50% meals, entertainment, club dues, penalties, political, life ins, state tax, warranty/litigation reserves, partner health ins, cap improvement, amort diffs, charitable & inv interest. If wrong, check Lines 2, 6, 7.
A100: 61 | B100: M-1 Line 5 | C100: Total (Lines 1-4) | D100: =D94+D95+D96+D99 | H100: =H94+H95+H96+H99 | J100: Calculated.
A101: 64 | B101: M-1 Line 8 | C101: Total (Lines 6 + 7) | D101: =D97+D98 | H101: =H97+H98 | J101: Calculated.
A102: 65 | B102: M-1 Line 9 | C102: INCOME PER RETURN (Line 5 - Line 8) = K Lines 1-11 | D102: =D100-D101 | H102: =H100-H101 | J102: MUST EQUAL K Lines 1-11 total.
B103: CHECK | C103: M-1 Line 9 vs K Total (should be ZERO) | H103: =H102-H82 | J103: ZERO = BALANCED. If not, check M-1 Lines 2, 6, 7.
A105: SCHEDULE M-2 — PARTNERS' CAPITAL ACCOUNTS
A106: 66 | B106: M-2 Line 1 | C106: Balance at Beginning of Year | D106: =D18 | F106: 0 | G106: 0 | H106: =D106+IF(F106,F106,0)-IF(G106,G106,0) | J106: [Enter adjustment notes here]
A107: 67 | B107: M-2 Line 2 | C107: Capital Contributed During Year | D107: ='Client Books'!D54+'Client Books'!D55 | F107: 0 | G107: 0 | H107: =D107+IF(F107,F107,0)-IF(G107,G107,0) | J107: [Enter adjustment notes here]
A108: 68 | B108: M-2 Line 3 | C108: Net Income / Income Per Return | D108: =D94 | H108: =H102 | J108: Book col = M-1 Line 1 (book NI). Tax col = M-1 Line 9 (income per return). Use tax col for tax-basis L.
...

Sheet Sch K Workpaper
A1: SCHEDULE K — DETAILED WORKPAPER
A2: [ENTITY NAME] | EIN: [XX-XXXXXXX] | Tax Year Ended: [MM/DD/YYYY]
A4: # | B4: K Line | C4: Description | D4: Book Amount | E4: Tax Amount | F4: Adjustment | G4: IRC / Authority | H4: Source / WTB Ref
A5: INCOME (K Lines 1-11)
A6: 1 | B6: K Line 1 | C6: Ordinary Business Income (Loss) | D6: ='Working Trial Balance'!D70 | E6: ='Working Trial Balance'!H70 | F6: =E6-D6 | G6: Sec 702(a)(8) | H6: WTB Row 70 = P1 Line 22. QBI starting point (Sec 199A).
A7: 2 | B7: K Line 2 | C7: Net Rental RE Income (Form 8825) | D7: ='Working Trial Balance'!D71 | E7: ='Working Trial Balance'!H71 | F7: =E7-D7 | G7: Sec 469 / Sec 168 | H7: WTB Row 71. Income $96K - exp $63K = $33K book. Tax +$4.5K (rental MACRS > book depr). Passive activity.
A8: 3 | B8: K Line 3c | C8: Net Other Rental Income (Equipment) | D8: ='Working Trial Balance'!D72 | E8: ='Working Trial Balance'!H72 | F8: =E8-D8 | G8: Sec 469 | H8: WTB Row 72. Equipment rental $36K. Passive activity for all partners.
A9: 4 | B9: K Lines 4a-4c | C9: Guaranteed Payments (total) | D9: ='Working Trial Balance'!D73 | E9: ='Working Trial Balance'!H73 | F9: =E9-D9 | G9: Sec 707(c) | H9: WTB Row 73. Services 4a: $180K (A $90K + B $90K). Capital 4b: $12K. Total 4c: $192K.
A10: 5 | B10: K Line 5 | C10: Interest Income (portfolio) | D10: ='Working Trial Balance'!D74 | E10: ='Working Trial Balance'!H74 | F10: =E10-D10 | G10: Sec 702(a)(4) | H10: WTB Row 74. Bank $4.2K + corp bond $2.6K = $6.8K. Muni $3.8K excluded (K 18a).
A11: 6 | B11: K Lines 6a-6b | C11: Dividends (ordinary + qualified) | D11: ='Working Trial Balance'!D75 | E11: ='Working Trial Balance'!H75 | F11: =E11-D11 | G11: Sec 702(a)(5) | H11: WTB Row 75. Ordinary 6a: $5.5K + Qualified 6b: $8.2K = $13.7K total.
A12: 7 | B12: K Line 7 | C12: Royalties | D12: ='Working Trial Balance'!D76 | E12: ='Working Trial Balance'!H76 | F12: =E12-D12 | G12: Sec 702(a)(3) | H12: WTB Row 76. $12K.
A13: 8 | B13: K Line 8 | C13: Net Short-Term Capital Gain | D13: ='Working Trial Balance'!D77 | E13: ='Working Trial Balance'!H77 | F13: =E13-D13 | G13: Sec 702(a)(1) | H13: WTB Row 77. Stock sale $6.5K (held <1 yr).
A14: 9 | B14: K Line 9a | C14: Net Long-Term Capital Gain | D14: ='Working Trial Balance'!D78 | E14: ='Working Trial Balance'!H78 | F14: =E14-D14 | G14: Sec 702(a)(2) | H14: WTB Row 78. Stocks $18.5K + sub-partnership K-1 $4K = $22.5K.
A15: 10 | B15: K Line 9b | C15: Collectibles (28%) Gain | D15: ='Working Trial Balance'!D79 | E15: ='Working Trial Balance'!H79 | F15: =E15-D15 | G15: Sec 1(h)(5) | H15: WTB Row 79. Art sale $7.5K. 28% rate per Sec 1(h)(5).
A16: 11 | B16: K Line 10 | C16: Net Sec 1231 Gain (Loss) | D16: ='Working Trial Balance'!D80 | E16: ='Working Trial Balance'!H80 | F16: =E16-D16 | G16: Sec 1231 / 1245 | H16: WTB Row 80. Book $28K, less $12K Sec 1245 recapture to P1 L6 = $16K net 1231.
A17: 12 | B17: K Line 11 | C17: Other Income (Loss) | D17: ='Working Trial Balance'!D81 | E17: ='Working Trial Balance'!H81 | F17: =E17-D17 | G17: Sec 702(a)(7) | H17: WTB Row 81. None for this entity.
C18: K INCOME TOTAL (Lines 1-11) | D18: =SUM(D6:D17) | E18: =SUM(E6:E17) | F18: =E18-D18 | H18: WTB Row 82. Must = M-1 Line 9.
A19: SEPARATELY STATED DEDUCTIONS & OTHER ITEMS (K Lines 12-20)
A20: 13 | B20: K Line 12 | C20: Sec 179 Deduction | D20: ='Working Trial Balance'!D84 | E20: ='Working Trial Balance'!H84 | F20: =E20-D20 | G20: Sec 179 | H20: WTB Row 84. $35K on capitalized improvement. Each partner applies own limit.
A21: 14 | B21: K Line 13a | C21: Charitable Contributions | D21: ='Working Trial Balance'!D85 | E21: ='Working Trial Balance'!H85 | F21: =E21-D21 | G21: Sec 170 / 702(a)(4) | H21: WTB Row 85. $25K. Separately stated; partner applies AGI limits.
A22: 15 | B22: K Line 13b | C22: Investment Interest Expense | D22: ='Working Trial Balance'!D86 | E22: ='Working Trial Balance'!H86 | F22: =E22-D22 | G22: Sec 163(d) | H22: WTB Row 86. Margin acct interest $3.5K. Partner applies Sec 163(d) limit.
A23: 16 | B23: K Line 14a | C23: Net Earnings from Self-Employment | E23: ='Working Trial Balance'!H87 | G23: Sec 1402 | H23: WTB Row 87. = OBI + GP for services. General partners only. Not a separately stated item per se.
A24: 17 | B24: K Line 18a | C24: Tax-Exempt Interest Income | D24: ='Working Trial Balance'!D88 | E24: ='Working Trial Balance'!H88 | F24: =E24-D24 | G24: Sec 103 | H24: WTB Row 88. Muni bond $3.8K. Increases outside basis, not taxable. Flows to M-2 Line 4.
A25: 18 | B25: K Line 18c | C25: Nondeductible Expenses (total) | D25: ='Working Trial Balance'!D89 | E25: ='Working Trial Balance'!H89 | F25: =E25-D25 | G25: Various | H25: WTB Row 89. $58.6K total: meals 50% $16K, entertainment $8.5K, clubs $6K, penalties $4.5K, political $2K, life ins $9.6K, state tax $12K. Decreases basis. Flows to M-2 Line 7.
A26: 19 | B26: K Line 19a | C26: Distributions - Cash | D26: ='Working Trial Balance'!D90 | E26: ='Working Trial Balance'!H90 | F26: =E26-D26 | G26: Sec 731 | H26: WTB Row 90. A $110K + B $110K = $220K. Nontaxable to extent of basis. Flows to M-2 Line 6.
A27: 20 | B27: K Line 20 | C27: Other Information (Sec 199A QBI) | E27: ='Working Trial Balance'!H91 | G27: Sec 199A | H27: WTB Row 91. Report QBI, W-2 wages, UBIA of qualified property per partner.
A29: K-1 ALLOCATION (50/50 — 2 General Partners)
B30: K-1 Line | C30: Description | D30: K Total | E30: Partner A (50%) | F30: Partner B (50%) | H30: Source
B31: K-1 Line 1 | C31: Ordinary Business Income | D31: ='Working Trial Balance'!H70 | E31: =D31*0.5 | F31: =D31*0.5 | H31: WTB R70
B32: K-1 Line 2 | C32: Net Rental RE Income | D32: ='Working Trial Balance'!H71 | E32: =D32*0.5 | F32: =D32*0.5 | H32: WTB R71
B33: K-1 Line 3 | C33: Other Rental Income | D33: ='Working Trial Balance'!H72 | E33: =D33*0.5 | F33: =D33*0.5 | H33: WTB R72
B34: K-1 Line 4a | C34: GP for Services | D34: ='Working Trial Balance'!H73 | E34: =D34*0.5 | F34: =D34*0.5 | H34: WTB R73
B35: K-1 Line 5 | C35: Interest Income | D35: ='Working Trial Balance'!H74 | E35: =D35*0.5 | F35: =D35*0.5 | H35: WTB R74
B36: K-1 Line 6a | C36: Ordinary Dividends | D36: ='Working Trial Balance'!H75 | E36: =D36*0.5 | F36: =D36*0.5 | H36: WTB R75
B37: K-1 Line 7 | C37: Royalties | D37: ='Working Trial Balance'!H76 | E37: =D37*0.5 | F37: =D37*0.5 | H37: WTB R76
B38: K-1 Line 8 | C38: STCG | D38: ='Working Trial Balance'!H77 | E38: =D38*0.5 | F38: =D38*0.5 | H38: WTB R77
B39: K-1 Line 9a | C39: LTCG | D39: ='Working Trial Balance'!H78 | E39: =D39*0.5 | F39: =D39*0.5 | H39: WTB R78
B40: K-1 Line 10 | C40: Sec 1231 Gain | D40: ='Working Trial Balance'!H80 | E40: =D40*0.5 | F40: =D40*0.5 | H40: WTB R80
B41: K-1 Line 12 | C41: Sec 179 | D41: ='Working Trial Balance'!H84 | E41: =D41*0.5 | F41: =D41*0.5 | H41: WTB R84
B42: K-1 Line 13a | C42: Charitable | D42: ='Working Trial Balance'!H85 | E42: =D42*0.5 | F42: =D42*0.5 | H42: WTB R85
B43: K-1 Line 14a | C43: SE Earnings | D43: ='Working Trial Balance'!H87 | E43: =D43*0.5 | F43: =D43*0.5 | H43: WTB R87
B44: K-1 Line 18a | C44: Tax-Exempt | D44: ='Working Trial Balance'!H88 | E44: =D44*0.5 | F44: =D44*0.5 | H44: WTB R88
B45: K-1 Line 18c | C45: Nondeductible | D45: ='Working Trial Balance'!H89 | E45: =D45*0.5 | F45: =D45*0.5 | H45: WTB R89
B46: K-1 Line 19a | C46: Distributions | D46: ='Working Trial Balance'!H90 | E46: =D46*0.5 | F46: =D46*0.5 | H46: WTB R90

Sheet M-1 Workpaper
A1: SCHEDULE M-1 — BOOK-TO-TAX RECONCILIATION WORKPAPER
A2: [ENTITY NAME] | EIN: [XX-XXXXXXX] | Tax Year Ended: [MM/DD/YYYY]
A4: # | B4: M-1 Line | C4: Description | D4: Book Amount | E4: Tax Amount | F4: Difference | G4: Perm / Temp | H4: IRC / Authority | I4: Detail / WTB Ref
A5: M-1 RECONCILIATION — FORM LINES
A6: 1 | B6: M-1 Line 1 | C6: Net Income (Loss) Per Books | D6: ='Working Trial Balance'!D94 | E6: ='Working Trial Balance'!H94 | F6: =E6-D6 | I6: WTB Row 94. Computed from all Client Books revenue less all expenses. Starting point for reconciliation.
A7: 2 | B7: M-1 Line 2 | C7: Income on K not on books | D7: ='Working Trial Balance'!D95 | E7: ='Working Trial Balance'!H95 | F7: =E7-D7 | H7: Sec 1245 | I7: WTB Row 95. Sec 1245 recapture $12K: tax depreciation exceeded book on disposed equipment, creating ordinary gain on return but not on books.
A8: 3 | B8: M-1 Line 3 | C8: Guaranteed Payments | D8: ='Working Trial Balance'!D96 | E8: ='Working Trial Balance'!H96 | F8: =E8-D8 | H8: Sec 707(c) | I8: WTB Row 96. $192K. Already deducted on books as expense. Added back here per M-1 format (deducted on books, also flows to K 4c).
A9: 4 | B9: M-1 Line 4 | C9: Expenses on books NOT deducted (auto-balanced) | D9: ='Working Trial Balance'!D99 | E9: ='Working Trial Balance'!H99 | F9: =E9-D9 | H9: Various | I9: WTB Row 99. AUTO-BALANCED formula. See detail breakdown below.
A10: 5 | B10: M-1 Line 5 | C10: Total (Lines 1 + 2 + 3 + 4) | D10: ='Working Trial Balance'!D100 | E10: ='Working Trial Balance'!H100 | F10: =E10-D10 | I10: WTB Row 100.
A11: 6 | B11: M-1 Line 6 | C11: Income on books NOT on K | D11: ='Working Trial Balance'!D97 | E11: ='Working Trial Balance'!H97 | F11: =E11-D11 | H11: Sec 103 / 108 | I11: WTB Row 97. Tax-exempt muni interest $3.8K (Sec 103) + COD income excluded $15K (Sec 108 insolvency) = $18.8K.
A12: 7 | B12: M-1 Line 7 | C12: Deductions on return NOT on books | D12: ='Working Trial Balance'!D98 | E12: ='Working Trial Balance'!H98 | F12: =E12-D12 | H12: Sec 168/179 | I12: WTB Row 98. MACRS > book depr $67K + Sec 179 $35K + rental MACRS > book $4.5K = $106.5K.
A13: 8 | B13: M-1 Line 8 | C13: Total (Lines 6 + 7) | D13: ='Working Trial Balance'!D101 | E13: ='Working Trial Balance'!H101 | F13: =E13-D13 | I13: WTB Row 101.
A14: 9 | B14: M-1 Line 9 | C14: INCOME PER RETURN (Line 5 - Line 8) | D14: ='Working Trial Balance'!D102 | E14: ='Working Trial Balance'!H102 | F14: =E14-D14 | I14: WTB Row 102. Must = K Lines 1-11 total.
B15: CHECK | C15: M-1 Line 9 vs K Total | E15: ='Working Trial Balance'!H103 | I15: WTB Row 103. ZERO = balanced.
A17: M-1 LINE 4 — DETAILED BREAKDOWN OF EXPENSES ON BOOKS NOT DEDUCTED ON RETURN
B18: Adj # | C18: Description | D18: Book Expense | E18: Tax Deduction | F18: Disallowed | G18: Perm / Temp | H18: IRC / Authority | I18: WTB Ref / Explanation
B19: 4a | C19: Sec 263A UNICAP Adjustment | D19: 0 | F19: -8500 | G19: Temp | H19: Sec 263A | I19: WTB R8. Inventory capitalization. Additional $8.5K added to inventory/COGS basis. Reverses when inventory sold.
B20: 4b | C20: Sec 267 Related-Party Accrued Bonus | E20: 0 | F20: 35000 | G20: Temp | H20: Sec 267(a)(2) | I20: WTB R37 Adj(-). $35K accrued bonus to related party unpaid >2.5 months after YE. Deductible when paid.
B21: 4c | C21: Bad Debt Reserve (not specific charge-off) | E21: 0 | F21: 22000 | G21: Temp | H21: Sec 166 | I21: WTB R40 Adj(-). Book reserve method $22K. Tax requires specific charge-off; actual write-offs = $0.
B22: 4d | C22: Meals — 50% Disallowance | F22: 16000 | G22: Perm | H22: Sec 274(n) | I22: WTB R51. Book $32K, tax 50% = $16K. Nondeductible $16K to K 18c.
B23: 4e | C23: Entertainment — 100% Disallowed | E23: 0 | F23: 8500 | G23: Perm | H23: Sec 274(a)(1) | I23: WTB R52. $8.5K 100% nondeductible post-TCJA. To K 18c.
B24: 4f | C24: Club Dues — 100% Disallowed | E24: 0 | F24: 6000 | G24: Perm | H24: Sec 274(a)(3) | I24: WTB R53. Country club $6K. To K 18c.
B25: 4g | C25: Penalties & Fines | E25: 0 | F25: 4500 | G25: Perm | H25: Sec 162(f) | I25: WTB R54. $4.5K nondeductible. To K 18c.
B26: 4h | C26: Political Contributions | E26: 0 | F26: 2000 | G26: Perm | H26: Sec 162(e) | I26: WTB R55. $2K nondeductible. To K 18c.
B27: 4i | C27: Life Insurance (partnership beneficiary) | E27: 0 | F27: 9600 | G27: Perm | H27: Sec 264(a)(1) | I27: WTB R56. Key person $9.6K. Partnership is beneficiary. To K 18c.
B28: 4j | C28: State Income / Franchise Tax | E28: 0 | F28: 12000 | G28: Perm | H28: Sec 275(a)(4) | I28: WTB R57. $12K not deductible on federal partnership return. To K 18c.
B29: 4k | C29: Warranty Reserve (economic performance) | E29: 0 | F29: 15000 | G29: Temp | H29: Sec 461(h) | I29: WTB R58. $15K accrued. Not deductible until economic performance (payment/fix). Temporary diff.
B30: 4l | C30: Litigation Reserve (economic performance) | E30: 0 | F30: 40000 | G30: Temp | H30: Sec 461(h) | I30: WTB R59. $40K accrued. Not deductible until settlement/judgment. Temporary diff.
B31: 4m | C31: Partner Health Insurance (to K-1) | E31: 0 | F31: 28000 | G31: Perm* | H31: Sec 162(l) | I31: WTB R60. A $14K + B $14K. Not P1 deduction; flows to K-1 Line 13 Code M. *Deductible at partner level.
B32: 4n | C32: Capital Improvement (reclassed to Sec 179) | E32: 0 | F32: 35000 | G32: N/A | H32: Sec 179 / 263 | I32: WTB R61. Book expensed $35K. Tax: capitalize and elect Sec 179 on K Line 12. Net neutral on M-1.
B33: 4o | C33: Goodwill Amort Difference (10yr vs 15yr) | F33: 10000 | G33: Temp | H33: Sec 197 | I33: WTB R62. Book 10yr = $30K. Tax Sec 197 15yr = $20K. $10K timing difference.
B34: 4p | C34: Patent Amort Difference (10yr vs 15yr) | F34: 2500 | G34: Temp | H34: Sec 197 | I34: WTB R63. Book 10yr = $7.5K. Tax Sec 197 15yr = $5K. $2.5K timing difference.
B35: 4q | C35: Charitable Contributions (separately stated) | E35: 0 | F35: 25000 | G35: N/A | H35: Sec 170 | I35: WTB R64. $25K reclassed from P1 to K 13a. Not a disallowance; flows to partner for AGI limit.
B36: 4r | C36: Investment Interest (separately stated) | E36: 0 | F36: 3500 | G36: N/A | H36: Sec 163(d) | I36: WTB R65. $3.5K reclassed from P1 to K 13b. Partner applies Sec 163(d) limit.
C37: TOTAL M-1 LINE 4 COMPONENTS | D37: =SUM(D19:D36) | E37: =SUM(E19:E36) | F37: =SUM(F19:F36) | I37: Should approximate M-1 Line 4 tax amount.
A39: PERMANENT vs TEMPORARY DIFFERENCE SUMMARY
C40: Category | D40: Amount
C41: Meals 50%
C42: Entertainment
C43: Club Dues
C44: Penalties
C45: Political
C46: Life Ins
C47: State Tax
C48: Total Permanent | D48: =SUM(D41:D47)
C50: Sec 263A UNICAP
C51: Sec 267 Bonus
C52: Bad Debt Reserve
C53: Warranty Reserve
C54: Litigation Reserve
C55: Goodwill Amort
C56: Patent Amort
C57: Total Temporary | D57: =SUM(D50:D56)

Sheet M-2 Workpaper
A1: SCHEDULE M-2 — PARTNERS' CAPITAL ACCOUNT RECONCILIATION WORKPAPER
A2: [ENTITY NAME] | EIN: [XX-XXXXXXX] | Tax Year Ended: [MM/DD/YYYY]
A4: # | B4: M-2 Line | C4: Description | D4: Book Basis | E4: Tax Basis | F4: IRC / Authority | G4: Detail / WTB Ref
A5: M-2 CAPITAL ACCOUNT RECONCILIATION
A6: 1 | B6: M-2 Line 1 | C6: Balance at Beginning of Year | D6: ='Working Trial Balance'!D106 | E6: ='Working Trial Balance'!H106 | F6: Sec 704(b) | G6: PRIOR YEAR: MANUALLY ENTER from prior year return. WTB Row 106. Book = $1M (A $500K + B $500K). Tax beg cap should come from PY M-2 Line 9 / PY L col (d).
A7: 2 | B7: M-2 Line 2 | C7: Capital Contributed During Year | D7: ='Working Trial Balance'!D107 | E7: ='Working Trial Balance'!H107 | F7: Sec 721/722 | G7: WTB Row 107. A $25K + B $25K = $50K. Cash contributions. Sec 721: no gain recognized on contribution. Verify bank records.
A8: 3 | B8: M-2 Line 3 | C8: Net Income / Income Per Return | D8: ='Working Trial Balance'!D108 | E8: ='Working Trial Balance'!H108 | F8: Sec 704(a) | G8: WTB Row 108. Book = M-1 Line 1 ($674K). Tax = M-1 Line 9 / K total ($1,077K). Difference = all M-1 adjustments.
A9: 4 | B9: M-2 Line 4 | C9: Other Increases (tax-exempt income) | D9: ='Working Trial Balance'!D109 | E9: ='Working Trial Balance'!H109 | F9: Sec 103 / 705(a)(1)(B) | G9: WTB Row 109. Tax: K Line 18a muni interest $3.8K. Increases outside basis per Sec 705(a)(1)(B). Book: $0 (already in book NI).
A10: 5 | B10: M-2 Line 5 | C10: TOTAL (Lines 1 through 4) | D10: ='Working Trial Balance'!D110 | E10: ='Working Trial Balance'!H110 | G10: WTB Row 110.
A11: 6 | B11: M-2 Line 6 | C11: Distributions (Cash and Property) | D11: ='Working Trial Balance'!D111 | E11: ='Working Trial Balance'!H111 | F11: Sec 731 | G11: WTB Row 111. $220K. Must = K Lines 19a-19b. Nontaxable to extent of basis. If excess = gain under Sec 731(a)(1).
A12: 7 | B12: M-2 Line 7 | C12: Other Decreases (nondeductible expenses) | D12: ='Working Trial Balance'!D112 | E12: ='Working Trial Balance'!H112 | F12: Sec 705(a)(2)(B) | G12: WTB Row 112. Tax: K Line 18c = $58.6K total nondeductible. Decreases outside basis per Sec 705(a)(2)(B). Book: $0 (already in book NI).
A13: 8 | B13: M-2 Line 8 | C13: Total Decreases (Lines 6 + 7) | D13: ='Working Trial Balance'!D113 | E13: ='Working Trial Balance'!H113 | G13: WTB Row 113.
A14: 9 | B14: M-2 Line 9 | C14: BALANCE AT END OF YEAR (Line 5 - Line 8) | D14: ='Working Trial Balance'!D114 | E14: ='Working Trial Balance'!H114 | F14: Sec 704(b) | G14: WTB Row 114. Must = L Line 22 and sum of K-1 ending capital accounts.
B16: CHECK | C16: M-2 Line 9 vs L Line 22 (should match) | E16: ='Working Trial Balance'!H114-'Working Trial Balance'!H117 | G16: Should be ZERO. L Line 22 is forced = M-2 Line 9 by formula.
A18: PER-PARTNER CAPITAL ACCOUNT DETAIL (50/50)
C19: Item | D19: Partner A | E19: Partner B
C20: Beginning Capital | D20: ='Working Trial Balance'!H106/2 | E20: ='Working Trial Balance'!H106/2 | G20: PY return
C21: Contributions | D21: ='Working Trial Balance'!H107/2 | E21: ='Working Trial Balance'!H107/2 | G21: Bank records
C22: Share of Income (per return) | D22: ='Working Trial Balance'!H108/2 | E22: ='Working Trial Balance'!H108/2 | G22: K-1 total income
C23: Tax-Exempt Income | D23: ='Working Trial Balance'!H109/2 | E23: ='Working Trial Balance'!H109/2 | G23: K 18a
C24: Distributions | D24: =0-'Working Trial Balance'!H111/2 | E24: =0-'Working Trial Balance'!H111/2 | G24: K 19a
C25: Nondeductible Expenses | D25: =0-'Working Trial Balance'!H112/2 | E25: =0-'Working Trial Balance'!H112/2 | G25: K 18c
C26: Ending Tax Capital (per K-1) | D26: =SUM(D20:D25) | E26: =SUM(E20:E25)
C27: Combined (A + B) = M-2 Line 9? | D27: =D26+E26 | E27: ='Working Trial Balance'!H114
C28: Difference (should be ZERO) | D28: =D27-E27

Sheet M-3 Workpaper
A1: SCHEDULE M-3 (FORM 1065) — NET INCOME RECONCILIATION WORKPAPER
A2: [ENTITY NAME] | EIN: [XX-XXXXXXX] | Tax Year Ended: [MM/DD/YYYY]
A3: Gold = Linked to WTB | Blue font = Manual input | Green = Check/auto | Red = Prior year (manually enter)
A5: PART I — FINANCIAL INFORMATION AND NET INCOME (LOSS) RECONCILIATION
A6: # | B6: M-3 Ref | C6: Description | D6: Amount | H6: Authority | I6: Detail / WTB Ref
A7: 1 | B7: Pt I L1 | C7: Net Income (Loss) per Income Statement | D7: ='Working Trial Balance'!D94 | I7: WTB Row 94. Book net income $674K. Starting point.
A8: 2 | B8: Pt I L2 | C8: Net Income (Loss) of Nonincludible Entities | D8: 0 | I8: None.
A9: 4 | B9: Pt I L4a | C9: Income from Equity Method Foreign Corps | D9: 0 | H9: Sec 902/960 | I9: None.
A10: 5 | B10: Pt I L4b | C10: Income from Equity Method US Corps | D10: 0 | I10: None.
A11: 6 | B11: Pt I L5 | C11: Income from Entity Not Included on Return | D11: 0 | I11: None.
A12: 7 | B12: Pt I L6 | C12: Income from Entity on Return Not on Books | D12: 0 | I12: None.
A13: 8 | B13: Pt I L7 | C13: Income (Loss) of Other Includible Entities | D13: 0 | I13: None.
A14: 9 | B14: Pt I L8 | C14: Adjustment to Reconcile | D14: 0 | I14: Enter if reclasses needed. Usually $0.
A15: 3 | B15: Pt I L3 | C15: Net Income per IS of Includible Entities (L1 - L2) | D15: =D7-D8 | I15: Should = book NI $674K.
A16: 10 | B16: Pt I L9 | C16: Net Income per IS After Adjustments | D16: =D15+SUM(D9:D14) | I16: Flows as col(a) starting point to Part II.
A17: 11 | B17: Pt I L11 | C17: Income Per Return (K Lines 1-11 total) | G17: ='Working Trial Balance'!H82 | I17: WTB Row 82. $1,077,300.
A19: PART II — INCOME AND GAIN ITEMS
A20: # | B20: M-3 Ref | C20: Description | D20: (a) Book Amt | E20: (b) Temp Diff | F20: (c) Perm Diff | G20: (d) Tax Amt | H20: IRC / Authority | I20: Detail / WTB Ref
A21: 1 | B21: Pt II L1 | C21: Net Income (Loss) Per Income Statement | D21: ='Working Trial Balance'!D94 | E21: 0 | F21: 0 | G21: =D21+E21+F21 | I21: Pt I L9 = $674K. All subsequent lines have col(a)=0; diffs go in (b) and (c).
A22: 2 | B22: Pt II L2 | C22: Sec 1245 Ordinary Income Recapture (M-1 L2) | D22: 0 | E22: ='Working Trial Balance'!H95 | F22: 0 | G22: =D22+E22+F22 | H22: Sec 1245 | I22: WTB R95. $12K recapture on disposed equipment. On K, not on books. Temp.
A23: 3 | B23: Pt II L3 | C23: Guaranteed Payments Reclass (M-1 L3) | D23: 0 | E23: ='Working Trial Balance'!H96 | F23: 0 | G23: =D23+E23+F23 | H23: Sec 707(c) | I23: WTB R96. $192K. Deducted in book NI; reclassed to K Line 4c on return. Temp reclass.
A24: 4 | B24: Pt II L4 | C24: Tax-Exempt Interest — On Books, Not on K (M-1 L6) | D24: 0 | E24: 0 | G24: =D24+E24+F24 | H24: Sec 103 | I24: Muni $3.8K in book NI; excluded from taxable. Perm. Flows to K 18a.
A25: 5 | B25: Pt II L5 | C25: COD Income Excluded Sec 108 — On Books, Not on K (M-1 L6) | D25: 0 | E25: 0 | G25: =D25+E25+F25 | H25: Sec 108 | I25: $15K excluded under insolvency. In book NI; not on return. Perm.
C26: PART II TOTAL — INCOME ITEMS | D26: =SUM(D21:D25) | E26: =SUM(E21:E25) | F26: =SUM(F21:F25) | G26: =SUM(G21:G25)
A28: PART III — EXPENSE / DEDUCTION ITEMS
A29: # | B29: M-3 Ref | C29: Description | D29: (a) Book Amt | E29: (b) Temp Diff | F29: (c) Perm Diff | G29: (d) Tax Amt | H29: IRC / Authority | I29: Detail / WTB Ref
A30: 1 | B30: Pt III L1 | C30: Sec 263A UNICAP Adjustment | D30: 0 | F30: 0 | G30: =D30+E30+F30 | H30: Sec 263A | I30: M-1 4a. $8.5K additional COGS capitalization on tax. Temp (reverses when sold).
A31: 2 | B31: Pt III L2 | C31: Related-Party Accrued Comp (Sec 267) | D31: 0 | F31: 0 | G31: =D31+E31+F31 | H31: Sec 267(a)(2) | I31: M-1 4b. $35K accrued on books; deferred on tax until paid. Temp.
A32: 3 | B32: Pt III L3 | C32: Bad Debt — Reserve vs Specific Write-Off | D32: 0 | F32: 0 | G32: =D32+E32+F32 | H32: Sec 166 | I32: M-1 4c. Book reserve $22K; tax specific charge-off $0. Temp.
A33: 4 | B33: Pt III L4 | C33: Meals — 50% Limitation | D33: 0 | E33: 0 | G33: =D33+E33+F33 | H33: Sec 274(n) | I33: M-1 4d. $32K book, $16K tax. $16K perm disallowed to K 18c.
A34: 5 | B34: Pt III L5 | C34: Entertainment — 100% Disallowed | D34: 0 | E34: 0 | G34: =D34+E34+F34 | H34: Sec 274(a)(1) | I34: M-1 4e. Post-TCJA fully nondeductible. Perm to K 18c.
A35: 6 | B35: Pt III L6 | C35: Club Dues — 100% Disallowed | D35: 0 | E35: 0 | G35: =D35+E35+F35 | H35: Sec 274(a)(3) | I35: M-1 4f. Country club $6K. Perm to K 18c.
A36: 7 | B36: Pt III L7 | C36: Penalties and Fines | D36: 0 | E36: 0 | G36: =D36+E36+F36 | H36: Sec 162(f) | I36: M-1 4g. $4.5K. Perm to K 18c.
A37: 8 | B37: Pt III L8 | C37: Political Contributions | D37: 0 | E37: 0 | G37: =D37+E37+F37 | H37: Sec 162(e) | I37: M-1 4h. $2K. Perm to K 18c.
A38: 9 | B38: Pt III L9 | C38: Key Person Life Insurance | D38: 0 | E38: 0 | G38: =D38+E38+F38 | H38: Sec 264(a)(1) | I38: M-1 4i. $9.6K. Partnership beneficiary. Perm to K 18c.
A39: 10 | B39: Pt III L10 | C39: State Income / Franchise Tax | D39: 0 | E39: 0 | G39: =D39+E39+F39 | H39: Sec 275(a)(4) | I39: M-1 4j. $12K. Not deductible on federal return. Perm to K 18c.
A40: 11 | B40: Pt III L11 | C40: Warranty Reserve | D40: 0 | F40: 0 | G40: =D40+E40+F40 | H40: Sec 461(h) | I40: M-1 4k. $15K. Accrued on books; not deductible until economic performance. Temp.
A41: 12 | B41: Pt III L12 | C41: Litigation Reserve | D41: 0 | F41: 0 | G41: =D41+E41+F41 | H41: Sec 461(h) | I41: M-1 4l. $40K. Accrued on books; not deductible until settlement. Temp.
A42: 13 | B42: Pt III L13 | C42: Partner Health Insurance (reclass to K-1) | D42: 0 | E42: 0 | G42: =D42+E42+F42 | H42: Sec 162(l) | I42: M-1 4m. $28K. Not P1 deduction; to K-1 13 Code M. Perm at entity level.
A43: 14 | B43: Pt III L14 | C43: Capital Improvement (Sec 179 reclass) | D43: 0 | F43: 0 | G43: =D43+E43+F43 | H43: Sec 179/263 | I43: M-1 4n. Book expensed $35K. Tax: capitalize + Sec 179 (K L12). Temp/reclass.
A44: 15 | B44: Pt III L15 | C44: Goodwill Amort (10yr book vs 15yr Sec 197) | D44: 0 | F44: 0 | G44: =D44+E44+F44 | H44: Sec 197 | I44: M-1 4o. Book $30K, Tax $20K. $10K temp timing diff.
A45: 16 | B45: Pt III L16 | C45: Patent Amort (10yr book vs 15yr Sec 197) | D45: 0 | F45: 0 | G45: =D45+E45+F45 | H45: Sec 197 | I45: M-1 4p. Book $7.5K, Tax $5K. $2.5K temp timing diff.
A46: 17 | B46: Pt III L17 | C46: Charitable Contributions (reclass to K 13a) | D46: 0 | E46: 0 | G46: =D46+E46+F46 | H46: Sec 170 | I46: M-1 4q. $25K reclassed P1 to K 13a. Partner applies AGI limit. Reclass/perm.
A47: 18 | B47: Pt III L18 | C47: Investment Interest (reclass to K 13b) | D47: 0 | E47: 0 | G47: =D47+E47+F47 | H47: Sec 163(d) | I47: M-1 4r. $3.5K reclassed P1 to K 13b. Reclass/perm.
A48: 19 | B48: Pt III L19 | C48: Depreciation — Tax MACRS Exceeds Book | D48: 0 | F48: 0 | G48: =D48+E48+F48 | H48: Sec 168 | I48: M-1 L7. MACRS > book depr $67K. On return, not on books. Temp.
A49: 20 | B49: Pt III L20 | C49: Rental Depreciation — Tax MACRS Exceeds Book | D49: 0 | F49: 0 | G49: =D49+E49+F49 | H49: Sec 168 | I49: M-1 L7. Rental MACRS > book $4.5K. On return, not on books. Temp.
A50: 21 | B50: Pt III L21 | C50: Sec 179 Expense (on return, not on books) | D50: 0 | F50: 0 | G50: =D50+E50+F50 | H50: Sec 179 | I50: M-1 L7. $35K deducted K L12. Not on books. Temp. Offset by L14 reclass.
A51: 22 | B51: Pt III L22 | C51: Other / Auto-Balance (M-1 L4 residual) | D51: 0 | E51: ='Working Trial Balance'!H82-G26-SUM(G30:G50) | F51: 0 | G51: =D51+E51+F51 | H51: Various | I51: Auto-balanced from M-1 L4 residual. Captures interaction effects between OBI adjustments and separately stated items. Review for material items.
C52: PART III TOTAL — EXPENSE/DEDUCTION ITEMS | D52: =SUM(D30:D51) | E52: =SUM(E30:E51) | F52: =SUM(F30:F51) | G52: =SUM(G30:G51)
A54: RECONCILIATION TOTALS AND TIE-OUTS
C55: Description | D55: (a) Book | E55: (b) Temp | F55: (c) Perm | G55: (d) Tax | I55: Detail
B56: Net | C56: COMBINED TOTAL (Part II + Part III) | D56: =D26+D52 | E56: =E26+E52 | F56: =F26+F52 | G56: =G26+G52 | I56: Col(a)=$674K=Book NI. Col(d)=$1,077,300=K total.
B57: CHECK 1 | C57: Book Total vs M-1 Line 1 (should be ZERO) | D57: =D56-'Working Trial Balance'!D94 | I57: Col(a) total must = book NI ($674K).
B58: CHECK 2 | C58: Tax Total vs K Lines 1-11 (should be ZERO) | G58: =G56-'Working Trial Balance'!H82 | I58: Col(d) total must = K total ($1,077,300).
B59: CHECK 3 | C59: a + b + c = d Proof (should be ZERO) | G59: =(D56+E56+F56)-G56 | I59: Temp+Perm must bridge book to tax exactly.
A61: DIFFERENCE CLASSIFICATION SUMMARY
C62: Category | D62: Amount | H62: IRC
B63: PERMANENT | C63: Meals 50% disallowed | H63: Sec 274(n)
C64: Entertainment 100% | H64: Sec 274(a)(1)
C65: Club Dues 100% | H65: Sec 274(a)(3)
C66: Penalties & Fines | H66: Sec 162(f)
C67: Political Contributions | H67: Sec 162(e)
C68: Life Insurance Premiums | H68: Sec 264(a)(1)
C69: State Income/Franchise Tax | H69: Sec 275(a)(4)
C70: Tax-Exempt Interest (excluded) | H70: Sec 103
C71: COD Excluded (Sec 108) | H71: Sec 108
C72: Partner Health Ins (reclass) | H72: Sec 162(l)
C73: Charitable (reclass to K) | H73: Sec 170
C74: Investment Interest (reclass to K) | H74: Sec 163(d)
C75: Total Permanent | D75: =SUM(D62:D73)
B77: TEMPORARY | C77: Sec 263A UNICAP | H77: Sec 263A
C78: Sec 267 Related-Party Bonus | H78: Sec 267(a)(2)
C79: Bad Debt Reserve | H79: Sec 166
C80: Warranty Reserve | H80: Sec 461(h)
C81: Litigation Reserve | H81: Sec 461(h)
C82: Capital Improvement / Sec 179 reclass | H82: Sec 179/263
C83: Goodwill Amort Diff | H83: Sec 197
C84: Patent Amort Diff | H84: Sec 197
C85: Depreciation MACRS > Book | H85: Sec 168
C86: Rental MACRS > Book | H86: Sec 168
C87: Sec 179 Deduction (not on books) | H87: Sec 179
C88: Sec 1245 Recapture | H88: Sec 1245
C89: Guaranteed Payments Reclass | H89: Sec 707(c)
C90: Total Temporary | D90: =SUM(D76:D88)
C92: Total Temp + Perm Differences | D92: =E56+F56
C93: Tax Income - Book Income | D93: ='Working Trial Balance'!H82-'Working Trial Balance'!D94
C94: DIFFERENCE (should be ZERO) | D94: =D92-D93
A96: NOTE: Schedule M-3 required if: (a) total assets >= $10M, (b) 250+ K-1s, or (c) voluntary election. This workpaper serves as a detailed book-to-tax bridge in M-3 format for any client. Hide rows for items that don't apply.

Sheet Adjustments Workpaper
A1: [ENTITY NAME] — BOOK-TO-TAX ADJUSTMENTS WORKPAPER
A2: EIN: [XX-XXXXXXX] | Tax Year Ended: [MM/DD/YYYY] | Form 1065
A3: LEGEND: Blue font = Manual entry from PBC / depr schedule | Gold fill = Linked to WTB | Green = Auto-calculated | Red = Prior year / manually enter
A5: SECTION A — BOOK-TO-TAX ADJUSTMENTS CHECKLIST
A6: Review each category below. Enter book amounts and adjustments. Tax amount auto-calculates. Hide rows that do not apply to this client.
A8: AJE# | B8: Category | C8: Description / What to Look For | D8: IRC Section | E8: WTB Row | F8: Book Amount | G8: Adjustment (+/-) | H8: Tax Amount | I8: Perm / Temp | J8: M-1 Line | K8: K Line | L8: Preparer Notes / Status
A9: INCOME ADJUSTMENTS
A10: AJE-01 | B10: Depreciation — MACRS vs Book | C10: Compare book depreciation to tax MACRS. Excess MACRS over book increases tax deduction. Get from depreciation schedule. | D10: §167/168 | E10: 44 (P1 L16a) | F10: ='Working Trial Balance'!D44 | G10: ='Working Trial Balance'!F44 | H10: ='Working Trial Balance'!H44 | I10: Temp | J10: 4a / 7 | L10: Enter MACRS from tax depr schedule. Verify assets placed-in-service dates.
A11: AJE-02 | B11: Sec 179 Expense Election | C11: Capital items expensed under Sec 179. Reclassify book expense to asset, then elect Sec 179 on K-1. | D11: §179 | E11: 61 (sub-line) / 84 (K L12) | F11: ='Working Trial Balance'!D61 | G11: =-'Working Trial Balance'!G61 | H11: ='Working Trial Balance'!H61 | I11: Temp | J11: 7 | K11: K 12 | L11: Book expensed $35K. Tax: remove from P1 deductions, elect Sec 179 on K Line 12. Partner applies own limit.
A12: AJE-03 | B12: Sec 1245 Ordinary Recapture | C12: On asset dispositions, recapture gain attributable to depreciation as ordinary income (Form 4797). | D12: §1245 | E12: 33 (P1 L6) | F12: ='Working Trial Balance'!D33 | G12: ='Working Trial Balance'!F33 | H12: ='Working Trial Balance'!H33 | I12: Temp | J12: 2 | L12: Analyze each disposition. Recapture = lesser of gain or total depr taken.
A13: AJE-04 | B13: Sec 1231 Gain Reclassification | C13: Remaining gain on business property held >1yr after Sec 1245 recapture. Separately stated on K. | D13: §1231 | E13: 80 (K L10) | F13: ='Working Trial Balance'!D80 | G13: =-'Working Trial Balance'!G80 | H13: ='Working Trial Balance'!H80 | I13: N/A | K13: K 10 | L13: Check 5-yr lookback for prior Sec 1231 losses.
A14: AJE-05 | B14: COD Income Exclusion (Insolvency) | C14: Cancellation of debt income excluded under Sec 108 if partnership was insolvent at time of discharge. | D14: §108 | E14: 34 (P1 L7) | F14: ='Working Trial Balance'!D34 | G14: =-'Working Trial Balance'!G34 | H14: ='Working Trial Balance'!H34 | I14: Perm | J14: 6 | L14: File Form 982. Reduce tax attributes. Get insolvency documentation.
A15: AJE-06 | B15: Rental Real Estate — Depr Diff | C15: Rental property depreciation difference. Tax depreciation on rental assets vs book. | D15: §167/168 | E15: 71 (K L2) | F15: ='Working Trial Balance'!D71 | G15: ='Working Trial Balance'!F71 | H15: ='Working Trial Balance'!H71 | I15: Temp | J15: 7 | K15: K 2 | L15: Separate depreciation schedule for rental property.
A16: DEDUCTION ADJUSTMENTS — TIMING (TEMPORARY)
A17: AJE-07 | B17: Sec 263A — UNICAP Adjustment | C17: Uniform capitalization — additional costs capitalized into inventory for tax. Compare COGS with/without UNICAP. | D17: §263A | E17: 8 (L L3-5) | F17: ='Working Trial Balance'!D8 | G17: ='Working Trial Balance'!F8 | H17: ='Working Trial Balance'!H8 | I17: Temp | J17: 4c | L17: Required if avg gross receipts >$29M (2025). Calculate using simplified method.
A18: AJE-08 | B18: Sec 267 — Related Party Accrued Expenses | C18: Accrued expenses to related parties (>50% ownership) not deductible until paid. Check if paid within 2.5 months. | D18: §267 | E18: 37 (P1 L9) | F18: ='Working Trial Balance'!D37 | G18: =-'Working Trial Balance'!G37 | H18: ='Working Trial Balance'!H37 | I18: Temp | J18: 4c | L18: Review AP aging for partner/related-party payables. Reverses when paid.
A19: AJE-09 | B19: Bad Debt Reserve vs Specific Charge-Off | C19: Book reserve method not allowed for tax. Only specific charge-offs when debt becomes worthless. | D19: §166 | E19: 40 (P1 L12) | F19: ='Working Trial Balance'!D40 | G19: =-'Working Trial Balance'!G40 | H19: ='Working Trial Balance'!H40 | I19: Temp | J19: 4c | L19: Identify actual write-offs during year. Reserve reverses as accounts are collected/written off.
A20: AJE-10 | B20: Warranty Reserve | C20: Book accrual for estimated warranty costs. Tax: deductible only when economic performance occurs (claims paid). | D20: §461(h) | E20: 58 (sub-line) | F20: ='Working Trial Balance'!D58 | G20: =-'Working Trial Balance'!G58 | H20: ='Working Trial Balance'!H58 | I20: Temp | J20: 4c | L20: Get actual warranty claims paid. Temporary — reverses as claims settle.
A21: AJE-11 | B21: Litigation Reserve / Contingent Liabilities | C21: Book accrual for probable litigation losses. Tax: not deductible until all-events test met and economic performance. | D21: §461(h) | E21: 59 (sub-line) | F21: ='Working Trial Balance'!D59 | G21: =-'Working Trial Balance'!G59 | H21: ='Working Trial Balance'!H59 | I21: Temp | J21: 4c | L21: Review legal correspondence. Settlement or judgment triggers deduction.
A22: AJE-12 | B22: Allowance for Doubtful Accounts (B/S) | C22: Book reserve against A/R. Tax: add back to assets (reserve method not allowed). | D22: §166 | E22: 7 (L L1-2) | F22: ='Working Trial Balance'!D7 | G22: ='Working Trial Balance'!F7 | H22: ='Working Trial Balance'!H7 | I22: Temp | L22: B/S only adjustment. Affects tax basis of receivables. Cross-ref AJE-09.
A23: AJE-13 | B23: Goodwill Amortization (Book 10yr vs Tax 15yr) | C23: Book amortizes goodwill over useful life (often 10yr). Tax: Sec 197 requires 15-year straight-line. | D23: §197 | E23: 62 (sub-line) | F23: ='Working Trial Balance'!D62 | G23: =-'Working Trial Balance'!G62 | H23: ='Working Trial Balance'!H62 | I23: Temp | J23: 4a | L23: Calculate: Cost / 180 months × months. Compare to book amort.
A24: AJE-14 | B24: Patent/Intangible Amortization (Book vs Tax) | C24: Patents and other Sec 197 intangibles. Book life may differ from 15-year tax amortization. | D24: §197 | E24: 63 (sub-line) | F24: ='Working Trial Balance'!D63 | G24: =-'Working Trial Balance'!G63 | H24: ='Working Trial Balance'!H63 | I24: Temp | J24: 4a | L24: Same 15-yr rule applies. Calculate monthly amort × months.
A25: DEDUCTION ADJUSTMENTS — PERMANENT
A26: AJE-15 | B26: Meals — 50% Limitation | C26: Business meals deductible at 50%. Identify total meals expense and disallow half. | D26: §274(n) | E26: 51 (sub-line) | F26: ='Working Trial Balance'!D51 | G26: =-'Working Trial Balance'!G51 | H26: ='Working Trial Balance'!H51 | I26: Perm | J26: 4b | K26: K 18c | L26: Verify meals vs entertainment classification. Must have business purpose documented.
A27: AJE-16 | B27: Entertainment — 100% Nondeductible | C27: Entertainment expenses fully nondeductible post-TCJA. Includes sporting events, theater, etc. | D27: §274(a) | E27: 52 (sub-line) | F27: ='Working Trial Balance'!D52 | G27: =-'Working Trial Balance'!G52 | H27: ='Working Trial Balance'!H52 | I27: Perm | J27: 4b | K27: K 18c | L27: Confirm proper classification. Entertainment ≠ meals.
A28: AJE-17 | B28: Club Dues — Nondeductible | C28: Country club, social club, athletic club dues. Fully nondeductible regardless of business use. | D28: §274(a)(3) | E28: 53 (sub-line) | F28: ='Working Trial Balance'!D53 | G28: =-'Working Trial Balance'!G53 | H28: ='Working Trial Balance'!H53 | I28: Perm | J28: 4c | K28: K 18c
A29: AJE-18 | B29: Penalties & Fines — Nondeductible | C29: Government fines and penalties. Nondeductible unless restitution or compliance payments. | D29: §162(f) | E29: 54 (sub-line) | F29: ='Working Trial Balance'!D54 | G29: =-'Working Trial Balance'!G54 | H29: ='Working Trial Balance'!H54 | I29: Perm | J29: 4c | K29: K 18c | L29: Review GL for penalty accounts. Check if any qualify under exception.
A30: AJE-19 | B30: Political Contributions — Nondeductible | C30: Contributions to political parties, candidates, or PACs. Always nondeductible. | D30: §162(e) | E30: 55 (sub-line) | F30: ='Working Trial Balance'!D55 | G30: =-'Working Trial Balance'!G55 | H30: ='Working Trial Balance'!H55 | I30: Perm | J30: 4c | K30: K 18c
A31: AJE-20 | B31: Life Insurance (Entity Beneficiary) | C31: Premiums on policies where partnership is beneficiary. Nondeductible. | D31: §264(a)(1) | E31: 56 (sub-line) | F31: ='Working Trial Balance'!D56 | G31: =-'Working Trial Balance'!G56 | H31: ='Working Trial Balance'!H56 | I31: Perm | J31: 4c | K31: K 18c | L31: Confirm partnership is beneficiary. Key-person policies.
A32: AJE-21 | B32: State Income/Franchise Tax | C32: State income or franchise taxes paid. Not deductible on federal partnership return. | D32: §275 | E32: 57 (sub-line) | F32: ='Working Trial Balance'!D57 | G32: =-'Working Trial Balance'!G57 | H32: ='Working Trial Balance'!H57 | I32: Perm | J32: 4c | K32: K 18c | L32: Separate from deductible property taxes and payroll taxes.
A33: SEPARATELY STATED / K-1 ITEMS
A34: AJE-22 | B34: Tax-Exempt Interest Income | C34: Municipal bond interest. Not taxable but increases partner basis. Report on K Line 18a. | D34: §103 | E34: 88 (K L18a) | F34: ='Working Trial Balance'!D88 | G34: 0 | H34: ='Working Trial Balance'!H88 | I34: Perm | J34: 6 | K34: K 18a | L34: Include in M-2 other increases. Increases basis.
A35: AJE-23 | B35: Partner Health Insurance (to K-1) | C35: Health insurance premiums for partners. Not a P1 deduction — goes to each K-1 Line 13 Code M. | D35: §162(l) | E35: 60 (sub-line) | F35: ='Working Trial Balance'!D60 | G35: =-'Working Trial Balance'!G60 | H35: ='Working Trial Balance'!H60 | I35: N/A | J35: 4c | K35: K-1 13M | L35: Allocate per partner. Partner takes as SE health ins deduction on 1040.
A36: AJE-24 | B36: Charitable Contributions (to K-1) | C36: Charitable donations. Separately stated — not on P1. Each partner applies own AGI limitation. | D36: §170 | E36: 64 (sub-line) | F36: ='Working Trial Balance'!D64 | G36: =-'Working Trial Balance'!G64 | H36: ='Working Trial Balance'!H64 | I36: N/A | J36: 4c | K36: K 13a | L36: Get donation receipts for >$250. Noncash >$500 needs Form 8283.
A37: AJE-25 | B37: Investment Interest Expense (to K-1) | C37: Interest on debt to carry investments. Separately stated — partner applies Sec 163(d) limitation. | D37: §163(d) | E37: 65 (sub-line) | F37: ='Working Trial Balance'!D65 | G37: =-'Working Trial Balance'!G65 | H37: ='Working Trial Balance'!H65 | I37: N/A | J37: 4c | K37: K 13b | L37: Match to investment income. Partner nets on Form 4952.
A39: CHECKLIST TOTALS | F39: =SUM(F9:F37) | G39: =SUM(G9:G37) | H39: =SUM(H9:H37)
A40: CHECK: Net Adjustment (Tax Total - Book Total) should match sum of Adj column | G40: =H39-F39-G39
A43: SECTION B — ADJUSTING JOURNAL ENTRIES (AJEs)
A44: Each AJE represents a book-to-tax adjustment. DR increases tax amount, CR decreases. These entries bridge the gap between client books and the tax return.
A46: AJE# | B46: Date | C46: Account / Line Description | D46: WTB Row | E46: DR (+) | F46: CR (-) | G46: Net Effect | H46: Perm / Temp | I46: IRC Reference | J46: Memo / Workpaper Reference
A47: AJE-01 | B47: 12/31/25 | C47: DR: Tax Depreciation (MACRS excess over book) | D47: 44 | E47: ='Working Trial Balance'!F44 | G47: =E47 | H47: Temp | I47: §167/168 | J47: MACRS depr exceeds book by this amount. DR increases tax deduction (P1 L16a). Get from depr schedule.
C48: CR: Book Depreciation (reclassify excess) | D48: 44 | F48: ='Working Trial Balance'!F44
A49: AJE-02 | B49: 12/31/25 | C49: DR: Fixed Asset — Capitalize for Tax (Sec 179) | D49: 10 | E49: ='Working Trial Balance'!F84 | G49: =E49 | H49: Temp | I49: §179 | J49: Book expensed $35K capital improvement. Tax: capitalize and elect Sec 179 on K L12.
C50: CR: Other Deductions — Remove book expense | D50: 61 | F50: ='Working Trial Balance'!F84
A51: AJE-03 | B51: 12/31/25 | C51: DR: Ordinary Income — Sec 1245 Recapture | D51: 33 | E51: ='Working Trial Balance'!F33 | G51: =E51 | H51: Temp | I51: §1245 | J51: Recapture depr on disposed asset. $12K from 1231 reclassed to ordinary (P1 L6).
C52: CR: Sec 1231 Gain — Reclassify recapture portion | D52: 80 | F52: ='Working Trial Balance'!G80
A53: AJE-04 | B53: 12/31/25 | C53: DR: Other Income — Remove COD excluded | D53: 34 | E53: ='Working Trial Balance'!G34 | G53: =E53 | H53: Perm | I53: §108 | J53: Partnership insolvent at time of COD. File Form 982. Reduce tax attributes.
C54: CR: Book Income — Sec 108 exclusion | D54: 34 | F54: ='Working Trial Balance'!G34
A55: AJE-05 | B55: 12/31/25 | C55: DR: Rental Real Estate — Tax depr adjustment | D55: 71 | E55: ='Working Trial Balance'!F71 | G55: =E55 | H55: Temp | I55: §167/168 | J55: Rental property MACRS exceeds book depr. Increases net rental income for tax.
C56: CR: Rental Depreciation — Excess tax over book | D56: 71 | F56: ='Working Trial Balance'!F71
A57: AJE-06 | B57: 12/31/25 | C57: DR: Inventory — UNICAP Sec 263A add-back | D57: 8 | E57: ='Working Trial Balance'!F8 | G57: =E57 | H57: Temp | I57: §263A | J57: UNICAP adds $8.5K to inventory basis. Required if avg gross receipts >$29M.
C58: CR: Cost Capitalized to Inventory | D58: 8 | F58: ='Working Trial Balance'!F8
A59: AJE-07 | B59: 12/31/25 | C59: DR: Salaries Expense — Sec 267 disallowance | D59: 37 | E59: ='Working Trial Balance'!G37 | G59: =E59 | H59: Temp | I59: §267 | J59: Accrued bonus to related partner not paid within 2.5 months. Disallow until paid.
C60: CR: Accrued Bonus — Related party unpaid | D60: 37 | F60: ='Working Trial Balance'!G37
A61: AJE-08 | B61: 12/31/25 | C61: DR: Bad Debt Expense — Reserve disallowance | D61: 40 | E61: ='Working Trial Balance'!G40 | G61: =E61 | H61: Temp | I61: §166 | J61: Book reserve method not allowed for tax. Specific charge-off only. Actual write-offs = $0.
C62: CR: Allowance for Doubtful Accounts — Tax add-back | D62: 40 | F62: ='Working Trial Balance'!G40
A63: AJE-09 | B63: 12/31/25 | C63: DR: Warranty Expense — Reserve disallowance | D63: 58 | E63: ='Working Trial Balance'!G58 | G63: =E63 | H63: Temp | I63: §461(h) | J63: Tax: deductible when claims actually paid, not when accrued.
C64: CR: Warranty Reserve — Economic performance not met | D64: 58 | F64: ='Working Trial Balance'!G58
A65: AJE-10 | B65: 12/31/25 | C65: DR: Litigation Expense — Reserve disallowance | D65: 59 | E65: ='Working Trial Balance'!G59 | G65: =E65 | H65: Temp | I65: §461(h) | J65: Tax: deductible when settled/paid. Get status from legal counsel.
C66: CR: Litigation Reserve — Economic performance not met | D66: 59 | F66: ='Working Trial Balance'!G59
A67: AJE-11 | B67: 12/31/25 | C67: DR: A/R Allowance — Tax add-back | D67: 7 | E67: ='Working Trial Balance'!F7 | G67: =E67 | H67: Temp | I67: §166 | J67: B/S only. Increase tax basis of receivables by book reserve amount.
C68: CR: Receivables Basis Adjustment | D68: 7 | F68: ='Working Trial Balance'!F7
A69: AJE-12 | B69: 12/31/25 | C69: DR: Goodwill Amort — Book exceeds tax | D69: 62 | E69: ='Working Trial Balance'!G62 | G69: =E69 | H69: Temp | I69: §197 | J69: Book 10yr ($30K) vs tax 15yr ($20K). Tax basis $10K higher than book.
C70: CR: Intangible Basis — Sec 197 slower amort | D70: 11 | F70: ='Working Trial Balance'!G62
A71: AJE-13 | B71: 12/31/25 | C71: DR: Patent Amort — Book exceeds tax | D71: 63 | E71: ='Working Trial Balance'!G63 | G71: =E71 | H71: Temp | I71: §197 | J71: Book 10yr ($7.5K) vs tax 15yr ($5K). Tax basis $2.5K higher than book.
C72: CR: Intangible Basis — Sec 197 slower amort | D72: 11 | F72: ='Working Trial Balance'!G63
A73: AJE-14 | B73: 12/31/25 | C73: DR: Meals Expense — 50% disallowance | D73: 51 | E73: ='Working Trial Balance'!G51 | G73: =E73 | H73: Perm | I73: §274(n) | J73: Business meals 50% deductible. $16K nondeductible portion to K-1 Line 18c.
C74: CR: Nondeductible Expense (K 18c) | D74: 51 | F74: ='Working Trial Balance'!G51
A75: AJE-15 | B75: 12/31/25 | C75: DR: Entertainment Expense — Full disallowance | D75: 52 | E75: ='Working Trial Balance'!G52 | G75: =E75 | H75: Perm | I75: §274(a) | J75: 100% nondeductible post-TCJA.
C76: CR: Nondeductible Expense (K 18c) | D76: 52 | F76: ='Working Trial Balance'!G52
A77: AJE-16 | B77: 12/31/25 | C77: DR: Club Dues — Full disallowance | D77: 53 | E77: ='Working Trial Balance'!G53 | G77: =E77 | H77: Perm | I77: §274(a)(3) | J77: 100% nondeductible.
C78: CR: Nondeductible Expense (K 18c) | D78: 53 | F78: ='Working Trial Balance'!G53
A79: AJE-17 | B79: 12/31/25 | C79: DR: Penalties & Fines — Full disallowance | D79: 54 | E79: ='Working Trial Balance'!G54 | G79: =E79 | H79: Perm | I79: §162(f) | J79: Government penalties nondeductible unless restitution.
C80: CR: Nondeductible Expense (K 18c) | D80: 54 | F80: ='Working Trial Balance'!G54
A81: AJE-18 | B81: 12/31/25 | C81: DR: Political Contributions — Full disallowance | D81: 55 | E81: ='Working Trial Balance'!G55 | G81: =E81 | H81: Perm | I81: §162(e)
C82: CR: Nondeductible Expense (K 18c) | D82: 55 | F82: ='Working Trial Balance'!G55
A83: AJE-19 | B83: 12/31/25 | C83: DR: Life Insurance Premiums — Full disallowance | D83: 56 | E83: ='Working Trial Balance'!G56 | G83: =E83 | H83: Perm | I83: §264(a)(1) | J83: Partnership is beneficiary.
C84: CR: Nondeductible Expense (K 18c) | D84: 56 | F84: ='Working Trial Balance'!G56
A85: AJE-20 | B85: 12/31/25 | C85: DR: State Income/Franchise Tax — Full disallowance | D85: 57 | E85: ='Working Trial Balance'!G57 | G85: =E85 | H85: Perm | I85: §275 | J85: Not deductible on federal return.
C86: CR: Nondeductible Expense (K 18c) | D86: 57 | F86: ='Working Trial Balance'!G57
A87: AJE-21 | B87: 12/31/25 | C87: DR: Tax-Exempt Interest — Remove from taxable | D87: 88 | E87: 0 | G87: =E87 | H87: Perm | I87: §103 | J87: Not an income/expense adj. Separately stated on K 18a. Increases partner basis via M-2.
C88: CR: Tax-Exempt Income (K 18a, M-2 increase) | D88: 88 | F88: 0
A89: AJE-22 | B89: 12/31/25 | C89: DR: Partner Health Ins — Remove from P1 deductions | D89: 60 | E89: ='Working Trial Balance'!G60 | G89: =E89 | H89: N/A | I89: §162(l) | J89: Reclassify from P1 to K-1. Partner takes as SE health ins deduction.
C90: CR: K-1 Line 13 Code M (separately stated) | D90: 60 | F90: ='Working Trial Balance'!G60
A91: AJE-23 | B91: 12/31/25 | C91: DR: Charitable Contributions — Remove from P1 | D91: 64 | E91: ='Working Trial Balance'!G64 | G91: =E91 | H91: N/A | I91: §170 | J91: Separately stated. Partner applies own AGI limitation.
C92: CR: K Line 13a (separately stated) | D92: 64 | F92: ='Working Trial Balance'!G64
A93: AJE-24 | B93: 12/31/25 | C93: DR: Investment Interest — Remove from P1 | D93: 65 | E93: ='Working Trial Balance'!G65 | G93: =E93 | H93: N/A | I93: §163(d) | J93: Separately stated. Partner applies Sec 163(d) net investment income limitation.
C94: CR: K Line 13b (separately stated) | D94: 65 | F94: ='Working Trial Balance'!G65
A95: AJE-25 | B95: 12/31/25 | C95: DR: Intangible Assets — Tax basis higher (Sec 197) | D95: 11 | E95: ='Working Trial Balance'!F11 | G95: =E95 | H95: Temp | I95: §197 | J95: B/S only. Tax basis of intangibles exceeds book due to slower Sec 197 amort.
C96: CR: Accumulated Amortization — Tax slower | D96: 11 | F96: ='Working Trial Balance'!F11
A98: AJE TOTALS | E98: =SUM(E47:E96) | F98: =SUM(F47:F96) | G98: =E98-F98
A99: CHECK: DR Total = CR Total (should be ZERO) | G99: =E98-F98
A102: SECTION C — ADJUSTMENT SUMMARY & CROSS-REFERENCE TO 1065
A104: 1065 Section | B104: Book Amount | C104: Total Adjustments | D104: Tax Amount | E104: Tied To | F104: Status
A105: Page 1 — Income (L8) | B105: ='Working Trial Balance'!D35 | C105: ='Working Trial Balance'!H35-'Working Trial Balance'!D35 | D105: ='Working Trial Balance'!H35 | E105: WTB R35 | F105: =IF(D105=B105+C105,"✓","✗")
A106: Page 1 — Deductions (L21) | B106: ='Working Trial Balance'!D66 | C106: ='Working Trial Balance'!H66-'Working Trial Balance'!D66 | D106: ='Working Trial Balance'!H66 | E106: WTB R66 | F106: =IF(D106=B106+C106,"✓","✗")
A107: Page 1 — OBI (L22) | B107: ='Working Trial Balance'!D67 | C107: ='Working Trial Balance'!H67-'Working Trial Balance'!D67 | D107: ='Working Trial Balance'!H67 | E107: WTB R67 | F107: =IF(D107=B107+C107,"✓","✗")
A108: Schedule K — Total | B108: ='Working Trial Balance'!D82 | C108: ='Working Trial Balance'!H82-'Working Trial Balance'!D82 | D108: ='Working Trial Balance'!H82 | E108: WTB R82 | F108: =IF(D108=B108+C108,"✓","✗")
A109: Schedule L — Total Assets | B109: ='Working Trial Balance'!D12 | C109: ='Working Trial Balance'!H12-'Working Trial Balance'!D12 | D109: ='Working Trial Balance'!H12 | E109: WTB R12 | F109: =IF(D109=B109+C109,"✓","✗")
A110: Schedule L — Liabilities | B110: ='Working Trial Balance'!D15 | C110: ='Working Trial Balance'!H15-'Working Trial Balance'!D15 | D110: ='Working Trial Balance'!H15 | E110: WTB R15 | F110: =IF(D110=B110+C110,"✓","✗")
...

Sheet Tax Strategies Workpaper
A1: TAX STRATEGIES WORKPAPER — 1065 ENTITY-LEVEL STRATEGIES
A2: Strategies that create adjustments on the Form 1065 partnership return. Hide sections not applicable to client.
A3: LEGEND: Blue = Manual entry | Gold = Linked to WTB | Green = Auto-calc | Orange = Adjustment row
A5: 1. AUGUSTA RULE — IRC §280A(g) (14-Day Home Rental to Entity)
A7: FIRM PARAMETERS
B8: Criteria | C8: Amount / Rule | K8: Notes
B9: Income > $1M/yr | C9: $2,000/day × 14 days = $28,000 max | K9: Must own primary residence (not leased)
B10: Income < $1M/yr | C10: $1,000/day × 14 days = $14,000 max | K10: Must own primary residence (not leased)
B11: Eligible entities | C11: Multi-member LLCs, S-Corps, C-Corps | K11: NOT sole prop or Single Member LLC
B12: Documentation | C12: Lease, FMV comps, agendas, minutes, attendee list | K12: Payment trail from entity to member
A14: 1065 ADJUSTMENTS
A15: # | B15: 1065 Line | C15: Description | D15: Book Amt | E15: Tax Adj | F15: Tax Amt | G15: M-1 Line | H15: K Line | I15: WTB Row | J15: AJE Ref | K15: How to Handle
A16: 1 | B16: P1 L20 (Other Ded) | C16: Augusta Rule rent — deduction to partnership | D16: If on books | E16: If not on books | F16: Auto | G16: None if on books. M-1 L7 if tax-only. | H16: Reduces OBI (K L1) | I16: Row 50 | J16: New | K16: If client books the rent expense → flows through P1 L20 naturally, no M-1 adj. If tax-only deduction (not on books) → WTB Row 50 Adj(+), M-1 Line 7 "deduction on return not on books." Either way: reduces OBI → reduces each partner K-1 Box 1.
A17: 2 | B17: Partner (not on 1065) | C17: Partner receives rent — TAX FREE under §280A(g) | K17: Partner does NOT report rental income anywhere. Excluded from gross income. No Schedule E, no 1099-MISC required. Some practitioners issue 1099 and zero out on Sch E — either works.
A19: DOCUMENTATION CHECKLIST
A20: ☐ | B20: Written lease agreement (partnership ↔ member) | J20: Entity file
A21: ☐ | B21: FMV analysis — comparable venue rates (hotels, Airbnb, conference centers) | J21: Entity file
A22: ☐ | B22: Meeting agendas for each of the ≤14 rental days | J22: Entity file
A23: ☐ | B23: Meeting minutes/notes with business decisions documented | J23: Entity file
A24: ☐ | B24: Attendee list per meeting | J24: Entity file
A25: ☐ | B25: Day-count calendar (running total of days used YTD) | J25: Entity file
A26: ☐ | B26: Payment proof — check/wire/ACH from entity account to member personal account | J26: Entity file
A27: ☐ | B27: Partner resolution authorizing the rental arrangement | J27: Entity file
A28: ☐ | B28: Confirm member OWNS primary residence (deed/mortgage statement — strategy fails if leased) | J28: Entity file
A30: 2. KIDS ON PAYROLL / MANAGEMENT COMPANY — IRC §3121(b)(3)(A)
A32: FIRM PARAMETERS
B33: Criteria | C33: Amount / Rule | K33: Notes
B34: Max per child | C34: $16,100/child (2026 standard deduction) | K34: Child owes $0 federal income tax if wages ≤ this
B35: FICA exempt | C35: Child under 18, partnership = both parents only | K35: Any non-parent partner → full FICA applies
B36: FUTA exempt | C36: Child under 21, same ownership rule | K36: Still must file W-2 and 941s even if exempt
B37: Mgmt Co option | C37: Combine Mgmt Co + Kids Payroll when possible | K37: Mgmt Co invoices partnership; pays kids from Mgmt Co
B38: Work must be real | C38: Filing, cleaning, social media, data entry, inventory | K38: Document hours, duties, pay rate
A40: 1065 ADJUSTMENTS
A41: # | B41: 1065 Line | C41: Description | D41: Book Amt | E41: Tax Adj | F41: Tax Amt | G41: M-1 Line | H41: K Line | I41: WTB Row | J41: AJE Ref | K41: How to Handle
A42: 1 | B42: P1 L9 (Salaries) | C42: Wages to partner's child(ren) | D42: If on books | E42: If not on books | F42: Auto | G42: None if on books. M-1 L7 if tax-only. | H42: Reduces OBI (K L1) | I42: Row 37 | J42: New | K42: If wages on client books → no M-1 adj, flows through P1 L9. If tax-only → WTB Row 37 Adj(+), M-1 Line 7. Issue W-2 to child. File 941s quarterly. FICA exempt boxes on W-2 if both-parent partnership and child <18.
A43: 2 | B43: P1 L9 (Salaries) | C43: Employer payroll taxes (if FICA applies) | I43: Row 42 (Taxes) | K43: If FICA exempt: $0 employer FICA. Only FUTA ($42/child max). If NOT exempt (non-parent partner exists): employer pays 7.65% FICA on wages. Payroll tax expense goes to P1 L14 (Taxes and Licenses).
A44: 3 | B44: P1 L20 (Other Ded) | C44: Mgmt Co fees (if using Mgmt Co structure) | D44: If on books | E44: If not on books | F44: Auto | G44: None if on books. M-1 L7 if tax-only. | H44: Reduces OBI (K L1) | I44: Row 50 | J44: New | K44: Partnership pays management fee to separate Mgmt Co (owned by spouse/family). Mgmt Co then pays kids as W-2 employees. Partnership deducts as management fees on P1 L20 Other Deductions. Must be arm's length — reasonable for services rendered.
A46: DOCUMENTATION CHECKLIST
A47: ☐ | B47: Written job description per child — specific duties, responsibilities | J47: Entity file
A48: ☐ | B48: Time sheets / work log signed by child and supervising partner | J48: Entity file
A49: ☐ | B49: Pay rate documentation — reasonable for age, skill, local market (min wage check) | J49: Entity file
A50: ☐ | B50: W-4 from child (may claim exempt if no liability expected) | J50: Entity file
A51: ☐ | B51: W-2 issued to each child annually | J51: Entity file
A52: ☐ | B52: Form 941 quarterly (or 944 annual) | J52: Entity file
A53: ☐ | B53: Partnership agreement confirming both partners are parents (FICA exemption) | J53: Entity file
A54: ☐ | B54: Proof of payment — check or direct deposit to child's own bank account | J54: Entity file
A55: ☐ | B55: Work product samples (social media posts, filed docs, photos of work) | J55: Entity file
A56: ☐ | B56: If using Mgmt Co: management agreement, invoices, Mgmt Co books/W-2s to kids | J56: Entity file
A58: 3. HOME OFFICE / ACCOUNTABLE REIMBURSEMENT PLAN (ARP) / BUH
A60: FIRM PARAMETERS
B61: Criteria | C61: Amount / Rule | K61: Notes
B62: Minimum estimate | C62: $6,000 starting point | K62: Member-specific calculation needed
B63: ARP (Accountable Plan) | C63: Entity reimburses member for home office | K63: Deduction on entity, tax-free to member
B64: UPE (no ARP) | C64: Member deducts on 1040 Sch E Page 2 | K64: Partnership agreement must require UPE
B65: Method | C65: Regular (actual × %) or Simplified ($5/sqft, max 300 sqft) | K65: Regular method usually gives larger deduction
A67: 1065 ADJUSTMENTS — TWO PATHS
A68: • | B68: PATH A — ACCOUNTABLE REIMBURSEMENT PLAN (ARP): Entity reimburses member for home office expenses under an accountable plan. Reimbursement is deductible to the entity on P1 L20 (Other Deductions). Tax-free to the member (not on W-2, not on K-1). This IS an entity-level deduction. Goes on WTB Row 50. If not on books → M-1 Line 7.
A69: • | B69: PATH B — UPE (NO ARP): Member claims as Unreimbursed Partner Expense on their 1040 Schedule E Page 2. NO IMPACT on the 1065 at all. No WTB entry. No M-1. No K adjustment. Purely individual. Partnership agreement MUST state members pay home office without reimbursement (McLauchlan, 558 Fed. Appx. 374). UPE reduces both income tax and SE tax.
A71: # | B71: 1065 Line | C71: Description | D71: Book Amt | E71: Tax Adj | F71: Tax Amt | G71: M-1 Line | H71: K Line | I71: WTB Row | J71: AJE Ref | K71: How to Handle
A72: A | B72: P1 L20 (Other Ded) | C72: ARP reimbursement — home office (entity deduction) | D72: If on books | E72: If not on books | F72: Auto | G72: None if on books. M-1 L7 if tax-only. | H72: Reduces OBI (K L1) | I72: Row 50 | J72: New | K72: ARP PATH: Entity pays/reimburses member under accountable plan. Deducted on P1 L20. Tax-free to member. Must meet accountable plan rules: business connection, substantiation, return of excess.
A73: B | B73: NOT on 1065 | C73: UPE — home office (member's 1040 Sch E P2) | G73: N/A | H73: N/A | I73: N/A | J73: N/A | K73: UPE PATH: No 1065 adjustment. Member claims on Sch E P2. Reduces K-1 income on their 1040 and reduces SE income via SE worksheet. Partnership agreement must explicitly require UPE.
A75: DOCUMENTATION CHECKLIST
A76: ☐ | B76: Accountable Reimbursement Plan document (if using ARP path) | J76: Entity file
A77: ☐ | B77: Partnership/Operating agreement with UPE clause (if using UPE path) | J77: Entity file
A78: ☐ | B78: Floor plan / measurement of home office (dedicated and regular use) | J78: Entity file
A79: ☐ | B79: Mortgage interest or rent receipts | J79: Entity file
A80: ☐ | B80: Property tax statements | J80: Entity file
A81: ☐ | B81: Utility bills (electric, gas, internet, phone) | J81: Entity file
A82: ☐ | B82: Home insurance declarations page | J82: Entity file
A83: ☐ | B83: IRS Pub 587 worksheet or Form 8829 computation | J83: Entity file
A84: ☐ | B84: Receipts for any other reimbursed business expenses under ARP | J84: Entity file
A86: 4. IRC §179 / §168(k) BONUS DEPRECIATION
A88: FIRM PARAMETERS
B89: Criteria | C89: Amount / Rule | K89: Notes
B90: Bonus Depr (§168(k)) | C90: 100% for assets purchased and placed in service by 1/20/25 | K90: Check phase-down schedule for later dates
B91: §168(k) phase-down | C91: 2025: 100% (if placed in service by 1/20/25) → 2026: 20% → 2027: 0% | K91: TCJA sunset — verify current year rate
B92: §179 Election | C92: Expense entire cost in year placed in service | K92: Subject to §179 annual limit ($1,250,000 for 2025)
B93: §179 income limit | C93: Cannot exceed taxable income of partnership | K93: Excess carries forward to partners on K-1 L12
B94: Eligible property | C94: Tangible personal property, QIP, certain software | K94: NOT real property (unless QIP or elected)
A96: 1065 ADJUSTMENTS
A97: # | B97: 1065 Line | C97: Description | D97: Book Amt | E97: Tax Adj | F97: Tax Amt | G97: M-1 Line | H97: K Line | I97: WTB Row | J97: AJE Ref | K97: How to Handle
A98: 1 | B98: P1 L16a (Tax Depr) | C98: MACRS / Bonus Depreciation (tax depr > book) | D98: ='Working Trial Balance'!D44 | F98: ='Working Trial Balance'!H44 | G98: M-1 L4a (book depr) M-1 L7 (tax depr excess) | I98: Row 44 | J98: AJE-01 | K98: Book depreciation on P1 L16a. Tax MACRS/bonus in Adj(+) column. Difference = M-1 adjustment. Get from tax depreciation schedule. Existing AJE-01 on Adjustments tab handles this.
A99: 2 | B99: K L12 (§179) | C99: Section 179 expense election | D99: ='Working Trial Balance'!D61 | E99: ='Working Trial Balance'!F84 | F99: ='Working Trial Balance'!H84 | G99: M-1 L7 (ded on return not on books) | H99: K L12 (separately stated) | I99: Row 84 | J99: AJE-02 | K99: Book: expensed as repair/cap improvement. Tax: capitalize then elect §179 on K L12. Separately stated — passes to each partner's K-1. Partner applies their own §179 limit. Existing AJE-02 on Adjustments tab.
A100: 3 | B100: Schedule L (L9-10) | C100: Fixed asset basis — tax vs book | D100: ='Working Trial Balance'!D10 | F100: ='Working Trial Balance'!H10 | I100: Row 10 | J100: AJE-01 | K100: Tax basis of fixed assets differs from book due to bonus/179. Schedule L tax column reflects tax basis (lower if more depr taken). Tracked in Balance Sheet section of WTB.
A102: DOCUMENTATION CHECKLIST
A103: ☐ | B103: Tax depreciation schedule (MACRS lives, methods, conventions) | J103: Entity file
A104: ☐ | B104: Asset purchase invoices / settlement statements (date placed in service) | J104: Entity file
A105: ☐ | B105: Book depreciation schedule (for M-1 comparison) | J105: Entity file
A106: ☐ | B106: §179 election statement (if electing) | J106: Entity file
A107: ☐ | B107: Bonus depreciation calculation worksheet | J107: Entity file
A108: ☐ | B108: Confirmation asset was placed in service before applicable deadline | J108: Entity file
A110: 5. COST SEGREGATION / STR / LTR / SELF-RENTAL
A112: FIRM PARAMETERS
B113: Type | C113: Estimate / Rule | K113: Notes
B114: $1M purchase | C114: Est. bonus depreciation = $259,000 | K114: Estimated at 90/10 ratio (land/building)
B115: $750K purchase | C115: Est. bonus depreciation = $194,000 | K115: Column label: LTR or STR w/ purchase price + est. bonus
B116: $500K purchase | C116: Est. bonus depreciation = $129,000 | K116: Actual cost seg study will refine
B117: $250K purchase | C117: Est. bonus depreciation = $64,000 | K117: Must have cost seg study performed
B118: STR avg stay | C118: <7 days avg tenant stay = STR | K118: Material participation → nonpassive losses (offset W-2)
B119: LTR | C119: >7 days avg tenant stay | K119: Passive activity — may need grouping election or REP status
...
