Workbook

Sheet Instructions
A1: 1120-S WORKING TRIAL BALANCE TEMPLATE
A2: Version 1.0
A4: HOW TO USE THIS TEMPLATE
A6: STEP 1: PASTE PBC DATA
A7: • Export P&L from QuickBooks → paste into "PBC - P&L2" tab
A8: • Export Balance Sheet from QuickBooks → paste into "PBC- Balance Sheet" tab
A9: • Make sure Net Income lands in PBC-P&L2 cell B63
A10: • Make sure Total Equity lands in PBC-BS cell B88, Total L&E in B89
A12: STEP 2: BUILD WORKING P&L & BALANCE SHEET
A13: • Map QuickBooks line items to Working P&L (P&L tab, column B) — yellow cells
A14: • Map QuickBooks line items to Working Balance Sheet (Balance Sheet tab) — yellow cells
A15: • Subtotals and totals auto-calculate via formulas
... A63: 13. Schedule M-3 Net income reconciliation (if needed)

Sheet P&L
A1: [ENTITY NAME] — Working Profit & Loss
A2: Profit & Loss — December 1, 2024 to November 30, 2025
A3: Provided by Client (PBC) — QuickBooks Export
A5: Account | B5: Amount
A6: REVENUE
A7: Software Licensing Revenue
A8: —
A9: Equipment Rental Income
A10: Returns & Allowances
A11: Total Revenue | B11: =SUM(B7:B10)
A12: COST OF GOODS SOLD
A13: 5000 · COGS (N/A — service company)
A14: —
A15: —
A16: Total COGS | B16: =SUM(B13:B15)
A17: GROSS PROFIT | B17: =B11-B16
A18: OPERATING EXPENSES
A19: 02 Payroll – Wages & Salaries (all staff)
A20: 02 Payroll – Bonus
A21: 02 Payroll – Health Insurance
A22: 02 Payroll – Payroll Taxes (FICA/FUTA)
A23: 02 Payroll – 401K Retirement Program
A24: 02 Payroll – Payroll Processing Fees
A25: 03 IT – Computer Software & Supplies
A26: 04 Leases – 540 NE 4th Street LLC
A27: —
A28: —
A29: —
... A49: Travel Meals
A50: Total Operating Expenses | B50: =SUM(B19:B49)
A51: OPERATING INCOME | B51: =B17-B50
A52: OTHER INCOME / (EXPENSE)
A53: Interest Income (Schwab & Bank Accounts)
A54: ST Investment Income (Dividends – Schwab)
A55: ↳ Qualified Dividends: TBD (memo — need 1099-DIV)
A56: Capital Gain / (Loss) on Investments
A57: —
A58: —
A59: —
A60: Tax-Exempt Interest
A61: Unrealized Capital Gain / Loss (Book Only)
A62: Total Other Income / (Expense) | B62: =SUM(B53:B61)
A63: NET INCOME PER BOOKS | B63: =B51+B62
B64: =B63-'PBC - P&L2'!B63

Sheet  Balance Sheet
A1: [ENTITY NAME] — Working Balance Sheet
A2: Tax Year Ended [MM/DD/YYYY]
A3: Provided by Client (PBC) — QuickBooks Export
A5: Account | B5: November 30, 2025 | C5: November 30, 2024 (PY) ⚠ MANUALLY ENTER / VERIFY
A6: ASSETS
A7: Current Assets
A8: Cash – Chase 7884 / Chase Operating – 1180 / Wells Fargo – 6016
A9: Intercompany Receivable – IPS (net)
A10: Loans Receivable – Stockholder
A11: Prepaid Expenses
A12: —
A13: —
A14: —
A15: Total Current Assets | B15: =SUM(B8:B14) | C15: =SUM(C8:C14)
A17: Investments
A18: S-T Investments – Schwab One 2480-2532
A19: —
A20: Total Investments | B20: =SUM(B18:B19) | C20: =SUM(C18:C19)
A22: Fixed Assets
A23: Office & Computer Equipment (gross)
A24: Accumulated Depreciation – Office & Computer Equipment
A25: —
A26: —
A27: —
A28: —
A29: —
A30: —
A31: Total Fixed Assets | B31: =SUM(B23:B30) | C31: =SUM(C23:C30)
A33: Other Assets
A34: Security Deposit
A35: L-T Investments (VFT Global + IPS Mexico)
A36: Total Other Assets | B36: =SUM(B34:B35) | C36: =SUM(C34:C35)
A38: TOTAL ASSETS | B38: =B15+B20+B31+B36 | C38: =C15+C20+C31+C36
A40: LIABILITIES
A41: Current Liabilities
A42: Accounts Payable
A43: —
A44: Payroll Liabilities (401K ADP + Payroll Expense Liability)
A45: Accrued Expenses
A46: —
A47: —
A48: Total Current Liabilities | B48: =SUM(B42:B47) | C48: =SUM(C42:C47)
A50: Long-Term Liabilities
A51: —
A52: —
A53: —
A54: Total Long-Term Liabilities | B54: =SUM(B51:B53) | C54: =SUM(C51:C53)
A56: TOTAL LIABILITIES | B56: =B48+B54 | C56: =C48+C54
A58: EQUITY
A59: Common Stock
A60: —
A61: Retained Earnings (Cumulative, per QuickBooks) | E61: Distributions
A62: Sub. S Distributions (Cumulative thru Nov 30, 2025) | E62: =B62-C62
A63: ↳ CY Distributions only (Sch K Ln 16d / M-2): $877,164.44 — tracked in WTB distributions section
A64: Net Income (Current Year) | B64: ='P&L'!B63
A65: Total Equity | B65: =SUM(B59:B64) | C65: =SUM(C59:C64)
A67: TOTAL LIABILITIES & EQUITY | B67: =B56+B65 | C67: =C56+C65 | D67: ='PBC- Balance Sheet'!B89-' Balance Sheet'!B67 | E67: =C67-'PBC- Balance Sheet'!C89
A68: CHECK: Assets - L&E (should be zero) | B68: =B38-B67 | C68: =C38-C67

Sheet PBC- Balance Sheet
A1: PASTE CLIENT BALANCE SHEET FROM QUICKBOOKS HERE
A2: Column A = Account Name, Column B = Current Year, Column C = Prior Year
A3: Row 88: Total Equity, Row 89: Total L&E (referenced by M-2 formulas)
B88: Total Equity
B89: Total L&E

Sheet PBC - P&L2
A1: PASTE CLIENT P&L FROM QUICKBOOKS HERE
A2: Column A = Account Name, Column B = Amount (Current Year)
A3: Row 63: Net Income (this cell is referenced by formulas)
B63: Net Income goes here

Sheet Working Trial Balance
A1: [ENTITY NAME] — 1120-S Working Trial Balance
A2: Tax Year Ended [MM/DD/YYYY]
A3: Prepared by: ____________ Reviewed by: ____________ Date: ____________
A5: Account Description | B5: A PBC / Book (As Provided) | C5: B Pre-Book Reclass Adj | D5: C = A+B Adjusted Book (Post-Reclass) | E5: D Schedule K Adjustments | F5: E = C+D Tax Return Amount | G5: Ties To (Tax Return Line) | H5: F M-1 Adjustments | I5: M-1 Line Ref | J5: Notes / Explanation
A6: LEGEND: ■ Yellow = M-1 adjustment ■ Green = Separately stated (→ Sch K) ■ Orange = Nondeductible ■ Purple = Basis-affecting (AAA/OAA) ■ Red = Prior-year / Manually Enter
A7: ASSETS (from PBC Balance Sheet — Sch L)
A8: 1000 · Cash - Business Checking | B8: =' Balance Sheet'!B8 | C8: 0 | D8: =B8+C8 | F8: =D8 | G8: Sch L, Ln 1
A9: 1010 · Cash - Business Savings | B9: =' Balance Sheet'!B9 | D9: =B9+C9 | F9: =D9 | G9: Sch L, Ln 1
A10: 1020 · Accounts Receivable | B10: =' Balance Sheet'!B10 | C10: 0 | D10: =B10+C10 | F10: =D10 | G10: Sch L, Ln 5a
A11: 1030 · Allowance for Doubtful Accounts | B11: =' Balance Sheet'!B11 | C11: 0 | D11: =B11+C11 | F11: =D11 | G11: Sch L, Ln 5b
A12: 1040 · Prepaid Expenses | B12: =' Balance Sheet'!B12 | C12: 0 | D12: =B12+C12 | F12: =D12 | G12: Sch L, Ln 6
A13: 1050 · Employee Advances | B13: =' Balance Sheet'!B13 | C13: 0 | D13: =B13+C13 | F13: =D13 | G13: Sch L, Ln 6
A14: 1060 · Inventory | B14: =' Balance Sheet'!B14 | C14: 0 | D14: =B14+C14 | F14: =D14 | G14: Sch L, Ln 7
A15: Total Current Assets | B15: =SUM(B8:B14) | C15: =SUM(C8:C14) | D15: =SUM(D8:D14) | F15: =SUM(F8:F14) | G15: Sch L, Ln 1-7 | H15: =SUM(H8:H14)
A17: 1100 · Brokerage Account | B17: =' Balance Sheet'!B18 | C17: 0 | D17: =B17+C17 | F17: =D17 | G17: Sch L, Ln 8 | J17: Book FMV — may differ from tax basis if unrealized gains.
A18: 1110 · Municipal Bond Portfolio | B18: =' Balance Sheet'!B19 | C18: 0 | D18: =B18+C18 | F18: =D18 | G18: Sch L, Ln 8 | J18: Tax-exempt bonds — interest flows to Sch K Ln 16a.
A19: Total Investments | B19: =SUM(B17:B18) | C19: =SUM(C17:C18) | D19: =SUM(D17:D18) | F19: =SUM(F17:F18) | G19: Sch L, Ln 8 | H19: =SUM(H17:H18)
A21: 1200 · FF&E (Cost) | B21: =' Balance Sheet'!B23 | C21: 0 | D21: =B21+C21 | F21: =D21 | G21: Sch L, Ln 10a
A22: 1201 · Accum Depr - FF&E | B22: =' Balance Sheet'!B24 | C22: 0 | D22: =B22+C22 | F22: =D22 | G22: Sch L, Ln 10b | J22: Book accum depr — tax accum depr may differ (MACRS)
A23: 1210 · Computer Equipment (Cost) | B23: =' Balance Sheet'!B25 | C23: 0 | D23: =B23+C23 | F23: =D23 | G23: Sch L, Ln 10a
A24: 1211 · Accum Depr - Computers | B24: =' Balance Sheet'!B26 | C24: 0 | D24: =B24+C24 | F24: =D24 | G24: Sch L, Ln 10b
A25: 1220 · Leasehold Improvements (Cost) | B25: =' Balance Sheet'!B27 | C25: 0 | D25: =B25+C25 | F25: =D25 | G25: Sch L, Ln 10a
A26: 1221 · Accum Depr - LHI | B26: =' Balance Sheet'!B28 | C26: 0 | D26: =B26+C26 | F26: =D26 | G26: Sch L, Ln 10b
A27: 1230 · Vehicles (Cost) | B27: =' Balance Sheet'!B29 | C27: 0 | D27: =B27+C27 | F27: =D27 | G27: Sch L, Ln 10a
A28: 1231 · Accum Depr - Vehicles | B28: =' Balance Sheet'!B30 | C28: 0 | D28: =B28+C28 | F28: =D28 | G28: Sch L, Ln 10b | J28: Listed property — verify >50% business use.
A29: Total Fixed Assets (Net) | B29: =SUM(B21:B28) | C29: =SUM(C21:C28) | D29: =SUM(D21:D28) | F29: =SUM(F21:F28) | G29: Sch L, Ln 10c | H29: =SUM(H21:H28)
A31: 1300 · Security Deposits | B31: =' Balance Sheet'!B34 | C31: 0 | D31: =B31+C31 | F31: =D31 | G31: Sch L, Ln 13
A32: 1310 · Organizational Costs (Net) | B32: =' Balance Sheet'!B35 | C32: 0 | D32: =B32+C32 | F32: =D32 | G32: Sch L, Ln 13 | J32: §248 amortization. Verify remaining balance.
A33: Total Other Assets | B33: =SUM(B31:B32) | C33: =SUM(C31:C32) | D33: =SUM(D31:D32) | F33: =SUM(F31:F32) | G33: Sch L, Ln 13 | H33: =SUM(H31:H32)
A35: TOTAL ASSETS | B35: =B15+B19+B29+B33 | C35: =C15+C19+C29+C33 | D35: =D15+D19+D29+D33 | F35: =F15+F19+F29+F33 | G35: Sch L, Ln 15
A37: LIABILITIES (from PBC Balance Sheet — Sch L)
A38: 2000 · Accounts Payable | B38: =' Balance Sheet'!B42 | C38: 0 | D38: =B38+C38 | F38: =D38 | G38: Sch L, Ln 16
A39: 2010 · Accrued Expenses | B39: =' Balance Sheet'!B43 | C39: 0 | D39: =B39+C39 | F39: =D39 | G39: Sch L, Ln 18
A40: 2020 · Payroll Liabilities | B40: =' Balance Sheet'!B44 | C40: 0 | D40: =B40+C40 | F40: =D40 | G40: Sch L, Ln 18
A41: 2030 · Credit Card Payable | B41: =' Balance Sheet'!B45 | C41: 0 | D41: =B41+C41 | F41: =D41 | G41: Sch L, Ln 18
A42: 2040 · Sales Tax Payable | B42: =' Balance Sheet'!B46 | C42: 0 | D42: =B42+C42 | F42: =D42 | G42: Sch L, Ln 18
A43: 2050 · Current Portion - Vehicle Loan | B43: =' Balance Sheet'!B47 | C43: 0 | D43: =B43+C43 | F43: =D43 | G43: Sch L, Ln 17
A44: Other liabilities | B44: =' Balance Sheet'!B51 | D44: =B44+C44 | F44: =D44 | G44: Sch L, Ln 19 | J44: Check §163(j) interest limitation.
A45: 2110 · Vehicle Loan (Net of Current) | B45: =' Balance Sheet'!B52 | C45: 0 | D45: =B45+C45 | F45: =D45 | G45: Sch L, Ln 19
A46: 2120 · Shareholder Loan - Principal Shareholder | B46: =' Balance Sheet'!B53 | C46: 0 | D46: =B46+C46 | F46: =D46 | G46: Sch L, Ln 19 | J46: Debt basis for loss limitation. Document loan terms.
A47: TOTAL LIABILITIES | B47: =SUM(B38:B46) | C47: =SUM(C38:C46) | D47: =SUM(D38:D46) | F47: =SUM(F38:F46) | G47: Sch L, Ln 20 | H47: =SUM(H38:H46)
A49: EQUITY (from PBC Balance Sheet — Sch L)
A50: 3000 · Common Stock | B50: =' Balance Sheet'!B59 | C50: 0 | D50: =B50+C50 | F50: =D50 | G50: Sch L, Ln 22a
A51: 3010 · Additional Paid-In Capital | B51: =' Balance Sheet'!B60 | C51: 0 | D51: =B51+C51 | F51: =D51 | G51: Sch L, Ln 23
A52: 3020 · Retained Earnings (Prior Years) | B52: =' Balance Sheet'!B61 | C52: 0 | D52: =B52+C52 | F52: =D52 | G52: Sch L, Ln 24 | J52: Book-basis RE. Includes cumulative book-tax diffs.
A53: 3030 · Distributions - Principal Shareholder (100%) | B53: =' Balance Sheet'!B62 | C53: 0 | D53: =B53+C53 | F53: =D53 | G53: M-2 / Sch K Ln 16d | J53: Reduces AAA → OAA → basis.
A54: 3031 · Distributions - — (N/A) | B54: =' Balance Sheet'!B63 | C54: 0 | D54: =B54+C54 | F54: =D54 | G54: M-2 / Sch K Ln 16d | J54: Same ordering rules.
A55: 3100 · Net Income (Current Year) | B55: ='P&L'!B63 | C55: 0 | D55: =B55+C55 | F55: =D55 | G55: Sch L, Ln 24 | J55: Ties to P&L net income.
A56: TOTAL EQUITY | B56: =SUM(B50:B55) | C56: =SUM(C50:C55) | D56: =SUM(D50:D55) | F56: =SUM(F50:F55) | G56: Sch L, Ln 25 | H56: =SUM(H50:H55)
A58: TOTAL LIABILITIES & EQUITY | B58: =B47+B56 | C58: =C47+C56 | D58: =D47+D56 | F58: =F47+F56
A59: CHECK: Total Assets − Total L&E (should be zero) | B59: =B35-B58 | C59: =C35-C58 | D59: =D35-D58 | F59: =F35-F58
A62: INCOME STATEMENT — BOOK-TO-TAX ADJUSTMENTS
A63: INCOME
A64: Gross Receipts - Consulting | B64: ='P&L'!B7 | C64: 0 | D64: =B64+C64 | F64: =D64+E64 | G64: Pg 1, Line 1a
A65: Gross Receipts - Software Licensing | B65: ='P&L'!B8 | C65: 0 | D65: =B65+C65 | F65: =D65+E65 | G65: Pg 1, Line 1a
A66: Equipment Rental Income | B66: ='P&L'!B9 | C66: 0 | D66: =B66+C66 | E66: =-IF('Strategy Inputs'!C7<>"",'Strategy Inputs'!C7,'Strategy Inputs'!D7) | F66: =D66+E66 | G66: → Sch K, Ln 3a | J66: SEPARATELY STATED: Rental income reclassed from Page 1 to Schedule K, Line 3a
A67: Returns & Allowances | B67: ='P&L'!B10 | C67: 0 | D67: =B67+C67 | F67: =D67+E67 | G67: Pg 1, Line 1b
A68: Interest Income → See Other Income section below
A69: Dividend Income → See Other Income section below
A70: Capital Gain / (Loss) → See Other Income section below
A71: Gain on Sale of Equipment → See Other Income section below
A72: Tax-Exempt Interest → See Other Income section below
A73: Unrealized Gain on Investments → See Other Income section below
A74: TOTAL INCOME (per WTB) | B74: =SUM(B64:B67) | C74: =SUM(C64:C67) | D74: =SUM(D64:D67) | F74: =SUM(F64:F67) | H74: =SUM(H64:H73)
A76: COST OF GOODS SOLD
A77: Subcontractor Costs | B77: ='P&L'!B13 | C77: 0 | D77: =B77+C77 | F77: =D77+E77 | G77: Pg 1, Ln 2 (Sch A) | J77: Verify 1099-NEC issued for all subs > $600
A78: Software Licenses (Resold) | B78: ='P&L'!B14 | C78: 0 | D78: =B78+C78 | F78: =D78+E78 | G78: Pg 1, Ln 2 (Sch A)
A79: Project Materials | B79: ='P&L'!B15 | C79: 0 | D79: =B79+C79 | F79: =D79+E79 | G79: Pg 1, Ln 2 (Sch A)
A80: TOTAL COGS | B80: =SUM(B77:B79) | C80: =SUM(C77:C79) | D80: =SUM(D77:D79) | F80: =SUM(F77:F79) | G80: Pg 1, Line 2 | H80: =SUM(H77:H79)
A82: OFFICER COMPENSATION
A83: Officer Comp - [SH1 Name] ([Title], [%]%) | D83: =B83+C83 | F83: =D83+E83 | G83: Pg 1, Line 7 | J83: REASONABLE COMP: $95K comp vs $180K distributions — document comp analysis.
A84: Officer Comp - [SH2 Name] ([Title], [%]%) | C84: 0 | D84: =B84+C84 | F84: =D84+E84 | G84: Pg 1, Line 7 | J84: REASONABLE COMP: $65K — verify duties, hours, industry comparisons.
A85: TOTAL OFFICER COMP | B85: =SUM(B83:B84) | D85: =SUM(D83:D84) | F85: =SUM(F83:F84) | G85: Pg 1, Line 7 | H85: =SUM(H83:H84)
A87: DEDUCTIONS
A88: Health Insurance (all staff) | B88: ='P&L'!B21 | C88: 0 | D88: =B88+C88 | F88: =D88+E88 | G88: Pg 1, Line 8 | J88: Reconcile to W-3. Needed for §199A W-2 wage calculation.
A89: Payroll Taxes (FICA/FUTA) | B89: ='P&L'!B22 | C89: 0 | D89: =B89+C89 | F89: =D89+E89 | G89: Pg 1, Line 12 | J89: Employer FICA/FUTA/SUTA. Tie to 941s/940.
A90: 401K Retirement Program | B90: ='P&L'!B23 | C90: 0 | D90: =B90+C90 | F90: =D90+E90 | G90: Pg 1, Line 18 | J90: Staff-only health insurance. Fully deductible.
A91: Payroll Processing Fees | B91: ='P&L'!B24 | C91: 0 | D91: =B91+C91 | E91: =-D91 | F91: =D91+E91 | G91: NOT on 1120-S → W-2 / K-1 | H91: =D91 | I91: M-1 Ln 3 | J91: >2% SH HEALTH INS: Cannot deduct on 1120-S. Added to officer W-2 Box 1, deducted on 1040.
A92: Computer Software & Supplies (IT) | B92: ='P&L'!B25 | C92: 0 | D92: =B92+C92 | F92: =D92+E92 | G92: Pg 1, Line 17 | J92: Verify within deductible limits.
A93: Rent – 540 NE 4th Street LLC | B93: ='P&L'!B26 | C93: 0 | D93: =B93+C93 | F93: =D93+E93 | G93: Pg 1, Line 11
A94: Payroll | B94: ='P&L'!B19 | D94: =B94+C94 | F94: =D94+E94 | G94: Pg 1, Line 19
A95: Bonus | B95: ='P&L'!B20 | C95: 0 | D95: =B95+C95 | F95: =D95+E95 | G95: Pg 1, Line 19
A96: Telephone & Internet | B96: ='P&L'!B29 | C96: 0 | D96: =B96+C96 | F96: =D96+E96 | G96: Pg 1, Line 19
A97: — | B97: ='P&L'!B30 | C97: 0 | D97: =B97+C97 | F97: =D97+E97 | G97: Pg 1, Line 16
A98: Dues & Subscriptions | B98: ='P&L'!B31 | C98: 0 | D98: =B98+C98 | F98: =D98+E98 | G98: Pg 1, Line 19
A99: Meals & Entertainment (combined) | B99: ='P&L'!B32 | C99: =4592+509 | D99: =B99+C99 | E99: =-D99*0.5 | F99: =D99+E99 | G99: Pg 1 Ln 19 (50% only) | H99: =D99*0.5 | I99: M-1 Ln 3c | J99: 50% MEALS: $18K book × 50% = $9K nondeductible. Full amount stays in Col D but only $9K allowed. M-1 add-back $9K.
A100: Office Meals | B100: ='P&L'!B33 | D100: =B100+C100 | F100: =D100+E100 | G100: N/A — $0 on return | H100: =D100 | I100: M-1 Ln 3d | J100: 100% NONDEDUCTIBLE per §274(a). Sch K adj zeroes it out. Full M-1 add-back.
A101: Travel | B101: ='P&L'!B34 | C101: 0 | D101: =B101+C101 | F101: =D101+E101 | G101: Pg 1, Line 19 | J101: Verify business purpose documentation.
A102: Consulting Fees | B102: ='P&L'!B35 | C102: 0 | D102: =B102+C102 | F102: =D102+E102 | G102: Pg 1, Line 19
A103: Recruitment Fees | B103: ='P&L'!B36 | C103: 0 | D103: =B103+C103 | F103: =D103+E103 | G103: Pg 1, Line 19
A104: Auto Expense | B104: ='P&L'!B37 | C104: 0 | D104: =B104+C104 | F104: =D104+E104 | G104: Pg 1, Line 19 | J104: Verify business use %. Listed property > 50% test.
A105: Book Depreciation - Vehicle | B105: ='P&L'!B38 | C105: 0 | D105: =B105+C105 | E105: =-D105 | F105: =D105+E105 | G105: Removed → tax depr | H105: =D105 | I105: M-1 Ln 3a | J105: BOOK DEPR REMOVED: Tax MACRS replaces book.
A106: Book Depreciation (single line per PBC) | B106: ='P&L'!B39 | C106: 0 | D106: =B106+C106 | E106: =-D106 | F106: =D106+E106 | G106: Removed → tax depr | H106: =D106 | I106: M-1 Ln 3a | J106: BOOK DEPR REMOVED: Book SL replaced by MACRS 7-yr.
A107: Book Depreciation – Office & Computer Equipment | B107: ='P&L'!B40 | C107: 0 | D107: =B107+C107 | E107: =-D107 | F107: =D107+E107 | G107: Removed → tax depr | H107: =D107 | I107: M-1 Ln 3a | J107: BOOK DEPR REMOVED: Book SL replaced by MACRS 5-yr.
A108: Book Depreciation - Leasehold | B108: ='P&L'!B41 | C108: 0 | D108: =B108+C108 | E108: =-D108 | F108: =D108+E108 | G108: Removed → tax depr | H108: =D108 | I108: M-1 Ln 3a | J108: BOOK DEPR REMOVED: Book SL replaced by 15-yr MACRS (QIP).
A109: Tax Depreciation - MACRS/Bonus (Form 4562) | F109: ='Strategy Inputs'!C30 | G109: Pg 1, Line 14 | H109: =-'Strategy Inputs'!C30 | I109: M-1 Ln 6a | J109: TAX DEPR ADDED: $75K from Form 4562. Not on books → M-1 subtraction.
A110: §179 Deduction | F110: ='Strategy Inputs'!C31 | G110: → Sch K, Ln 11 | H110: =-'Strategy Inputs'!C31 | I110: M-1 Ln 6b | J110: SEPARATELY STATED: §179 → Sch K Ln 11 → K-1 Box 11. SH-level income limit. M-1 subtraction.
A111: Liability Insurance | B111: ='P&L'!B42 | C111: 0 | D111: =B111+C111 | F111: =D111+E111 | G111: Pg 1, Line 19
A112: Workers Comp Insurance | B112: ='P&L'!B43 | C112: 0 | D112: =B112+C112 | F112: =D112+E112 | G112: Pg 1, Line 19
A113: Investment Management Fees (Portfolio) | B113: ='P&L'!B44 | C113: 0 | D113: =B113+C113 | E113: =-D113 | F113: =D113+E113 | G113: → Sch K, Ln 12c | H113: =D113 | I113: M-1 Ln 3 / K-12c | J113: PORTFOLIO DEDUCTION: Investment mgmt fees → Sch K Ln 12c. Not Pg 1 ordinary deduction.
...

Sheet Adjusting Entries
A1: [ENTITY NAME] — Adjusting Journal Entries
A2: Form 1120-S / 1065 — Tax Year Ended November 30, 2025
A3: [ENTITY NAME] — EIN: [XX-XXXXXXX]
A4: Each AJE represents one adjustment from the client's books (PBC) to the tax return. Yellow = document you need from client or workpapers. Green = verified/complete.
A6: AJE # | B6: Adjustment Description | C6: PBC Account / Reference | D6: Document Needed (Get This →) | E6: DR Amount | F6: CR Amount | G6: Net Effect on Taxable Inc | H6: Ties To (Return Line) | I6: WTB Row | J6: Status / Preparer Notes
B7: SECTION 1: SEPARATELY STATED INCOME ITEMS (Book → Schedule K)
A8: AJE-01 | B8: Reclassify equipment rental income to Sch K Ln 3 | C8: 4020 · Equipment Rental PBC P&L r9 | D8: Rental agreement / lease contract showing rental activity. Need to split gross income ($85K) and expenses ($35K) for K Ln 3a/3b. | E8: =IF('Strategy Inputs'!C7<>"",'Strategy Inputs'!C7,'Strategy Inputs'!D7) | F8: =E8 | G8: 0 | H8: Sch K Ln 3a (income) Sch K Ln 3b (expenses) | I8: WTB r66 | J8: Reclass only — removes from Pg 1 gross receipts, moves to K Ln 3. Net effect on taxable income = $0. Also need rental expense detail for Ln 3b ($35K). Verify rental is equipment, NOT real estate (real estate → Form 8825).
A9: AJE-02 | B9: Reclassify interest income to Sch K Ln 4 | C9: 7000 · Interest Income PBC P&L r53 | D9: 1099-INT from bank(s). Verify amount matches PBC. If multiple banks, sum all 1099-INTs. | E9: =IF('Strategy Inputs'!C9<>"",'Strategy Inputs'!C9,'Strategy Inputs'!D9) | F9: =E9 | G9: 0 | H9: Sch K Ln 4 / K-1 Box 4 | I9: WTB r68 | J9: Reclass from other income to separately stated. Must match 1099-INT(s). If client has multiple bank accounts, reconcile each.
A10: AJE-03 | B10: Reclassify dividend income to Sch K Ln 5a/5b | C10: 7010 · Dividend Income PBC P&L r54 | D10: 1099-DIV from brokerage. CRITICAL: Need Box 1b (qualified dividends) for K Ln 5b. Total ordinary = Ln 5a, qualified subset = Ln 5b. | E10: =IF('Strategy Inputs'!C10<>"",'Strategy Inputs'!C10,'Strategy Inputs'!D10) | F10: =E10 | G10: 0 | H10: Sch K Ln 5a (total) Sch K Ln 5b (qualified) | I10: WTB r69 | J10: Ordinary dividends = $8,500 (Ln 5a). Qualified = $6,800 (Ln 5b — verify against 1099-DIV Box 1b). Qualified must be ≤ ordinary.
A11: AJE-04 | B11: Reclassify LTCG to Sch K Ln 8a | C11: 7020 · Capital Gain PBC P&L r56 | D11: 1099-B from brokerage + Form 8949 / Schedule D. Need: purchase date, sale date, proceeds, cost basis for EACH transaction. Verify LTCG (held >1 yr). | E11: =IF('Strategy Inputs'!C12<>"",'Strategy Inputs'!C12,'Strategy Inputs'!D12) | F11: =E11 | G11: 0 | H11: Sch K Ln 8a / Sch D Form 8949 | I11: WTB r70 | J11: $12K net LTCG. Need 1099-B for each sale. If any STCG, separate to K Ln 7. Watch for wash sale adjustments (1099-B Box 1g).
A12: AJE-05 | B12: Adjust equipment sale gain: book → tax (§1231/§1245 split) | C12: 7030 · Gain on Sale PBC P&L r57 | D12: Form 4797 + Fixed asset schedule. Need: original cost, date placed in service, date sold, sale price, tax accum depr (MACRS). §1245 recapture portion vs §1231 gain. | E12: =IF('Strategy Inputs'!C13<>"",'Strategy Inputs'!C13,'Strategy Inputs'!D13) | F12: =E12 | G12: =E12-F12 | H12: Form 4797 Sch K Ln 9 (§1231) Pg 1 Ln 4 (§1245) | I12: WTB r71 | J12: Book gain $15K. Tax split: $10K §1245 recapture (stays on Pg 1) + $5K §1231 gain (→ K Ln 9). Need TAX cost basis and TAX accum depr — book depr differs from MACRS. Form 4797 required.
B13: SECTION 2: NONDEDUCTIBLE EXPENSES (Book Expense → $0 or Partial on Return)
A14: AJE-06 | B14: >2% Shareholder health insurance — remove from Pg 1 deductions | C14: 6031 · Officer Health Ins PBC P&L r24 | D14: Health insurance invoices/premiums paid for >2% SHs. Amount must be added to officers' W-2 Box 1. Verify W-2 includes this amount. Officers deduct on personal 1040 Ln 17. | E14: =IF('Strategy Inputs'!C20<>"",'Strategy Inputs'!C20,'Strategy Inputs'!D20) | F14: 0 | G14: =E14 | H14: M-1 Ln 3b K Ln 16c (nondeductible) W-2 Box 1 | I14: WTB r91 | J14: NOT deducted on 1120-S. Added to officer W-2 Box 1 (not Box 12, Code DD). Officer deducts on personal 1040 Schedule 1, Line 17. Verify payroll company added it correctly.
A15: AJE-07 | B15: Meals — 50% disallowance (book $18K → tax deduction $9K) | C15: 6300 · Business Meals PBC P&L r32 | D15: Meal receipts / expense reports. Verify ALL are business meals with business purpose documented (who, what, where, why). Restaurant vs non-restaurant distinction no longer matters post-2022. | E15: =IF('Strategy Inputs'!C21<>"",'Strategy Inputs'!C21,'Strategy Inputs'!D21) | F15: 0 | G15: =E15 | H15: Pg 1 Ln 19 (50% deductible) M-1 Ln 3c (50% addback) K Ln 16c (nondeductible) | I15: WTB r99 | J15: $18K book × 50% = $9K deductible on Pg 1 Ln 19 + $9K nondeductible on M-1/K Ln 16c. The 50% deductible portion stays on Pg 1. The 50% disallowed is the M-1 addback.
A16: AJE-08 | B16: Entertainment — 100% disallowed (book $12K → tax $0) | C16: 6310 · Entertainment PBC P&L r33 | D16: Entertainment receipts. Verify client properly separates meals AT entertainment events (those meals ARE 50% deductible). Pure entertainment = 100% nondeductible post-TCJA. | E16: =IF('Strategy Inputs'!C22<>"",'Strategy Inputs'!C22,'Strategy Inputs'!D22) | F16: 0 | G16: =E16 | H16: M-1 Ln 3d K Ln 16c (nondeductible) | I16: WTB r100 | J16: $0 on return. Full addback. Ask client: did any "entertainment" include separately invoiced food? If so, food portion is 50% deductible.
A17: AJE-09 | B17: Charitable contributions — remove from Pg 1, separately state on K Ln 12a | C17: 6900 · Charitable PBC P&L r45 | D17: Donation receipts / acknowledgment letters. Cash >$250 needs written acknowledgment. Noncash >$500 needs Form 8283. Verify all are to qualified §501(c)(3) organizations. | E17: =IF('Strategy Inputs'!C17<>"",'Strategy Inputs'!C17,'Strategy Inputs'!D17) | F17: 0 | G17: =E17 | H17: K Ln 12a / K-1 Box 12A M-1 Ln 3e | I17: WTB r114 | J17: ADDBACK — removed from entity Pg 1 deductions. Separately stated on K Ln 12a, flows to SH personal Sch A. From M-1 perspective, this is a Ln 3 addback. SH deducts on personal return subject to AGI limits.
A18: AJE-10 | B18: Political contributions — 100% nondeductible | C18: 6910 · Political PBC P&L r46 | D18: Cancelled checks / bank statements showing payment to political organizations, PACs, lobbying firms. No supporting receipt needed — just verify amounts. | E18: =IF('Strategy Inputs'!C23<>"",'Strategy Inputs'!C23,'Strategy Inputs'!D23) | F18: 0 | G18: =E18 | H18: M-1 Ln 3f K Ln 16c (nondeductible) | I18: WTB r115 | J18: $0 on return. §162(e) — political and lobbying expenses are permanently nondeductible. Reduces SH basis via K Ln 16c.
A19: AJE-11 | B19: Penalties & fines — 100% nondeductible | C19: 6920 · Penalties PBC P&L r47 | D19: Penalty notices / invoices. Check if any are "restitution" payments — those MAY be deductible under §162(f) exception. Get the actual notice to determine. | E19: =IF('Strategy Inputs'!C24<>"",'Strategy Inputs'!C24,'Strategy Inputs'!D24) | F19: 0 | G19: =E19 | H19: M-1 Ln 3g K Ln 16c | I19: WTB r116 | J19: §162(f) — fines/penalties paid to government for violation of law = nondeductible. Exception: amounts for restitution or compliance. Get the actual penalty letter.
A20: AJE-12 | B20: Life insurance premiums (corp beneficiary) — nondeductible | C20: 6930 · Life Insurance PBC P&L r48 | D20: Insurance policy + premium statement. CRITICAL: Verify corp is beneficiary (not SH). If SH is beneficiary, it's compensation — different treatment entirely (add to W-2). | E20: =IF('Strategy Inputs'!C25<>"",'Strategy Inputs'!C25,'Strategy Inputs'!D25) | F20: 0 | G20: =E20 | H20: M-1 Ln 3h K Ln 16c | I20: WTB r117 | J20: §264(a)(1) — premiums on policies where corp is beneficiary are nondeductible. If proceeds received, they're tax-exempt (§101) → K Ln 16b / OAA.
A21: AJE-13 | B21: Club dues (country club) — nondeductible | C21: 6940 · Club Dues PBC P&L r49 | D21: Club membership invoices / statements. NOTE: meals consumed at the club are SEPARATELY deductible at 50%. Ask client to split if not already separated in books. | E21: =IF('Strategy Inputs'!C26<>"",'Strategy Inputs'!C26,'Strategy Inputs'!D26) | F21: 0 | G21: =E21 | H21: M-1 Ln 3i K Ln 16c | I21: WTB r118 | J21: §274(a)(3) — club dues nondeductible since 1993. Country clubs, social clubs, athletic clubs, airline clubs. Ask: any separate meal charges billed by the club?
B22: SECTION 3: DEPRECIATION — BOOK TO TAX (Most Common Adjustment)
A23: AJE-14 | B23: Remove ALL book depreciation (replaced by tax MACRS) | C23: 6510-6620 · Book Depr PBC P&L r38-41 | D23: Book depreciation schedule / fixed asset report from client's accounting system. Verify total matches PBC: Vehicle $8K + FF&E $22K + Computers $18K + LHI $12K = $60K. | E23: =IF('Strategy Inputs'!C29<>"",'Strategy Inputs'!C29,'Strategy Inputs'!D29) | F23: 0 | G23: =E23 | H23: M-1 Ln 3a (addback) Removed from Pg 1 | I23: WTB r105-108 | J23: Book SL depr is REMOVED. Tax MACRS (AJE-15) replaces it. Net difference = M-1 adjustment. Verify book schedule ties to PBC exactly.
A24: AJE-15 | B24: Add tax depreciation — MACRS / bonus (Form 4562) | C24: Form 4562 Tax depr software | D24: Form 4562 (Depreciation & Amortization). Run tax depreciation software (CCH, Lacerte, UltraTax). Need asset-by-asset detail: cost, date in service, method (200DB/150DB/SL), convention, life, prior depr. | E24: 0 | F24: ='Strategy Inputs'!C30 | H24: Form 4562 Pg 1 Ln 14 M-1 Ln 6a | I24: WTB r109 | J24: $75K MACRS replaces $60K book depr. Net extra deduction = $15K. AJE-14 + AJE-15 together = net depreciation timing difference. Form 4562 is the support.
A25: AJE-16 | B25: §179 immediate expensing (Form 4562 Part I) | C25: Form 4562 Part I Election on return | D25: Form 4562 Part I. Asset must be §179 eligible (tangible personal property, off-the-shelf software, qualified improvement property). Need asset ID, cost, date placed in service. | E25: 0 | F25: ='Strategy Inputs'!C31 | H25: K Ln 11 / K-1 Box 11 Form 4562 Part I M-1 Ln 6b | I25: WTB r110 | J25: $17K §179. Separately stated on K (not on Pg 1). Subject to business income limitation at SH level. 2024 limit = $1,220,000. Phase-out begins at $3,050,000.
B26: SECTION 4: TAX-EXEMPT & BOOK-ONLY ITEMS (Remove from Taxable Income)
A27: AJE-17 | B27: Tax-exempt municipal bond interest — remove from taxable income | C27: 7200 · Tax-Exempt Muni PBC P&L r60 | D27: 1099-INT Box 8 (tax-exempt interest) from brokerage / bond custodian. Also check Box 9 for AMT-specific muni interest (private activity bonds). | E27: =IF('Strategy Inputs'!C15<>"",'Strategy Inputs'!C15,'Strategy Inputs'!D15) | F27: 0 | G27: =-E27 | H27: K Ln 16a / K-1 Box 16A M-1 Ln 5a M-2 → OAA | I27: WTB r72 | J27: On books as income, NOT on tax return. Increases SH basis (7203) and goes to OAA (not AAA) on M-2. Verify against 1099-INT Box 8.
A28: AJE-18 | B28: Unrealized gain on investments — remove (book only, not realized for tax) | C28: 7300 · Unrealized Gain PBC P&L r61 | D28: Brokerage statement showing beginning vs ending market value. Verify this is unrealized (not sold). If client uses mark-to-market accounting, need year-end portfolio valuation. | E28: =IF('Strategy Inputs'!C16<>"",'Strategy Inputs'!C16,'Strategy Inputs'!D16) | F28: 0 | G28: =-E28 | H28: M-1 Ln 5b No return line | I28: WTB r73 | J28: GAAP requires mark-to-market; tax doesn't recognize until sold. This reverses when positions are eventually sold. Track cumulative unrealized for Sch L book vs tax difference.
B30: SECTION 5: ADDITIONAL DOCUMENTS NEEDED (Not AJEs — Support for Return)
A31: DOC-01 | B31: Officer compensation — reasonable comp analysis | C31: Payroll records / W-2s / ADP report | D31: W-2s for all officers (Principal Shareholder $95K, — $65K). Pg 1 Ln 7/8. Verify comp is "reasonable" — IRS scrutinizes S-corp officer comp heavily. | H31: Pg 1 Ln 7-8
A32: DOC-02 | B32: Payroll tax summary | C32: Form 941 (quarterly) / W-3 / state returns | D32: Annual W-3, quarterly 941s. Tie total wages to P&L. Verify payroll taxes match 941 filings. Also need for §199A W-2 wages (K-1 Box 17W). | H32: Pg 1 Ln 8 / K-1 Box 17W
A33: DOC-03 | B33: Vehicle use log / mileage records | C33: IRS mileage log or fleet tracking | D33: If claiming actual expenses, need business use %. If >50% business, MACRS allowed. If ≤50%, must use SL. Listed property rules apply. Form 4562 Part V. | H33: Form 4562 Part V
A34: DOC-04 | B34: Loan amortization schedule(s) | C34: Bank statements / amort schedules | D34: LOC and vehicle loan: beginning balance, payments, interest, ending balance. Verify interest expense on P&L ($8,200 LOC + $2,400 vehicle = $10,600 per PBC). | H34: Pg 1 Ln 13 / Sch L
A35: DOC-05 | B35: Prior-year tax return (complete) | C35: 1120-S + all schedules + K-1s | D35: CRITICAL: Need prior-year Sch L ending balances (→ this year BOY), prior-year 7203 ending basis, prior-year AAA/OAA balances. Without this, multiple tabs cannot be completed. | H35: Sch L BOY / M-2 BOY / 7203 Ln 1
A36: DOC-06 | B36: Fixed asset / depreciation schedule | C36: Tax depreciation software output | D36: Complete asset list with tax basis, MACRS method, convention, life, prior depr, current depr. Drives Form 4562 and Sch L fixed assets. Verify disposals. | H36: Form 4562 / Sch L Ln 10
A37: DOC-07 | B37: Distribution records | C37: Board minutes / bank records | D37: Dates and amounts of each distribution to each SH. Verify J ($180K) + S ($120K) = $300K total. Pro rata to ownership? If not, risk second class of stock issue. | H37: K Ln 16d / M-2 / 7203
A38: DOC-08 | B38: Shareholder loan documentation | C38: Promissory note / repayment records | D38: Principal Shareholder $25K loan: note terms, interest rate, repayment schedule. Is there economic substance? Bona fide debt for 7203 debt basis? Below-market interest → §7872 imputed interest. | H38: 7203 Part II / Sch L Ln 19
A39: DOC-09 | B39: Entity-level state returns / estimates | C39: State return info / estimate payments | D39: Some states have entity-level taxes (e.g., CA $800 min franchise tax, PTE elections). Get state filing requirements and any estimated tax payments. | H39: State returns
A40: DOC-10 | B40: §199A qualified business income info | C40: QBI worksheets | D40: For each SH: QBI (usually = OBI), W-2 wages, UBIA of qualified property. SH takes 20% deduction on personal return. Need to report on K-1 Box 17 codes V/W/X. | H40: K-1 Box 17V/W/X
B42: CHECKSUM — AJE NET EFFECT PROOF
B43: Total DR (all AJEs) | E43: =SUM(E8:E28)
B44: Total CR (all AJEs) | F44: =SUM(F8:F28)
B45: Net effect on taxable income (sum of Col G) | G45: =SUM(G8:G28)
B46: Book NI per PBC | G46: ='P&L'!B63
B47: Book NI + Net AJE effect = should approach income per return | G47: =G46+G45
B48: Income per return (WTB M-1 Ln 7) | G48: ='Working Trial Balance'!F168
B49: Variance (AJE proof − M-1 Ln 7) | G49: =G47-G48 | H49: =IF(G49=0,"✓ TIES","✗ OFF — check AJEs vs WTB")
A51: NOTE: The AJE proof ties to the M-1 bridge (Book NI + addbacks + removals + tax depr adjustments = income per return). Reclassifications from Pg 1 to Sch K show net $0. Addbacks (nondeductibles + items separately stated on K) show positive. Tax deductions not on books show negative.
A52: For a 1065 (partnership): Same adjustments apply. Replace 'Sch K Ln' references with 1065 Sch K lines. Replace 'K-1 Box' with 1065 K-1 boxes. Replace M-2 (AAA/OAA) with partners' capital account analysis.

Sheet Schedule K
A1: [ENTITY NAME] — Schedule K — Shareholders' Pro Rata Share Items
A2: Tax Year Ended [MM/DD/YYYY]
A3: [ENTITY NAME] (S-Corp) — EIN: [XX-XXXXXXX]
A5: SHAREHOLDER OWNERSHIP
A6: Shareholder | B6: Principal Shareholder (100%) | C6: — (N/A)
A7: [SH1 Name] — Ownership % | B7: 1 | C7: 0
A9: K Line | B9: Description | C9: WTB Row / Source | D9: Amount | E9: K-1 Box | F9: Principal Shareholder (100%) | G9: — (N/A) | H9: Notes / Typical Items
B10: INCOME (LOSS)
A11: 1 | B11: Ordinary business income (loss) | C11: WTB r136, Col D | D11: ='Working Trial Balance'!F155 | E11: Box 1 | F11: =D11*B7 | G11: =D11*C7 | H11: Pg 1, Ln 21 → K Ln 1. Same amount.
A12: 2 | B12: Net rental real estate income (loss) | C12: Form 8825 | E12: Box 2 | H12: ⚠ MANUALLY ENTER — From Form 8825 if applicable
A13: 3a | B13: Net rental income — other (gross income) | C13: WTB r66 (−C66) | D13: =-'Working Trial Balance'!C66 | E13: Box 3 | F13: =D13*B7 | G13: =D13*C7 | H13: Rental income moved from Pg 1 to K. Desert Peak: $85K equipment rental.
A14: 3b | B14: Net rental income — other (expenses) | C14: WTB r121 | D14: ='Working Trial Balance'!D121*-1 | E14: Box 3 | F14: =D14*B7 | G14: =D14*C7 | H14: Rental expenses. Desert Peak: $35K equipment rental expense.
A15: 3c | B15: Net rental income — other (net) | C15: Ln 3a + Ln 3b | D15: =D13+D14 | E15: Box 3 | F15: =D15*B7 | G15: =D15*C7 | H15: Net = income − expenses. Should tie to M-2 AAA rental line.
A16: 4 | B16: Interest income | C16: WTB r68 (−C68) | D16: ='Working Trial Balance'!F133 | E16: Box 4 | F16: =D16*B7 | G16: =D16*C7 | H16: Bank interest, etc. Removed from Pg 1, separately stated on K.
A17: 5a | B17: Ordinary dividends | C17: WTB r69 (−C69) | E17: Box 5a | F17: =D17*B7 | G17: =D17*C7 | H17: All dividends. Qualified portion goes to 5b.
A18: 5b | B18: Qualified dividends | C18: PBC / 1099-DIV | E18: Box 5b | F18: =D18*B7 | G18: =D18*C7 | H18: ⚠ MANUALLY ENTER — Verify against 1099-DIV. Must be ≤ Line 5a.
A19: 6 | B19: Royalties | E19: Box 6 | H19: Oil/gas, intellectual property, etc.
A20: 7 | B20: Net short-term capital gain (loss) | C20: Form 8949 / Sch D | D20: ='Working Trial Balance'!F135 | E20: Box 7 | H20: From Sch D. Holding period ≤ 1 year.
A21: 8a | B21: Net long-term capital gain (loss) | C21: WTB r70 (−C70) | D21: =-'Working Trial Balance'!C70 | E21: Box 8a | F21: =D21*B7 | G21: =D21*C7 | H21: From Sch D. Desert Peak: $12K LTCG from stock sales.
A22: 8b | B22: Collectibles (28%) gain (loss) | E22: Box 8b | H22: Art, antiques, precious metals, etc.
A23: 8c | B23: Unrecaptured §1250 gain | E23: Box 8c | H23: Gain on sale of depreciable real property. From Form 4797.
A24: 9 | B24: Net §1231 gain (loss) | C24: WTB r71 (−C71) | D24: =-'Working Trial Balance'!C71 | E24: Box 9 | F24: =D24*B7 | G24: =D24*C7 | H24: From Form 4797. Desert Peak: $5K §1231 portion of equipment sale.
A25: 10 | B25: Other income (loss) | E25: Box 10 | H25: Cancellation of debt, gambling, etc. Attach statement.
B26: DEDUCTIONS
A27: 11 | B27: §179 deduction | C27: WTB r110 | D27: ='Working Trial Balance'!D110 | E27: Box 11 | F27: =D27*B7 | G27: =D27*C7 | H27: From Form 4562. Desert Peak: $17K. Subject to business income limitation.
A28: 12a | B28: Charitable contributions | C28: WTB r114 (F col) | D28: ='Working Trial Balance'!F114 | E28: Box 12A | F28: =D28*B7 | G28: =D28*C7 | H28: Cash + noncash. 50%/30%/20% AGI limits apply at SH level. Desert Peak: $15K.
A29: 12b | B29: Investment interest expense | E29: Box 12H | H29: Form 4952 at SH level. Margin interest, etc.
A30: 12c(1) | B30: Net §59(e)(2) expenditures — Type | E30: Box 12I/J | H30: Intangible drilling, mining, research — SH can elect to amortize.
A31: 12c(2) | B31: Net §59(e)(2) expenditures — Amount | E31: Box 12I/J
A32: 12d | B32: Other deductions | E32: Box 12 | H32: Attach statement. Soil/water conservation, etc.
A33: 13a | B33: Low-income housing credit (§42(j)(5)) | E33: Box 13A
A34: 13b | B34: Low-income housing credit (other) | E34: Box 13B
A35: 13c | B35: Qualified rehabilitation expenditures | E35: Box 13C
A36: 13d | B36: Other rental real estate credits | E36: Box 13D
A37: 13e | B37: Other rental credits | E37: Box 13E
A38: 13f | B38: Biofuel producer credit | E38: Box 13F
A39: 13g | B39: Other credits | E39: Box 13G | H39: R&D credit (Form 6765), W.O.T.C., etc. Attach statement.
B40: FOREIGN TRANSACTIONS
A41: 14a | B41: Name of country or U.S. possession | E41: Box 14 | H41: If foreign income/taxes paid
A42: 14b | B42: Gross income — general category | E42: Box 14
A43: 14c | B43: Gross income — other | E43: Box 14
A44: 14d | B44: Foreign taxes paid — general | E44: Box 14K
A45: 14e | B45: Foreign taxes accrued — general | E45: Box 14L
A46: 14f | B46: Reduction in taxes available for credit | E46: Box 14
A47: 14g | B47: Other foreign tax information | E47: Box 14N+ | H47: Attach statement with all Sec. 901/960 detail
B48: ALTERNATIVE MINIMUM TAX (AMT) ITEMS
A49: 15a | B49: Post-1986 depreciation adjustment | E49: Box 15A | H49: MACRS vs ADS difference. AMT uses 150% DB or ADS.
A50: 15b | B50: Adjusted gain or loss | E50: Box 15B | H50: AMT-basis gain/loss on asset dispositions
A51: 15c | B51: Depletion (other than oil & gas) | E51: Box 15C
A52: 15d | B52: Oil, gas & geothermal — gross income | E52: Box 15D
A53: 15e | B53: Oil, gas & geothermal — deductions | E53: Box 15E
A54: 15f | B54: Other AMT items | E54: Box 15F | H54: Attach statement
B55: ITEMS AFFECTING SHAREHOLDER BASIS
A56: 16a | B56: Tax-exempt interest income | C56: WTB r72 (−C72) | D56: =-'Working Trial Balance'!C72 | E56: Box 16A | F56: =D56*B7 | G56: =D56*C7 | H56: Muni bonds. Increases SH basis but not taxable. → OAA, not AAA.
A57: 16b | B57: Other tax-exempt income | E57: Box 16B | H57: PPP forgiveness, life ins proceeds. → OAA.
A58: 16c | B58: Nondeductible expenses | C58: WTB M-1 addbacks | D58: ='Working Trial Balance'!H99+'Working Trial Balance'!H115+'Working Trial Balance'!H116+'Working Trial Balance'!H117+'Working Trial Balance'!H118+'Working Trial Balance'!D91 | E58: Box 16C | F58: =D58*B7 | G58: =D58*C7 | H58: Total of all nondeductible items: meals 50%, entertainment, political, penalties, life ins, club dues, >2% SH health. Reduces SH basis, does NOT reduce AAA.
A59: 16d | B59: Distributions (cash & property) | C59: WTB r127 | D59: =-' Balance Sheet'!E62 | E59: Box 16D | F59: =D59*B7 | G59: =D59*C7 | H59: Total distributions to all SHs
A60: 16e | B60: Repayment of SH loans | E60: Box 16E | H60: Reduces SH debt basis.
B61: OTHER INFORMATION
A62: 17a | B62: Investment income | E62: Box 17A | H62: Interest + dividends + short-term CG. For investment interest expense limitation at SH level.
A63: 17b | B63: Investment expenses | E63: Box 17B | H63: Expenses related to investment income
A64: 17c | B64: Dividend equivalents | E64: Box 17C
A65: 17d | B65: Other information — §199A QBI | E65: Box 17V | H65: Qualified Business Income for §199A deduction at SH level. Usually = OBI for most S-corps.
A66: 17e | B66: Other information — §199A W-2 wages | E66: Box 17W | H66: ⚠ MANUALLY ENTER — From payroll records / Form W-3
A67: 17f | B67: Other information — §199A UBIA | E67: Box 17X | H67: ⚠ MANUALLY ENTER — From fixed asset schedule / depreciation report
A68: 17g | B68: Other information — additional codes | E68: Box 17 | H68: Codes AA-AJ as needed. Attach detail.
A70: TOTAL | B70: Total Sch K Income (Ln 1 through Ln 10 minus Ln 11-12a) | D70: =D11+D15+D16+D17+D21+D24-D27-D28
A72: TIE-OUT CHECKS
B73: K Ln 1 = WTB OBI (Pg 1 Ln 21) | D73: =D11-'Working Trial Balance'!F155 | E73: =IF(D73=0,"✓ TIES","✗ OFF")
B74: K Ln 3c net rental = M-2 rental (row 10) | D74: =D15-'Schedule M-2'!B10 | E74: =IF(D74=0,"✓ TIES","✗ OFF")
B75: K Ln 16d distributions = M-2 distributions | D75: =D59-'Schedule M-2'!B34 | E75: =IF(D75=0,"✓ TIES","✗ OFF")
B76: K Ln 16a tax-exempt = M-2 OAA increase | D76: =D56-'Schedule M-2'!C16 | E76: =IF(D76=0,"✓ TIES","✗ OFF")
B77: Ownership % check (should = 100%) | D77: =B7+C7 | E77: =IF(D77=1,"✓ 100%","✗ OFF")

Sheet Schedule M-1
A1: [ENTITY NAME] — Schedule M-1 — Reconciliation of Income (Loss) per Books With Income (Loss) per Return
A2: Tax Year Ended [MM/DD/YYYY]
A3: [ENTITY NAME] (S-Corp) — EIN: [XX-XXXXXXX]
A4: M-1 reconciles book net income → income per return. If gross receipts > $250K AND total assets > $10M at year-end, use Schedule M-3 instead.
A6: M-1 Line | B6: Description | C6: WTB Row / Source | D6: Amount | E6: Typical Items (Highlight = common for most clients) | F6: Ties To | G6: Notes
A7: 1 | B7: Net income (loss) per books | C7: WTB r139 / PBC P&L | D7: ='P&L'!B63 | E7: ALWAYS: Net income from financial statements / QuickBooks / PBC P&L. This is BOOK income, not tax. | F7: PBC P&L bottom line | G7: Must match P&L exactly. If client provides adjusted TB, may need to reconcile.
A8: 2 | B8: Income included on Sch K not on books | E8: RARE for S-corps. Example: income recognized on return earlier than books (installment sale reversal). Most clients = $0. | F8: Sch K detail | G8: Leave blank unless you have a specific item.
B9: LINE 3: EXPENSES ON BOOKS NOT DEDUCTED ON RETURN (ADD BACKS)
A10: 3a | B10: Book depreciation (replaced by tax MACRS) | C10: WTB r105-108 | D10: ='Working Trial Balance'!D105+'Working Trial Balance'!D106+'Working Trial Balance'!D107+'Working Trial Balance'!D108 | E10: COMMON: Book SL depreciation. Added back because tax uses MACRS (Ln 6a). Desert Peak: $60K book depr. | F10: Form 4562 | G10: Must tie to book depreciation schedule / fixed asset report. | H10: Placeholder till I get UT to work
A11: 3b | B11: >2% Shareholder health insurance | C11: WTB r91 (F col) | D11: ='Working Trial Balance'!D91 | E11: COMMON: Officer health insurance for >2% shareholders. Not deducted on 1120-S — goes on officer W-2 Box 1 and K-1. | F11: W-2 / K-1 | G11: Deducted on SH personal return (pg 1, line 17 of 1040). NOT on 1120-S.
A12: 3c | B12: Meals — 50% disallowance | C12: WTB r99 (F col) | D12: ='Working Trial Balance'!H99 | E12: COMMON: 50% of business meals (post-2022). $18K total × 50% = $9K disallowed. 50% IS on Pg 1. | F12: Pg 1, Ln 19 | G12: Verify: some years had 100% deduction (2021-2022 restaurant meals).
A13: 3d | B13: Entertainment (100% disallowed) | C13: WTB r100 (F col) | D13: ='Working Trial Balance'!H100 | E13: COMMON: All entertainment is 100% nondeductible post-TCJA. Sporting events, golf, concerts, etc. | F13: N/A ($0 on return) | G13: Confirm client properly separates meals from entertainment in their books.
A14: 3e | B14: Charitable contributions (separately stated) | C14: WTB r114 (F col) | D14: ='Working Trial Balance'!D114 | E14: COMMON: Deducted on books but separately stated on K Ln 12a. SH deducts on personal Sch A. | F14: K Ln 12a | G14: If corp received property donations, may need Form 8283 at SH level.
A15: 3f | B15: Political contributions | C15: WTB r115 (F col) | D15: ='Working Trial Balance'!D115 | E15: COMMON: 100% nondeductible. Lobbying, political campaigns, PACs. | F15: K Ln 16c | G15: Reduces SH basis only. Does NOT reduce AAA.
A16: 3g | B16: Penalties & fines | C16: WTB r116 (F col) | D16: ='Working Trial Balance'!D116 | E16: COMMON: Late filing penalties, parking tickets, regulatory fines. 100% nondeductible. | F16: K Ln 16c | G16: Exception: some restitution payments may be deductible — check §162(f).
A17: 3h | B17: Life insurance premiums (corp beneficiary) | C17: WTB r117 (F col) | D17: ='Working Trial Balance'!D117 | E17: COMMON: Key person life insurance where corp is beneficiary. Nondeductible. | F17: K Ln 16c | G17: If SH is beneficiary, may be compensation. Different treatment.
A18: 3i | B18: Club dues | C18: WTB r118 (F col) | D18: ='Working Trial Balance'!D118 | E18: COMMON: Country club, social club, athletic club. 100% nondeductible since 1993. | F18: K Ln 16c | G18: Business meals AT a club ARE deductible (50%) — separate those out.
A19: 3j | B19: Officers' life insurance (excess) | D19: ='Working Trial Balance'!H113 | E19: If >$50K term life provided to officers. Excess over $50K is nondeductible and included in W-2. | F19: W-2
A20: 3k | B20: Excess compensation (reasonable comp issue) | E20: RARE: If IRS determines officer comp exceeds reasonable amount. Amount reclassified as distribution. | G20: Typically only on exam / audit. Leave blank unless specific issue.
A21: 3l | B21: Travel & entertainment (other disallowed) | E21: Luxury water transportation, first-class airfare limits (usually immaterial). Check for "lavish or extravagant" items.
A22: 3m | B22: Other expenses on books not on return | E22: Catch-all: reserves, accrued expenses not deductible until paid (§461(h)), warranty accruals, etc. | G22: Attach detail if material. Consider if timing (temporary) or permanent.
A23: 3 | B23: TOTAL LINE 3 — Expenses on books not on return | C23: WTB r150 | D23: =SUM(D10:D22) | F23: WTB M-1 Ln 3 total
A24: 4 | B24: TOTAL (Lines 1 + 2 + 3) | D24: =D7+D8+D23 | G24: This is book NI adjusted for all items deducted on books but not on return.
B25: LINE 5: INCOME INCLUDED ON BOOKS NOT ON RETURN (SUBTRACT)
A26: 5a | B26: Tax-exempt interest income | C26: WTB r72 (F col) | D26: 0 | E26: COMMON: Municipal bond interest. On books as income but NOT taxable. Remove for tax. | F26: K Ln 16a | G26: Goes to OAA on M-2, not AAA. Sign should be negative (subtracting from Ln 4).
A27: 5b | B27: Unrealized gains/losses | C27: WTB r73 (F col) | D27: =-'Working Trial Balance'!D136 | E27: COMMON: Mark-to-market gains/losses on investments. Book income, not realized for tax. | F27: N/A (not on return) | G27: GAAP requires recognition; tax waits until sale. Reverse when sold.
A28: 5c | B28: Life insurance proceeds | E28: If corp received death benefit on key person policy. Book income, not taxable (§101). | F28: K Ln 16b | G28: Goes to OAA.
A29: 5d | B29: PPP loan forgiveness | E29: Was common 2020-2022. Book income from forgiveness, excluded from taxable income. | F29: K Ln 16b | G29: Related expenses ARE still deductible (Rev Proc 2021-48).
A30: 5e | B30: Other income on books not on return | E30: Installment sale income deferred for tax, income from flow-through entities recognized differently, etc.
A31: 5 | B31: TOTAL LINE 5 — Income on books not on return | C31: WTB r155 | D31: =SUM(D26:D30) | F31: WTB M-1 Ln 5 total | G31: These amounts should be NEGATIVE (reducing income per return). F column in WTB carries sign.
B32: LINE 6: DEDUCTIONS ON RETURN NOT ON BOOKS (SUBTRACT)
A33: 6a | B33: Tax depreciation — MACRS / bonus | C33: WTB r109 (F col) | D33: =-'Working Trial Balance'!F109 | E33: COMMON: Tax MACRS/bonus depreciation replaces book SL. Usually LARGER than book depr → negative here. | F33: Form 4562 / Pg 1 Ln 14 | G33: Desert Peak: $75K MACRS. Compare to $60K book depr (Ln 3a). Net extra deduction = $15K.
A34: 6b | B34: §179 deduction | C34: WTB r110 (F col) | D34: =-'Working Trial Balance'!F110 | E34: COMMON: Immediate expensing of qualifying assets. $1,220,000 limit (2024). Separately stated on K Ln 11. | F34: K Ln 11 / Form 4562 | G34: Desert Peak: $17K. Subject to business income limitation and total asset phase-out.
A35: 6c | B35: Bonus depreciation (if separate from MACRS) | E35: 100% bonus expired after 2022. 80% for 2023, 100% for 2024, 0% for 2025, 20% for 2026. Often combined with 6a. | F35: Form 4562 | G35: If your depreciation software breaks out bonus separately, add here. Otherwise included in 6a.
A36: 6d | B36: Amortization (tax vs book difference) | E36: §197 intangibles, organizational costs, start-up costs. Tax amortization may differ from book. | F36: Form 4562 Part VI
A37: 6e | B37: Other deductions on return not on books | E37: Catch-all: depletion, soil/water conservation, exploration expenditures, etc.
A38: 6 | B38: TOTAL LINE 6 — Deductions on return not on books | C38: WTB r159 | D38: =SUM(D33:D37) | F38: WTB M-1 Ln 6 total | G38: These amounts should be NEGATIVE (they reduce income per return).
A40: 7 | B40: INCOME (LOSS) PER RETURN (Line 4 + Line 5 + Line 6) | D40: =D24+D31+D38 | G40: THIS IS THE KEY NUMBER. Should = sum of all Sch K income items. Ties to WTB M-1 proof.
A42: TIE-OUT CHECKS
B43: M-1 Line 7 = WTB M-1 Proof Line 7 | D43: =D40-'Working Trial Balance'!H180 | E43: =IF(D43=0,"✓ TIES","✗ OFF")
B44: M-1 Line 1 = PBC P&L Net Income | D44: =D7-'P&L'!B63 | E44: =IF(D44=0,"✓ TIES","✗ OFF")
B45: M-1 Line 3 total = WTB F150 (addbacks total) | D45: =D23-'Working Trial Balance'!H170 | E45: =IF(D45=0,"✓ TIES","✗ OFF")
A47: TEMPLATE NOTES — Highlighted items in column E are COMMON adjustments for most S-corp clients. Delete or zero unused lines for your client.
A48: If gross receipts > $250K AND total assets > $10M → use Schedule M-3 (separate tab) instead of M-1. Both are included in this workbook.

Sheet Schedule M-2
A1: [ENTITY NAME] — Schedule M-2 — Analysis of AAA, OAA, and Shareholders' Equity
A2: Tax Year Ended [MM/DD/YYYY]
A3: M-2 is TAX BASIS. PBC Balance Sheet is BOOK BASIS. The equity tie-out at the bottom reconciles the difference.
B5: AAA (Accumulated Adjustments Account) | C5: OAA (Other Adjustments Account) | D5: PTI (Previously Taxed Income) | E5: Retained Earnings (per Books) | F5: Sch K Line / Source | G5: Notes
A6: 1. Balance at beginning of tax year | F6: Prior-year M-2 / Sch L | G6: ⚠ MANUALLY ENTER: Must tie to prior-year M-2 ending balances. Obtain from prior-year return.
A8: INCREASES
A9: 2. Ordinary business income (loss) | B9: ='Working Trial Balance'!F155 | E9: ='PBC - P&L2'!B63 | F9: K Ln 1 / Pg 1 Ln 21 | G9: AAA = tax OBI from WTB. RE = book net income from P&L.
A10: 3a. Net rental income (equipment) | B10: =-('Working Trial Balance'!C66)-'Working Trial Balance'!D121 | F10: K Ln 3a | G10: Net rental = income (−C66 = $85K moved to K) minus expenses (D121 = $35K). K Ln 3a net = $50K.
A11: 3b. Interest income | B11: ='Schedule K'!D16 | F11: K Ln 4 | G11: Sch K adj was negative (removed from Pg 1). Flip sign for AAA increase.
A12: 3c. Dividend income | B12: ='Schedule K'!D17 | F12: K Ln 5a | G12: Same — flip Sch K adj sign. Qualified $6,800 → K Ln 5b.
A13: 3d. Net capital gains | B13: ='Schedule K'!D20 | F13: K Ln 8a | G13: Net LTCG from stock sales = $12K. §1245 recapture ($10K) is ordinary income already in OBI (Ln 2). Only net capital gain goes here.
A14: 3e. §1231 gain (net) | F14: K Ln 9 | G14: §1231 portion of equipment sale gain → AAA
A15: 3f. Ordinary gain (§1245 recapture) | B15: 0 | F15: Pg 1 Ln 4 / F.4797 | G15: §1245 recapture ($10K) is ORDINARY income → Pg 1 Ln 4 → Ln 21 → already in OBI (Ln 2 above). DO NOT add here — would double count.
A16: 3g. Tax-exempt interest | C16: ='Working Trial Balance'!C72*-1 | F16: K Ln 16a | G16: Tax-exempt income → OAA, NOT AAA. Increases SH basis.
A17: 3h. Other tax-exempt income | F17: K Ln 16b | G17: PPP forgiveness, life insurance proceeds → OAA if applicable.
A18: Total Increases | B18: =SUM(B9:B17) | C18: =SUM(C9:C17) | D18: =SUM(D9:D17) | E18: =SUM(E9:E17)
A20: DECREASES
A21: 4a. Ordinary business loss | F21: K Ln 1 | G21: If loss year — decreases AAA (can go negative from losses)
A22: 4b. §179 deduction | B22: 0 | F22: See note → | G22: ⚠ §179 ($17K) is included in D column deductions (WTB row 110), which reduces OBI in Ln 2 above. Listing it here would DOUBLE-COUNT. Set to $0. If your WTB moves §179 out of the D column, add it back here.
A23: 4c. Charitable contributions | B23: ='Schedule K'!D28 | F23: K Ln 12a | G23: Separately stated → decreases AAA. Uses M-1 col (F) because that's where the separately stated amount is.
A24: 4d. Nondeductible expenses (K Ln 16c) | B24: ='Schedule K'!D58 | F24: K Ln 16c | G24: These reduce SH BASIS only. They do NOT reduce AAA. Total $42,700 → K-1 Box 16C.
A25: • 50% meals disallowance $___ | G25: Basis only
A26: • Entertainment (100%) $___ | G26: Basis only
A27: • Penalties & fines $___ | G27: Basis only
A28: • Political contributions $___ | G28: Basis only
A29: • Life insurance (corp beneficiary) $___ | G29: Basis only
A30: • Club dues $___ | G30: Basis only
A31: Total nondeductible $___ | F31: K Ln 16c | G31: Reduces SH basis. Does NOT reduce AAA.
A32: Total Decreases | B32: =SUM(B21:B24) | C32: =SUM(C21:C24) | D32: =SUM(D21:D24) | E32: =SUM(E21:E24)
A34: 5. Distributions | B34: =-' Balance Sheet'!E62 | E34: =B34 | F34: K Ln 16d | G34: Principal Shareholder $180K + — $120K = $300K. Formulas pull from WTB.
A35: DISTRIBUTION ORDERING RULES:
A36: 1st: Reduce AAA (cannot go negative from distributions) | G36: Excess → next bucket
A37: 2nd: Reduce accumulated E&P (taxed as DIVIDEND to SH) | G37: Only if prior C-corp — N/A here
A38: 3rd: Reduce OAA | G38: Tax-free to extent of OAA
A39: 4th: Return of capital (reduce stock basis) | G39: Tax-free to extent of basis
A40: 5th: Capital gain | G40: Excess over all basis → taxable LTCG
A42: 6. ENDING BALANCE | B42: =B6+B18-B32-B34 | C42: =C6+C18-C32 | D42: =D6+D18-D32 | E42: =E6+E18-E32-E34 | G42: See equity tie-out below.
A44: CHECK 1: AAA CANNOT GO NEGATIVE FROM DISTRIBUTIONS
A45: AAA before distributions | B45: =B6+B18-B32
A46: Distributions | B46: =B34
A47: AAA after distributions (= ending AAA) | B47: =B42
A48: STATUS: | B48: =IF(B42>=0,"OK - AAA positive","WARNING: AAA NEGATIVE - review distributions")
A50: CHECK 2: TAX-BASIS EQUITY (M-2 → Schedule L if tax basis)
A51: AAA ending | B51: =B42
A52: + OAA ending
A53: + Common Stock | B53: ='Schedule L'!D36 | G53: ⚠ MANUALLY ENTER from Sch L / Articles of Incorporation
A54: + Additional Paid-In Capital | B54: ='Schedule L'!D37 | G54: ⚠ MANUALLY ENTER from Sch L / capital records
A55: = TAX-BASIS EQUITY (if Sch L is tax basis, this IS Sch L equity) | B55: =SUM(B51:B54)
A57: CHECK 3: BOOK-TO-TAX EQUITY RECONCILIATION (if Sch L is BOOK basis)
A58: Book equity (from PBC Balance Sheet) | B58: ='PBC- Balance Sheet'!B88
A59: Less: Tax-basis equity (from Check 2 above) | B59: =-B55
A60: = Cumulative book-to-tax differences | B60: =B58+B59
A62: This difference is explained by:
A63: Prior-year cumulative book-to-tax differences (beg RE − beg AAA − beg OAA) | B63: =E6-B6-C6 | G63: ⚠ Computed from beginning balances — verify against prior-year workpaper
A64: + Unrealized gain on investments (book income, not on return) | B64: ='Working Trial Balance'!F73*-1 | G64: Book NI includes $9K unrealized gain; tax does not recognize → book equity higher
A65: − Entertainment expense (book expense, $0 on return) | B65: ='Working Trial Balance'!F100*-1 | G65: $12K on books as expense. Removed from return (D=0 via C adj). Reduces book RE, not AAA → book equity lower
A66: − >2% SH health insurance (book expense, not on 1120-S) | G66: $28K on books. Not deducted on 1120-S (goes to W-2/K-1). Reduces book RE, not AAA → book equity lower
A67: + Tax depreciation excess over book (MACRS $75K + §179 $17K vs book $60K) | B67: ='Working Trial Balance'!D109+'Working Trial Balance'!D110-('Working Trial Balance'!F105+'Working Trial Balance'!F106+'Working Trial Balance'!F107+'Working Trial Balance'!F108) | G67: Tax depr (MACRS+§179) = $92K vs book SL = $60K. Extra $32K tax deduction reduces AAA below RE → book equity higher. Note: §179 is in D column / OBI in this WTB.
A68: + Rental expenses (on return via K Ln 3, not on book P&L) | B68: ='Working Trial Balance'!D121 | G68: $35K rental expense reduces AAA (via net rental on K Ln 3a) but is NOT on book P&L → book equity higher
A69: + WTB structural adjustment: nondeductibles included in D/OBI | B69: =B60-SUM(B63:B68) | G69: ⚠ STRUCTURAL: This WTB includes meals (50%), political ($5K), penalties ($3.5K), life ins ($7.2K), and club dues ($6K) in D column deductions / OBI. These reduce AAA via OBI but are actually nondeductible. This line is a formula plug = cumulative diff − other items. If you move these out of D column (add Sch K adj), this line should become zero.
A70: = Total explained differences | B70: =SUM(B63:B69)
A72: VARIANCE (Cumulative diff − Explained — should be zero) | B72: =B60-B70

Sheet Schedule L
A1: [ENTITY NAME] — Schedule L — Balance Sheets per Books
A2: Tax Year Ended [MM/DD/YYYY]
A3: [ENTITY NAME] (S-Corp) — EIN: [XX-XXXXXXX]
A4: BOY = Beginning of Year (from prior-year return Sch L ending balances). EOY = End of Year (from current-year PBC / WTB). Red cells = manually enter from prior-year return.
A6: Line | B6: Description | C6: [PY] Amount | D6: (b) BOY Amount | E6: [CY] Amount | F6: (d) EOY Amount | G6: Ties To | H6: Notes / Source
B7: Sch L has dual columns: (a)/(c) for gross amounts, (b)/(d) for offsets (e.g., reserves, accum depr). Some lines use only (b)/(d).
B8: ASSETS
A9: 1 | B9: Cash | E9: =' Balance Sheet'!B8 | G9: WTB r8-9 | H9: ⚠ MANUALLY ENTER — BOY from prior-year 1120-S, Sch L Ln 1(d)
A10: 2a | B10: Trade notes & accounts receivable | E10: =' Balance Sheet'!B10 | G10: WTB r10 | H10: ⚠ MANUALLY ENTER — BOY from prior-year Sch L Ln 2a(a)
A11: 2b | B11: Less allowance for bad debts | E11: ='Working Trial Balance'!F11 | G11: WTB r11 | H11: ⚠ MANUALLY ENTER — BOY from prior-year Sch L Ln 2b(b)
A12: 3 | B12: Inventories | E12: =' Balance Sheet'!B14 | G12: WTB r14 | H12: ⚠ MANUALLY ENTER — BOY from prior-year Sch L Ln 3(d)
A13: 4 | B13: U.S. government obligations | H13: Treasury bills, notes, bonds. Most S-corps leave blank.
A14: 5a | B14: Tax-exempt securities | E14: =' Balance Sheet'!B19 | G14: WTB r18 | H14: ⚠ MANUALLY ENTER — BOY from prior-year Sch L Ln 5a(d)
A15: 6 | B15: Other current assets | E15: =' Balance Sheet'!B12+' Balance Sheet'!B13 | G15: WTB r12-13 | H15: ⚠ MANUALLY ENTER — BOY from prior-year Sch L Ln 6(d)
A16: 7 | B16: Loans to shareholders
A17: 8 | B17: Mortgage & real estate loans | H17: Notes receivable from RE loans. Most service S-corps = $0.
A18: 9 | B18: Other investments | E18: =' Balance Sheet'!B18 | G18: WTB r17 | H18: ⚠ MANUALLY ENTER — BOY from prior-year Sch L Ln 9(d)
A19: 10a | B19: Buildings & other depreciable assets | E19: =' Balance Sheet'!B23+' Balance Sheet'!B25+' Balance Sheet'!B27+' Balance Sheet'!B29 | G19: WTB r21,23,25,27 | H19: ⚠ MANUALLY ENTER — BOY from prior-year Sch L Ln 10a(a). If tax-basis Sch L, use tax cost basis.
A20: 10b | B20: Less accumulated depreciation | E20: =' Balance Sheet'!B24+' Balance Sheet'!B26+' Balance Sheet'!B28+' Balance Sheet'!B30 | G20: WTB r22,24,26,28 | H20: ⚠ MANUALLY ENTER — BOY from prior-year Sch L Ln 10b(b). CRITICAL: book vs tax depr difference.
A21: 11a | B21: Depletable assets | H21: Oil/gas, mining, timber. Most service S-corps = $0.
A22: 11b | B22: Less accumulated depletion
A23: 12 | B23: Land (net of any amortization) | H23: Land is NOT depreciable. Separate from Ln 10a.
A24: 13a | B24: Intangible assets (amortizable only) | E24: =' Balance Sheet'!B35 | G24: WTB r32 | H24: ⚠ MANUALLY ENTER — BOY from prior-year Sch L Ln 13a(a)
A25: 13b | B25: Less accumulated amortization | H25: If PBC provides org costs NET, this may be $0 and net amount goes in 13a. Check.
A26: 14 | B26: Other assets (attach statement) | E26: =' Balance Sheet'!B34 | G26: WTB r31 | H26: ⚠ MANUALLY ENTER — BOY from prior-year Sch L Ln 14(d)
A27: 15 | B27: TOTAL ASSETS | C27: =SUM(C9:C26) | D27: =D11+D20 | E27: =SUM(E9:E26) | F27: =F11+F20 | G27: WTB r35 | H27: Net total assets = (a/c) gross − (b/d) contras. Must tie to WTB Total Assets.
E28: =E27-'Working Trial Balance'!F35
B29: LIABILITIES AND SHAREHOLDERS' EQUITY
A30: 16 | B30: Accounts payable | F30: =' Balance Sheet'!B42 | G30: WTB r38 | H30: ⚠ MANUALLY ENTER — BOY from prior-year Sch L Ln 16(d)
A31: 17 | B31: Mortgages, notes, bonds payable < 1 year | F31: =' Balance Sheet'!B47 | G31: WTB r43 | H31: ⚠ MANUALLY ENTER — BOY from prior-year Sch L Ln 17(d)
A32: 18 | B32: Other current liabilities (attach statement) | F32: =' Balance Sheet'!B43+' Balance Sheet'!B44+' Balance Sheet'!B45+' Balance Sheet'!B46 | G32: WTB r39-42 | H32: ⚠ MANUALLY ENTER — BOY from prior-year Sch L Ln 18(d)
A33: 19 | B33: Loans from shareholders | F33: =' Balance Sheet'!B53 | G33: WTB r46 | H33: ⚠ MANUALLY ENTER — BOY from prior-year Sch L Ln 19(d)
A34: 20 | B34: Mortgages, notes, bonds payable ≥ 1 year | F34: =' Balance Sheet'!B51+' Balance Sheet'!B52 | G34: WTB r44-45 | H34: ⚠ MANUALLY ENTER — BOY from prior-year Sch L Ln 20(d)
A35: 21 | B35: Other liabilities (attach statement) | F35: ='Working Trial Balance'!F44 | H35: Deferred revenue, deferred rent, contingent liabilities. Desert Peak: none.
A36: 22a | B36: Capital stock | F36: =' Balance Sheet'!B59 | G36: WTB r50 | H36: ⚠ MANUALLY ENTER — BOY from prior-year Sch L Ln 22a(d)
A37: 23 | B37: Additional paid-in capital | F37: =' Balance Sheet'!B60 | G37: WTB r51 | H37: ⚠ MANUALLY ENTER — BOY from prior-year Sch L Ln 23(d)
A38: 24 | B38: Retained earnings | F38: =' Balance Sheet'!B65-' Balance Sheet'!B59-' Balance Sheet'!B60 | G38: WTB r52-55 / M-2 | H38: ⚠ MANUALLY ENTER — BOY from prior-year Sch L Ln 24(d). CRITICAL: This is BOOK RE, not AAA.
A39: 25 | B39: Adjustments to shareholders' equity (attach statement) | H39: Unrealized gains/losses on AFS securities (OCI), foreign currency adjustments. Most S-corps = $0.
A40: 26 | B40: Less cost of treasury stock | H40: S-corps can only have one class of stock. Treasury stock is rare. Leave blank unless repurchased shares.
A41: 27 | B41: TOTAL LIABILITIES & SHAREHOLDERS' EQUITY | D41: =SUM(D30:D38) | F41: =SUM(F30:F40) | G41: WTB r58 | H41: Must = Total Assets (Ln 15). If off, check each section.
A43: TIE-OUT CHECKS
B44: EOY Net Assets = WTB Total Assets | D44: =E27-'Working Trial Balance'!D35 | E44: =IF(D44=0,"✓ TIES","✗ OFF by "&TEXT(D44,"#,##0"))
B45: EOY: Total Assets = Total L&E (BS balances) | D45: =(E27-F27)-F41 | E45: =IF(D45=0,"✓ TIES","✗ OFF by "&TEXT(D45,"#,##0"))
B46: BOY: Total Assets = Total L&E (BS balances) | D46: =(C27-D27)-D41 | E46: =IF(D46=0,"✓ TIES","✗ OFF by "&TEXT(D46,"#,##0")) | F46: BOY values are hardcoded placeholders — replace with actual prior-year Sch L ending balances. Check will pass once real data is entered.
B47: EOY Equity (Sch L) = PBC Balance Sheet Equity | D47: =(F36+F37+F38)-' Balance Sheet'!B65 | E47: =IF(D47=0,"✓ TIES","✗ OFF by "&TEXT(D47,"#,##0"))
B48: EOY RE per Sch L = M-2 Book RE ending balance | D48: =F38-'Schedule M-2'!E42 | E48: =IF(D48=0,"✓ TIES","✗ OFF by "&TEXT(D48,"#,##0"))
B49: EOY Total Liabilities = WTB Total Liabilities | D49: =F41-'Working Trial Balance'!F58 | E49: =IF(D49=0,"✓ TIES","✗ OFF by "&TEXT(D49,"#,##0"))
A51: TEMPLATE NOTES:
A52: • Sch L is reported on BOOK BASIS for most S-corps. If the corp reports on TAX BASIS, the depreciation and equity numbers will differ from PBC.
A53: • BOY columns should equal EXACTLY what was reported on the prior-year Sch L ending columns. If you change anything, the IRS will notice the mismatch.
A54: • Sch L lines use dual columns: (a)/(c) for gross amounts and (b)/(d) for contra/offset amounts (like accum depr, allowance for bad debts). Liabilities and equity use only (b)/(d).
A55: • If total assets ≤ $250K at EOY, the IRS does not require Sch L (check Box G on page 1). Still recommended as a workpaper.

Sheet 7203 - Principal SH
A1: [ENTITY NAME] — Form 7203 — S Corporation Shareholder Stock and Debt Basis Limitations
A2: Tax Year Ended [MM/DD/YYYY]
A3: Shareholder: [NAME]
A4: Filed with shareholder's Form 1040. Required if SH claims loss/deduction, receives distribution, disposes of stock, or receives loan repayment.
A6: Line | B6: Description | C6: K-1 Box / Source | D6: Amount | E6: Running Basis | F6: Ties To | G6: Notes
B7: PART I — SHAREHOLDER STOCK BASIS
A8: 1 | B8: Stock basis at beginning of corporation's tax year | C8: Prior-year 7203 Ln 27 | G8: ⚠ MANUALLY ENTER — Beginning stock basis from prior-year Form 7203 Line 27 (or initial cost basis if first year). This is the MOST CRITICAL input.
A9: 2 | B9: Stock purchased or additional capital contributions during year | C9: Stock certs / PBC | D9: 0 | G9: ⚠ MANUALLY ENTER — Only if new capital contributed this year. Usually $0.
A10: 3 | B10: Basis from restored debt repayment (from Part II, if applicable) | C10: Part II below | D10: 0 | G10: Only if SH had reduced debt basis in prior year AND corp repaid some debt this year. Rare.
B11: INCREASES TO STOCK BASIS
A12: 4 | B12: Ordinary business income (K-1 Box 1) | C12: K-1 Box 1 / Sch K Ln 1 | D12: ='Schedule K'!F11 | F12: Sch K Ln 1 | G12: Pro rata share of OBI. Increases basis even though SH may not receive cash.
A13: 5 | B13: Net rental income (K-1 Box 2/3) | C13: K-1 Box 3 / Sch K Ln 3c | D13: 0 | F13: Sch K Ln 3c | G13: Net rental income (if positive). If negative, goes to loss section below.
A14: 6 | B14: Interest + dividends + capital gains + §1231 gains (K-1 Boxes 4-9) | C14: K-1 Boxes 4,5a,8a,9 | D14: ='Schedule K'!F16+'Schedule K'!F17+'Schedule K'!F21+'Schedule K'!F24 | F14: Sch K Ln 4+5a+8a+9 | G14: All separately stated income items: interest, dividends, LTCG, §1231. Only include positive amounts here.
A15: 7 | B15: Tax-exempt income (K-1 Box 16A/16B) | C15: K-1 Box 16A / Sch K Ln 16a | D15: 0 | F15: Sch K Ln 16a | G15: Muni bond interest. INCREASES basis even though not taxable. This is why it goes to OAA, not AAA.
A16: 8 | B16: Excess depletion (oil & gas) | C16: K-1 Box 15D | D16: 0 | G16: Only for oil/gas. Most S-corps = $0.
A17: 9 | B17: TOTAL INCREASES (Lines 4 through 8) | D17: =SUM(D12:D16) | G17: Sum of all items that increase SH stock basis.
A18: 10 | B18: Stock basis before distributions & losses (Ln 1 + 2 + 3 + 9) | D18: =D8+D9+D10+D17 | E18: =D18 | G18: KEY CHECKPOINT: This is your basis before subtracting distributions. Distributions cannot reduce basis below zero.
B19: DISTRIBUTIONS & NON-DIVIDEND DISTRIBUTIONS
A20: 11 | B20: Distributions (excluding dividend distributions) (K-1 Box 16D) | C20: K-1 Box 16D / Sch K Ln 16d | D20: ='Schedule K'!F59 | F20: Sch K Ln 16d / M-2 | G20: This SH's share of total distributions. Cannot reduce stock basis below zero — excess = capital gain.
A21: 12 | B21: Stock basis after distributions (Ln 10 − Ln 11, but not below zero) | D21: =MAX(D18-D20,0) | E21: =D21 | G21: If distributions > Ln 10, excess is capital gain to SH (report on Sch D). Basis cannot go negative from distributions.
B22: ► Distribution excess (capital gain to SH) | D22: =MAX(D20-D18,0) | E22: =IF(D22>0,"⚠ CG to SH","OK - within basis") | G22: If > 0, shareholder must report this as capital gain on personal Sch D. Basis drops to $0.
B23: DECREASES TO STOCK BASIS (order matters per §1367)
A24: 13 | B24: Nondeductible, noncapital expenses (K-1 Box 16C) | C24: K-1 Box 16C / Sch K Ln 16c | D24: ='Schedule K'!F58 | F24: Sch K Ln 16c | G24: Meals 50%, entertainment, political, penalties, life ins, club dues, >2% SH health. Reduces basis but NOT deductible.
A25: 14 | B25: Deductions — §179 expense (K-1 Box 11) | C25: K-1 Box 11 / Sch K Ln 11 | D25: 0 | F25: Sch K Ln 11 | G25: §179 expensing. Limited by SH basis AND SH business income. Already included in OBI for AAA but separately stated on K.
A26: 15 | B26: Deductions — Charitable contributions (K-1 Box 12A) | C26: K-1 Box 12A / Sch K Ln 12a | D26: ='Schedule K'!F28 | F26: Sch K Ln 12a | G26: Separately stated. SH deducts on personal Sch A. Still reduces stock basis regardless of SH AGI limits.
A27: 16 | B27: Other deductions, losses, and items that decrease basis | C27: K-1 various | D27: 0 | G27: Investment interest expense (Box 12H), net OBL if negative (Box 1), rental losses (Box 2/3), STCL (Box 7), other. Include any negative K-1 items here.
A28: 17 | B28: TOTAL DECREASES (Lines 13 through 16) | D28: =SUM(D24:D27) | G28: Total items that reduce stock basis. If this exceeds Ln 12, see Part III for loss limitations.
A29: 18 | B29: Allowable decrease (lesser of Ln 17 or Ln 12) | D29: =MIN(D28,D21) | G29: Cannot reduce stock basis below zero. Excess losses → carryforward (Part III) or to debt basis (Part II).
A30: 19 | B30: Suspended losses (Ln 17 − Ln 18, carried forward) | D30: =D28-D29 | E30: =IF(D30>0,"⚠ CARRYFORWARD","OK - all deducted") | G30: If > 0, these losses carry forward indefinitely until SH has sufficient basis. Track on next year's 7203.
A31: 20 | B31: STOCK BASIS AT END OF YEAR (Ln 12 − Ln 18) | D31: =D21-D29 | E31: =D31 | G31: THIS IS THE ENDING STOCK BASIS. Carries to next year's Ln 1. Should be ≥ $0. If $0, no further losses allowed against stock basis.
B33: PART II — SHAREHOLDER DEBT BASIS
B34: Debt basis = loans FROM the shareholder TO the corporation (not bank debt, not corp loans to SH). Only the SH who made the loan gets debt basis.
A35: 21 | B35: Shareholder debt basis at beginning of year | C35: Prior-year 7203 Ln 27 | G35: ⚠ MANUALLY ENTER — Debt basis from prior-year 7203. SH loan to corp = $25,000 per Sch L Ln 19. Debt basis may differ from loan balance if previously reduced.
A36: 22 | B36: Additional loans from SH to corp during year | C36: Loan docs / PBC | D36: 0 | G36: ⚠ MANUALLY ENTER — New loans from SH to corp this year. Verify with loan documents.
A37: 23 | B37: Debt basis before repayment and losses (Ln 21 + 22) | D37: =D35+D36 | G37: Available debt basis before any loan repayments or loss allocations.
A38: 24 | B38: Losses that exceeded stock basis, applied to debt basis | D38: =MIN(D30,D37) | G38: If stock basis hit $0 and there are excess losses, they reduce debt basis (up to debt basis amount). §1366(d)(1)(A).
A39: 25 | B39: Loan repayments from corporation to shareholder | C39: K-1 Box 16E / Loan docs | D39: 0 | G39: ⚠ MANUALLY ENTER — Loan repayments from corp to SH this year. Check bank records / loan amort schedule.
A40: 26 | B40: DEBT BASIS AT END OF YEAR (Ln 23 − 24 − 25) | D40: =MAX(D37-D38-D39,0) | E40: =D40 | G40: Ending debt basis. If reduced below face value of loan, a future repayment triggers gain recognition.
B41: ► Gain on loan repayment (if debt basis < repayment) | D41: =MAX(D39-D37+D38,0) | E41: =IF(D41>0,"⚠ TAXABLE GAIN","OK - no gain") | G41: If > 0, SH has ordinary income on loan repayment. Report on Form 1040. See §1367(b)(2).
B43: TOTAL BASIS SUMMARY
A44: 27 | B44: TOTAL SHAREHOLDER BASIS (Stock Ln 20 + Debt Ln 26) | D44: =D31+D40 | E44: =D44 | G44: TOTAL BASIS = stock + debt. This limits total deductible losses AND is used for gain/loss on stock sale. Carries forward to next year 7203 Line 1.
A46: TIE-OUT CHECKS
B47: Stock basis ≥ $0 (cannot be negative) | D47: =D31 | E47: =IF(D47>=0,"✓ OK","✗ NEGATIVE BASIS ERROR")
B48: Debt basis ≥ $0 (cannot be negative) | D48: =D40 | E48: =IF(D48>=0,"✓ OK","✗ NEGATIVE BASIS ERROR")
B49: Distributions within basis? (Ln 11 ≤ Ln 10) | D49: =D20-D18 | E49: =IF(D49<=0,"✓ OK - within basis","⚠ EXCESS = cap gain $"&TEXT(D49,"#,##0"))
B50: Distributions = Sch K allocation (100%) | D50: =D20-'Schedule K'!F59 | E50: =IF(D50=0,"✓ TIES","✗ OFF")
B51: Nondeductible expenses = Sch K allocation (100%) | D51: =D24-'Schedule K'!F58 | E51: =IF(D51=0,"✓ TIES","✗ OFF")
B52: Debt basis BOY ≤ Sch L SH loan BOY | D52: =D35-'Schedule L'!D33 | E52: =IF(D52<=0,"✓ OK","⚠ Debt basis > loan face value")
A54: TEMPLATE NOTES:
A55: • Beginning basis (Ln 1) MUST match prior-year 7203 Line 20 (stock) exactly. IRS compares year-over-year. If first year of S election, use initial stock cost basis.
A56: • ORDER OF BASIS ADJUSTMENTS MATTERS (§1367): 1st: Increase for income items → 2nd: Decrease for distributions → 3rd: Decrease for nondeductible → 4th: Decrease for losses/deductions.
A57: • Suspended losses from Line 19 carry forward indefinitely and are allowed when the shareholder gets additional basis (new contributions, future income allocations, new loans to corp).
A58: • At-risk rules (§465) and passive activity rules (§469) apply AFTER basis limitations. A loss that passes basis may still be limited by at-risk or passive activity rules at the SH level.

Sheet Schedule M-3
A1: [ENTITY NAME] — Schedule M-3 — Net Income (Loss) Reconciliation
A2: Tax Year Ended [MM/DD/YYYY]
A3: NOTE: Desert Peak files M-1 (assets < $10M). This M-3 is included as a template. All formulas tie to WTB.
A5: PART II — Reconciliation of Net Income per Income Statement to Income per Return
A6: Line Item | B6: (a) Book Amount | C6: (b) Temporary Differences | D6: (c) Permanent Differences | E6: (d) = a + b + c Tax Return Amount | F6: Ties To (Return Line) | G6: Notes
A7: INCOME ITEMS
A8: 1. Gross receipts / sales | B8: ='Working Trial Balance'!B64+'Working Trial Balance'!B65 | C8: 0 | D8: 0 | E8: =B8+C8+D8 | F8: Pg 1, Ln 1a | G8: Book consulting + software revenue from WTB
A9: 2. Returns & allowances | B9: ='Working Trial Balance'!B67 | C9: 0 | D9: 0 | E9: =B9+C9+D9 | F9: Pg 1, Ln 1b
A10: 3. Cost of goods sold | B10: =-'Working Trial Balance'!D80 | C10: 0 | D10: 0 | E10: =B10+C10+D10 | F10: Pg 1, Ln 2 | G10: Shown as negative (expense)
A11: 4. Interest income | B11: ='Working Trial Balance'!B68 | C11: 0 | D11: 0 | E11: =B11+C11+D11 | F11: K Ln 4 | G11: Portfolio — separately stated
A12: 5. Dividend income | B12: ='Working Trial Balance'!B69 | C12: 0 | D12: 0 | E12: =B12+C12+D12 | F12: K Ln 5a | G12: Qualified $6,800 → K Ln 5b
A13: 6. Capital gains (net LTCG) | B13: ='Working Trial Balance'!B70 | C13: 0 | D13: 0 | E13: =B13+C13+D13 | F13: K Ln 8a | G13: From Form 8949 / Sch D
A14: 7. Gain on sale of assets | B14: ='Working Trial Balance'!B71 | C14: 0 | D14: 0 | E14: =B14+C14+D14 | F14: Pg 1 Ln 4 / K Ln 9 | G14: Ordinary recapture $10K + §1231 $5K
A15: 8. Equipment rental income | B15: ='Working Trial Balance'!B66 | C15: 0 | D15: 0 | E15: =B15+C15+D15 | F15: K Ln 3a | G15: Separately stated rental activity
A16: 9. Tax-exempt interest | B16: ='Working Trial Balance'!B72 | C16: 0 | E16: =B16+C16+D16 | F16: K Ln 16a | G16: PERMANENT: Not taxable. Increases OAA & basis.
A17: 10. Unrealized gain on investments | B17: ='Working Trial Balance'!B73 | D17: 0 | E17: =B17+C17+D17 | F17: N/A | G17: TEMPORARY: Book mark-to-market not recognized for tax.
A18: TOTAL INCOME ITEMS | B18: =SUM(B8:B17) | C18: =SUM(C8:C17) | D18: =SUM(D8:D17) | E18: =SUM(E8:E17)
A20: EXPENSE / DEDUCTION ITEMS (shown as positive = expense)
A21: 11. Officer compensation | B21: ='Working Trial Balance'!B83+'Working Trial Balance'!B84 | C21: 0 | D21: 0 | E21: =B21+C21+D21 | F21: Pg 1, Ln 7 | G21: No book-tax diff. Verify reasonable comp.
A22: 12. Salaries & wages | B22: ='Working Trial Balance'!B88 | C22: 0 | D22: 0 | E22: =B22+C22+D22 | F22: Pg 1, Ln 8 | G22: Reconcile to W-3
A23: 13. Payroll taxes | B23: ='Working Trial Balance'!B89 | C23: 0 | D23: 0 | E23: =B23+C23+D23 | F23: Pg 1, Ln 12
A24: 14. >2% SH health insurance | B24: ='Working Trial Balance'!B91 | C24: 0 | E24: =B24+C24+D24 | F24: NOT on 1120-S | G24: PERMANENT: Added to W-2 instead. SH deducts on 1040.
A25: 15. Depreciation (book) | B25: 60000 | D25: 0 | E25: =B25+C25+D25 | F25: N/A — removed | G25: TEMPORARY: Book depr removed, replaced by tax MACRS.
A26: 16. Depreciation (tax MACRS/bonus) | B26: 0 | C26: ='Working Trial Balance'!D109 | D26: 0 | E26: =B26+C26+D26 | F26: Pg 1, Ln 14 | G26: TEMPORARY: Tax depr from Form 4562.
A27: 17. §179 deduction | B27: 0 | C27: ='Working Trial Balance'!D110 | D27: 0 | E27: =B27+C27+D27 | F27: K Ln 11 | G27: TEMPORARY: Separately stated. SH-level limit.
A28: 18. Business meals | B28: ='Working Trial Balance'!B99 | C28: 0 | E28: =B28+C28+D28 | F28: Pg 1 Ln 19 (50% only) | G28: PERMANENT: 50% disallowance.
A29: 19. Entertainment | B29: ='Working Trial Balance'!B100 | C29: 0 | E29: =B29+C29+D29 | F29: N/A — $0 | G29: PERMANENT: 100% nondeductible §274(a).
A30: 20. Charitable contributions | B30: ='Working Trial Balance'!B114 | C30: 0 | E30: =B30+C30+D30 | F30: K Ln 12a | G30: PERMANENT (entity): Separately stated. SH AGI limits.
A31: 21. Fines and penalties | B31: ='Working Trial Balance'!B116 | C31: 0 | E31: =B31+C31+D31 | F31: N/A — $0 | G31: PERMANENT: 100% nondeductible §162(f).
A32: 22. Political contributions | B32: ='Working Trial Balance'!B115 | C32: 0 | E32: =B32+C32+D32 | F32: N/A — $0 | G32: PERMANENT: 100% nondeductible.
A33: 23. Life insurance (corp beneficiary) | B33: ='Working Trial Balance'!B117 | C33: 0 | E33: =B33+C33+D33 | F33: N/A — $0 | G33: PERMANENT: Nondeductible — corp is beneficiary.
A34: 24. Club dues | B34: ='Working Trial Balance'!B118 | C34: 0 | E34: =B34+C34+D34 | F34: N/A — $0 | G34: PERMANENT: 100% nondeductible §274(a)(3).
A35: 25. Rent expense | B35: ='Working Trial Balance'!B93 | C35: 0 | D35: 0 | E35: =B35+C35+D35 | F35: Pg 1, Ln 11
A36: 26. Interest expense | B36: =-'Working Trial Balance'!B119-'Working Trial Balance'!B120 | C36: 0 | D36: 0 | E36: =B36+C36+D36 | F36: Pg 1, Ln 13 | G36: LOC + vehicle loan. Check §163(j).
A37: 27. Employee benefits + 401(k) | B37: ='Working Trial Balance'!B90+'Working Trial Balance'!B92 | C37: 0 | D37: 0 | E37: =B37+C37+D37 | F37: Pg 1, Ln 17-18 | G37: Staff health + 401(k)
A38: 28. Rental activity expenses | B38: 0 | C38: ='Working Trial Balance'!D121 | D38: 0 | E38: =B38+C38+D38 | F38: K Ln 3c | G38: Equipment rental expenses — separately stated
A39: 29. All other deductions | B39: ='Working Trial Balance'!B101+'Working Trial Balance'!B102+'Working Trial Balance'!B103+'Working Trial Balance'!B104+'Working Trial Balance'!B94+'Working Trial Balance'!B95+'Working Trial Balance'!B96+'Working Trial Balance'!B97+'Working Trial Balance'!B98+'Working Trial Balance'!B111+'Working Trial Balance'!B112+'Working Trial Balance'!B113 | C39: 0 | D39: 0 | E39: =B39+C39+D39 | F39: Pg 1, Ln 9/16/19 | G39: Travel, utils, supplies, telecom, ins, repairs, bank fees, vehicle, etc.
A40: TOTAL EXPENSE ITEMS | B40: =SUM(B21:B39) | C40: =SUM(C21:C39) | D40: =SUM(D21:D39) | E40: =SUM(E21:E39)
A41: NET INCOME RECONCILIATION
A42: Net income (loss) = Income − Expenses | B42: =B18-B40 | C42: =C18-C40 | D42: =D18-D40 | E42: =E18-E40
A44: TIE-OUT CHECKS
A45: CHECK 1: Column (a) net income = P&L Net Income per Books
A46: M-3 Col (a) net | B46: =B42
A47: P&L net income per books | B47: ='P&L'!B63
A48: DIFFERENCE (should be zero) | B48: =B46-B47
A50: CHECK 2: M-3 Col (d) Net Income → M-1 Line 7 Bridge
A51: M-3 Col (d) net income per return | B51: =E42
A52: M-1 Line 7 (income per return from WTB) | B52: ='Working Trial Balance'!F168
A53: DIFFERENCE | B53: =B51-B52
A55: NOTE: M-3 Col (d) and M-1 Line 7 will NOT match exactly.
A56: M-3 captures items at the Pg 1 / gross level. M-1 Line 7 reconciles from
A57: book NI and includes M-1 addbacks (SH health, nondeductibles) that are NOT
A58: on M-3. The difference represents these reconciling items. A large unexpected
A59: difference should be investigated.
A73: CHECK 5: Ordinary Business Income tie to WTB / Pg 1, Ln 21 / Sch K, Ln 1
A74: WTB Ordinary Business Income | B74: ='Working Trial Balance'!D144
A75: M-1 Line 1 (net income per books) | B75: ='Working Trial Balance'!F147
A76: M-3 Col (a) net income | B76: =B42
A77: Book NI vs M-1 Ln 1 DIFF (should be zero) | B77: =B76-B75

Sheet 7203 - SH2 (NA)
A1: [ENTITY NAME] — Form 7203 — S Corporation Shareholder Stock and Debt Basis Limitations
A2: Tax Year Ended [MM/DD/YYYY]
A3: Shareholder: [NAME]
A4: Filed with shareholder's Form 1040. Required if SH claims loss/deduction, receives distribution, disposes of stock, or receives loan repayment.
A6: Line | B6: Description | C6: K-1 Box / Source | D6: Amount | E6: Running Basis | F6: Ties To | G6: Notes
B7: PART I — SHAREHOLDER STOCK BASIS
A8: 1 | B8: Stock basis at beginning of corporation's tax year | C8: Prior-year 7203 Ln 27 | G8: ⚠ MANUALLY ENTER — Beginning stock basis from prior-year Form 7203 Line 27 (or initial cost basis if first year). This is the MOST CRITICAL input.
A9: 2 | B9: Stock purchased or additional capital contributions during year | C9: Stock certs / PBC | D9: 0 | G9: ⚠ MANUALLY ENTER — Only if new capital contributed this year. Usually $0.
A10: 3 | B10: Basis from restored debt repayment (from Part II, if applicable) | C10: Part II below | D10: 0 | G10: Only if SH had reduced debt basis in prior year AND corp repaid some debt this year. Rare.
B11: INCREASES TO STOCK BASIS
A12: 4 | B12: Ordinary business income (K-1 Box 1) | C12: K-1 Box 1 / Sch K Ln 1 | D12: ='Schedule K'!G11 | F12: Sch K Ln 1 | G12: Pro rata share of OBI. Increases basis even though SH may not receive cash.
A13: 5 | B13: Net rental income (K-1 Box 2/3) | C13: K-1 Box 3 / Sch K Ln 3c | D13: ='Schedule K'!G15 | F13: Sch K Ln 3c | G13: Net rental income (if positive). If negative, goes to loss section below.
A14: 6 | B14: Interest + dividends + capital gains + §1231 gains (K-1 Boxes 4-9) | C14: K-1 Boxes 4,5a,8a,9 | D14: ='Schedule K'!G16+'Schedule K'!G17+'Schedule K'!G21+'Schedule K'!G24 | F14: Sch K Ln 4+5a+8a+9 | G14: All separately stated income items: interest, dividends, LTCG, §1231. Only include positive amounts here.
A15: 7 | B15: Tax-exempt income (K-1 Box 16A/16B) | C15: K-1 Box 16A / Sch K Ln 16a | D15: ='Schedule K'!G56 | F15: Sch K Ln 16a | G15: Muni bond interest. INCREASES basis even though not taxable. This is why it goes to OAA, not AAA.
A16: 8 | B16: Excess depletion (oil & gas) | C16: K-1 Box 15D | D16: 0 | G16: Only for oil/gas. Most S-corps = $0.
A17: 9 | B17: TOTAL INCREASES (Lines 4 through 8) | D17: =SUM(D12:D16) | G17: Sum of all items that increase SH stock basis.
A18: 10 | B18: Stock basis before distributions & losses (Ln 1 + 2 + 3 + 9) | D18: =D8+D9+D10+D17 | E18: =D18 | G18: KEY CHECKPOINT: This is your basis before subtracting distributions. Distributions cannot reduce basis below zero.
B19: DISTRIBUTIONS & NON-DIVIDEND DISTRIBUTIONS
A20: 11 | B20: Distributions (excluding dividend distributions) (K-1 Box 16D) | C20: K-1 Box 16D / Sch K Ln 16d | D20: ='Schedule K'!G59 | F20: Sch K Ln 16d / M-2 | G20: This SH's share of total distributions. Cannot reduce stock basis below zero — excess = capital gain.
A21: 12 | B21: Stock basis after distributions (Ln 10 − Ln 11, but not below zero) | D21: =MAX(D18-D20,0) | E21: =D21 | G21: If distributions > Ln 10, excess is capital gain to SH (report on Sch D). Basis cannot go negative from distributions.
B22: ► Distribution excess (capital gain to SH) | D22: =MAX(D20-D18,0) | E22: =IF(D22>0,"⚠ CG to SH","OK - within basis") | G22: If > 0, shareholder must report this as capital gain on personal Sch D. Basis drops to $0.
B23: DECREASES TO STOCK BASIS (order matters per §1367)
A24: 13 | B24: Nondeductible, noncapital expenses (K-1 Box 16C) | C24: K-1 Box 16C / Sch K Ln 16c | D24: ='Schedule K'!G58 | F24: Sch K Ln 16c | G24: Meals 50%, entertainment, political, penalties, life ins, club dues, >2% SH health. Reduces basis but NOT deductible.
A25: 14 | B25: Deductions — §179 expense (K-1 Box 11) | C25: K-1 Box 11 / Sch K Ln 11 | D25: ='Schedule K'!G27 | F25: Sch K Ln 11 | G25: §179 expensing. Limited by SH basis AND SH business income. Already included in OBI for AAA but separately stated on K.
A26: 15 | B26: Deductions — Charitable contributions (K-1 Box 12A) | C26: K-1 Box 12A / Sch K Ln 12a | D26: ='Schedule K'!G28 | F26: Sch K Ln 12a | G26: Separately stated. SH deducts on personal Sch A. Still reduces stock basis regardless of SH AGI limits.
A27: 16 | B27: Other deductions, losses, and items that decrease basis | C27: K-1 various | D27: 0 | G27: Investment interest expense (Box 12H), net OBL if negative (Box 1), rental losses (Box 2/3), STCL (Box 7), other. Include any negative K-1 items here.
A28: 17 | B28: TOTAL DECREASES (Lines 13 through 16) | D28: =SUM(D24:D27) | G28: Total items that reduce stock basis. If this exceeds Ln 12, see Part III for loss limitations.
A29: 18 | B29: Allowable decrease (lesser of Ln 17 or Ln 12) | D29: =MIN(D28,D21) | G29: Cannot reduce stock basis below zero. Excess losses → carryforward (Part III) or to debt basis (Part II).
A30: 19 | B30: Suspended losses (Ln 17 − Ln 18, carried forward) | D30: =D28-D29 | E30: =IF(D30>0,"⚠ CARRYFORWARD","OK - all deducted") | G30: If > 0, these losses carry forward indefinitely until SH has sufficient basis. Track on next year's 7203.
A31: 20 | B31: STOCK BASIS AT END OF YEAR (Ln 12 − Ln 18) | D31: =D21-D29 | E31: =D31 | G31: THIS IS THE ENDING STOCK BASIS. Carries to next year's Ln 1. Should be ≥ $0. If $0, no further losses allowed against stock basis.
B33: PART II — SHAREHOLDER DEBT BASIS
B34: Debt basis = loans FROM the shareholder TO the corporation (not bank debt, not corp loans to SH). Only the SH who made the loan gets debt basis.
A35: 21 | B35: Shareholder debt basis at beginning of year | C35: Prior-year 7203 Ln 27 | D35: 0 | G35: This shareholder has no loans to the corporation. Debt basis = $0.
A36: 22 | B36: Additional loans from SH to corp during year | C36: Loan docs / PBC | D36: 0 | G36: ⚠ MANUALLY ENTER — New loans from SH to corp this year. Verify with loan documents.
A37: 23 | B37: Debt basis before repayment and losses (Ln 21 + 22) | D37: =D35+D36 | G37: Available debt basis before any loan repayments or loss allocations.
A38: 24 | B38: Losses that exceeded stock basis, applied to debt basis | D38: =MIN(D30,D37) | G38: If stock basis hit $0 and there are excess losses, they reduce debt basis (up to debt basis amount). §1366(d)(1)(A).
A39: 25 | B39: Loan repayments from corporation to shareholder | C39: K-1 Box 16E / Loan docs | D39: 0 | G39: ⚠ MANUALLY ENTER — Loan repayments from corp to SH this year. Check bank records / loan amort schedule.
A40: 26 | B40: DEBT BASIS AT END OF YEAR (Ln 23 − 24 − 25) | D40: =MAX(D37-D38-D39,0) | E40: =D40 | G40: Ending debt basis. If reduced below face value of loan, a future repayment triggers gain recognition.
B41: ► Gain on loan repayment (if debt basis < repayment) | D41: =MAX(D39-D37+D38,0) | E41: =IF(D41>0,"⚠ TAXABLE GAIN","OK - no gain") | G41: If > 0, SH has ordinary income on loan repayment. Report on Form 1040. See §1367(b)(2).
B43: TOTAL BASIS SUMMARY
A44: 27 | B44: TOTAL SHAREHOLDER BASIS (Stock Ln 20 + Debt Ln 26) | D44: =D31+D40 | E44: =D44 | G44: TOTAL BASIS = stock + debt. This limits total deductible losses AND is used for gain/loss on stock sale. Carries forward to next year 7203 Line 1.
A46: TIE-OUT CHECKS
B47: Stock basis ≥ $0 (cannot be negative) | D47: =D31 | E47: =IF(D47>=0,"✓ OK","✗ NEGATIVE BASIS ERROR")
B48: Debt basis ≥ $0 (cannot be negative) | D48: =D40 | E48: =IF(D48>=0,"✓ OK","✗ NEGATIVE BASIS ERROR")
B49: Distributions within basis? (Ln 11 ≤ Ln 10) | D49: =D20-D18 | E49: =IF(D49<=0,"✓ OK - within basis","⚠ EXCESS = cap gain $"&TEXT(D49,"#,##0"))
B50: Distributions = Sch K allocation (0%) | D50: =D20-'Schedule K'!G59 | E50: =IF(D50=0,"✓ TIES","✗ OFF")
B51: Nondeductible expenses = Sch K allocation (0%) | D51: =D24-'Schedule K'!G58 | E51: =IF(D51=0,"✓ TIES","✗ OFF")
A54: TEMPLATE NOTES:
A55: • Beginning basis (Ln 1) MUST match prior-year 7203 Line 20 (stock) exactly. IRS compares year-over-year. If first year of S election, use initial stock cost basis.
A56: • ORDER OF BASIS ADJUSTMENTS MATTERS (§1367): 1st: Increase for income items → 2nd: Decrease for distributions → 3rd: Decrease for nondeductible → 4th: Decrease for losses/deductions.
A57: • Suspended losses from Line 19 carry forward indefinitely and are allowed when the shareholder gets additional basis (new contributions, future income allocations, new loans to corp).
A58: • At-risk rules (§465) and passive activity rules (§469) apply AFTER basis limitations. A loss that passes basis may still be limited by at-risk or passive activity rules at the SH level.

Sheet Strategy Inputs
A1: [ENTITY NAME] — Tax Strategy Inputs
A2: Yellow cells = INPUT. Type the dollar amount. It auto-flows to the AJE tab and WTB. Blue font = you enter this. Black = formula/auto.
A3: M-1 ADJUSTMENTS do NOT adjust client books. They only create the M-1 addback. Book stays at the PBC amount — the tax return just doesn't deduct it.
A5: # | B5: Adjustment Description | C5: INPUT Amount ($) | D5: Auto / Calc | E5: What This Does / How It Works | F5: Flows To → AJE | G5: Flows To → WTB | H5: Type
A6: SECTION 1: SCHEDULE K RECLASSIFICATIONS — Remove from OBI, Report on Sch K Separately
A7: 1 | B7: Equipment Rental Income (Gross — remove from OBI → K Ln 3a) | D7: ='P&L'!B9 | E7: Removes rental income from Pg 1 OBI. Reports separately on Sch K Ln 3a. Input = $0 if no rental activity. Auto-pulls from PBC if left blank. | F7: AJE-01 (reclassification) | G7: WTB r66 Col C WTB r121 Col C (expenses) | H7: Sch K Reclass
A8: 2 | B8: Rental Activity Expenses (Goes to K Ln 3b — only if rental income above) | E8: Expenses related to the rental activity. Separately stated on K Ln 3b. Enter as positive number. | F8: AJE-01 (part of rental) | G8: WTB r121 Col C | H8: Sch K Reclass
A9: 3 | B9: Interest Income (Bank) (Remove from OBI → K Ln 4) | D9: ='P&L'!B53 | E9: Removes bank interest from Pg 1 OBI. Reports on Sch K Ln 4. Auto-pulls from PBC. | F9: AJE-02 | G9: WTB r68 Col C | H9: Sch K Reclass
A10: 4 | B10: Dividend Income (Ordinary) (Remove from OBI → K Ln 5a) | D10: ='P&L'!B54 | E10: Removes dividends from Pg 1 OBI. Reports on Sch K Ln 5a/5b. Need 1099-DIV Box 1b for qualified portion. | F10: AJE-03 | G10: WTB r69 Col C | H10: Sch K Reclass
A11: 4a | B11: Qualified Dividends (Subset of #4 — for K Ln 5b) | E11: Subset of total dividends that are qualified. From 1099-DIV Box 1b. Does NOT change the total — just tells Sch K the qualified portion. | F11: AJE-03 (detail) | G11: Schedule K Ln 5b | H11: Info Only
A12: 5 | B12: Capital Gain — Stock Sales (LTCG) (Remove from OBI → K Ln 8a) | D12: ='P&L'!B56 | E12: Removes LTCG from Pg 1. Reports on Sch K Ln 8a via Sch D/8949. Auto-pulls from PBC. | F12: AJE-04 | G12: WTB r70 Col C | H12: Sch K Reclass
A13: 6 | B13: Gain on Sale of Equipment (Split: §1245 recapture stays Pg 1, §1231 → K Ln 9) | D13: ='P&L'!B57 | E13: Total gain auto-pulls. §1245 recapture portion stays on Pg 1 Ln 4. §1231 portion goes to K Ln 9. Usually need to split. | F13: AJE-05 | G13: WTB r71 Col C | H13: Sch K Reclass
A14: 6a | B14: §1231 Gain Portion (The part that goes to K Ln 9 — enter here) | E14: Enter just the §1231 portion. The rest (§1245 recapture) stays on Pg 1. This drives the Col C adjustment on WTB r71. | F14: AJE-05 (§1231 split) | G14: WTB r71 Col C (partial) | H14: Sch K Reclass
A15: 7 | B15: Tax-Exempt Muni Bond Interest (Remove from income → K Ln 16a) | D15: ='P&L'!B60 | E15: Removes tax-exempt interest from income. Not taxable. Reports on K Ln 16a. Also hits M-1 Ln 5a and M-2 → OAA (not AAA). | F15: AJE-17 | G15: WTB r72 Col C + Col F | H15: Sch K + M-1
A16: 8 | B16: Unrealized Gain on Investments (Book only — remove entirely, not realized for tax) | D16: ='P&L'!B61 | E16: Book has unrealized gain; tax doesn't recognize until sold. Remove entirely. M-1 Ln 5b. | F16: AJE-18 | G16: WTB r73 Col C + Col F | H16: M-1 Adj
A17: 9 | B17: Charitable Contributions (Remove from Pg 1 → separately state on K Ln 12a) | D17: ='P&L'!B45 | E17: Charity is NOT deductible on entity Pg 1. Separately stated on K Ln 12a, SH deducts on personal Sch A. | F17: AJE-09 | G17: WTB r114 Col C + Col F | H17: Sch K + M-1
A19: SECTION 2: M-1 NONDEDUCTIBLE EXPENSES — Do NOT Adjust Books. Tax Just Doesn't Deduct These.
A20: 10 | B20: >2% SH Officer Health Insurance (Remove from Pg 1 deductions → W-2 / K Ln 16c) | D20: ='P&L'!B24 | E20: Not a Pg 1 deduction — added to officer W-2 Box 1 instead. SH deducts on personal 1040 Ln 17. Auto-pulls PBC. This IS a Col C adj (removes from deductions) AND M-1. | F20: AJE-06 | G20: WTB r91 Col C + Col F | H20: M-1 + Sch K
A21: 11 | B21: Business Meals — 50% Nondeductible Portion (Book has full amount, tax only deducts 50%) | D21: ='P&L'!B32*0.5 | E21: Auto-calculates 50% of PBC meals. The other 50% IS deductible on Pg 1 Ln 19. This amount = M-1 Ln 3c addback. Does NOT change books. | F21: AJE-07 | G21: WTB r99 Col F only (Col C stays blank) | H21: M-1 Only
A22: 12 | B22: Entertainment — 100% Nondeductible (On books but $0 on tax return) | D22: ='P&L'!B33 | E22: Full amount is nondeductible post-TCJA. M-1 Ln 3d addback. Col C removes from OBI (zero on return). Col F = M-1 addback. | F22: AJE-08 | G22: WTB r100 Col C + Col F | H22: M-1 + Col C
A23: 13 | B23: Political Contributions — 100% Nondeductible | D23: ='P&L'!B46 | E23: Always nondeductible. M-1 addback. Book stays, tax doesn't deduct. | F23: AJE-10 | G23: WTB r115 Col F only | H23: M-1 Only
A24: 14 | B24: Penalties & Fines — 100% Nondeductible | D24: ='P&L'!B47 | E24: Nondeductible under §162(f). Check if any are restitution (may be deductible). M-1 addback. | F24: AJE-11 | G24: WTB r116 Col F only | H24: M-1 Only
A25: 15 | B25: Life Insurance Premiums (Corp Beneficiary) — Nondeductible | D25: ='P&L'!B48 | E25: Nondeductible when corp is beneficiary. If SH is beneficiary, it's comp (different treatment). M-1 addback. | F25: AJE-12 | G25: WTB r117 Col F only | H25: M-1 Only
A26: 16 | B26: Club Dues (Country Club) — Nondeductible | D26: ='P&L'!B49 | E26: Always nondeductible. Meals at club ARE separately deductible at 50% — make sure client splits them out. M-1 addback. | F26: AJE-13 | G26: WTB r118 Col F only | H26: M-1 Only
A28: SECTION 3: DEPRECIATION — Remove Book Depreciation, Add Tax Depreciation (MACRS / §179)
A29: 17 | B29: Total Book Depreciation (Auto-pulls from PBC — ALL book depr removed) | D29: ='P&L'!B38+'P&L'!B39+'P&L'!B40+'P&L'!B41 | E29: Total of all book depreciation categories (vehicle + FF&E + computers + leasehold). Entire amount removed from Pg 1 — replaced by tax depreciation. M-1 Ln 3a addback. | F29: AJE-14 | G29: WTB r105-108 Col C WTB Col F (M-1 addback) | H29: Book→Tax
A30: 18 | B30: Tax Depreciation — MACRS/Bonus (From Form 4562 — ENTER FROM TAX SOFTWARE) | E30: Enter the total tax depreciation from your tax software (CCH, Lacerte, UltraTax). This is NOT on the client books. Goes to Pg 1 Ln 14. M-1 Ln 6a. | F30: AJE-15 | G30: WTB r109 Col D WTB Col F (M-1 deduction) | H30: Tax Only
A31: 19 | B31: §179 Deduction (From Form 4562 Part I — ENTER FROM TAX SOFTWARE) | E31: Enter §179 amount from tax software. Not on client books. Goes to K Ln 11. M-1 Ln 6b. | F31: AJE-16 | G31: WTB r110 Col D WTB Col F (M-1 deduction) | H31: Tax Only
A33: SECTION 4: TAX STRATEGY ADJUSTMENTS — Additional Entity-Level Deductions / Changes
A34: 20 | B34: Augusta Rule — §280A(g) Rent Payment (Entity pays SH for home rental ≤14 days) | E34: Enter total rent paid to SH. FMV × # of days (max 14). Entity deducts on Pg 1 Ln 18. SH gets tax-free income. No M-1 adj needed — deductible on books AND return. | F34: New AJE (auto-generated) | G34: WTB: New deduction Reduces OBI → K Ln 1 Sch L: Lower cash | H34: Entity Deduction
A35: 21 | B35: Home Office — Accountable Plan Reimbursement (Entity reimburses SH for home office expenses) | E35: Enter total reimbursement amount. Based on actual expenses × office %. Must have written Accountable Plan. Entity deducts on Pg 1 Ln 18. Not on W-2. | F35: New AJE (auto-generated) | G35: WTB: New deduction Reduces OBI → K Ln 1 | H35: Entity Deduction
A36: 22 | B36: Kids on Payroll — Child Wages (Wages paid to owner's children for real work) | E36: Enter total child wages. Goes to Pg 1 Ln 8 (salaries). S-Corp must pay FICA on these — FICA exemption only for sole props. Reduces OBI. | F36: New AJE (auto-generated) | G36: WTB: Add to wages Reduces OBI → K Ln 1 | H36: Entity Deduction
A37: 23 | B37: Officer Salary Adjustment (Increase/decrease from PBC amount — enter CHANGE only) | E37: Enter the CHANGE amount (positive = increase salary, negative = decrease). If PBC salary is already correct, leave at $0. Adjusts Pg 1 Ln 7. | F37: New AJE (if nonzero) | G37: WTB r85: Officer comp adj Changes OBI, FICA, distributions | H37: Entity Adj
A38: 24 | B38: Retirement Plan — Additional Employer Contribution (Amount NOT already on PBC books) | E38: Enter additional employer retirement contribution not on PBC. If PBC already has the full contribution, leave at $0. Goes to Pg 1 Ln 17. | F38: New AJE (if nonzero) | G38: WTB: Add to Pg 1 Ln 17 Reduces OBI | H38: Entity Deduction
A39: 25 | B39: Accountable Plan — Other Reimbursements (Cell phone, vehicle, education, travel) | E39: Enter total of other Accountable Plan reimbursements (non-home-office). Entity deducts Pg 1 Ln 18. Tax-free to SH. | F39: New AJE (if nonzero) | G39: WTB: New deduction Reduces OBI | H39: Entity Deduction
A41: TOTALS & FLOW CHECK
B42: Total Sch K Reclassifications (Section 1) | C42: =D7+C8+D9+D10+D12+D13+D15+D16+D17
B43: Total M-1 Nondeductible Addbacks (Section 2) | C43: =D20+D21+D22+D23+D24+D25+D26
B44: Total Depreciation Adjustment (Section 3) | C44: =D29-C30-C31
B45: Total Tax Strategy Additions (Section 4) | C45: =C34+C35+C36+C37+C38+C39
A47: HOW TO USE: Type amounts in the yellow INPUT cells (Col C). Items that auto-pull from PBC show the auto amount in Col D — override Col C if you need a different amount. Leave strategy inputs at $0 if not applicable to this client.
A48: FOR TEMPLATE USE: When starting a new client, clear all yellow input cells. PBC auto-pulls will update when you replace the PBC tabs. Strategy amounts start at $0.

Sheet Tax Strategies
A1: ⛔ NOT APPLICABLE — Client Workbook
A2: How each strategy flows through the 1120-S / 1065 workpapers. Blue = entity-level adjustment. Purple = individual/SH-level (not on entity return).
A3: For strategies that are INDIVIDUAL-ONLY, the entity return has NO adjustment — but the preparer must still ensure proper documentation and K-1 reporting to support the SH's personal return.
A5: # | B5: Strategy / Line Item | C5: Entity-Level Treatment (1120-S / 1065) | D5: Individual / SH Treatment (1040) | E5: Adjusting Entry (DR / CR) | F5: Return Line / Form | G5: WTB / Workpaper Link | H5: Documents Needed | I5: Notes / Risks / IRS Scrutiny
A6: STRATEGY 1: AUGUSTA RULE — §280A(g) 14-Day Home Rental
A7: 1.1 | B7: Overview: S-Corp rents SH's personal home for ≤14 days/year for legitimate business meetings. Corp deducts rent; SH receives tax-free income under §280A(g). | C7: ENTITY: Deductible business expense (rent). Reduces OBI on Pg 1. Flows through WTB as a deduction. | D7: INDIVIDUAL: Rental income is 100% TAX-FREE to SH. NOT reported on SH's 1040 at all. No Schedule E. No income inclusion anywhere. | E7: DR: Rent Expense CR: Cash (paid to SH) | F7: Pg 1 Ln 18 (Other deductions) or Pg 1 Ln 19 | G7: WTB: Add new row in deductions AJE tab: New AJE | H7: • Rental/lease agreement (written) • FMV rental comp analysis (Zillow, VRBO, etc.) • Meeting agendas for each rental day • Meeting minutes / attendee list • Calendar tracking ≤14 days • Payment trace (check/wire) | I7: HIGH SCRUTINY. IRS watches this closely. Must be bona fide business meetings with real business purpose. FMV must be supportable — get 3 comparable rental comps. Cannot exceed 14 days or entire exclusion is lost. Sole proprietors CANNOT use this (need separate entity). Keep meticulous records.
A8: 1.2 | B8: Entity AJE: Add rent expense to Pg 1 deductions | C8: New deduction on Pg 1. Reduces OBI. Flows to K Ln 1 (lower OBI = lower pass-through). No M-1 adjustment needed — this is a legitimate tax deduction that also hits the books. | D8: No effect. SH does NOT report the rental income anywhere on 1040. §280A(g) exclusion is automatic if ≤14 days. | E8: DR: 6950 · Augusta Rent CR: 1000 · Cash Amount: FMV × # days (e.g., $500/day × 12 days = $6,000) | F8: Pg 1 Ln 18 K Ln 1 (reduced OBI) 7203 (lower basis increase) | G8: WTB: New row ~r119 No M-1 adj needed K: Flows thru OBI 7203: Lower Ln 4 | H8: Same as 1.1 above | I8: If client books the rent expense on their P&L (QuickBooks), it flows naturally through PBC → WTB with no special adjustment. If NOT on books, add as an AJE. Tax savings = rent amount × SH marginal rate (both entity deduction AND tax-free income).
A9: 1.3 | B9: Impact on M-1 / M-2 / Sch K / 7203 | C9: M-1: NO adjustment (deductible on both books and return) M-2: AAA decreases by the amount (lower OBI) Sch K: Ln 1 OBI is lower Sch L: Cash decreases, no other BS effect | D9: 7203: SH stock basis increase is lower (lower OBI allocation) But SH received cash = to rent, so net wealth is the same SH does NOT report income → pure savings | G9: M-1: No adj M-2: Lower AAA K Ln 1: Lower 7203 Ln 4: Lower | I9: Savings example: $6,000 rent × 37% bracket = $2,220 income tax saved + $6,000 entity deduction × ~30% = $1,800 = ~$4,020 total family savings. FICA savings too since OBI distributions avoid FICA.
A10: STRATEGY 2: HOME OFFICE — Accountable Plan Reimbursement (§280A / §62(c))
A11: 2.1 | B11: Overview: S-Corp reimburses SH-employee for home office expenses under an Accountable Plan. Corp deducts reimbursement; SH receives tax-free reimbursement (not income). | C11: ENTITY: Deductible expense under Accountable Plan (§62(c)). Reduces OBI on Pg 1. NOT wages — no payroll tax. Booked as "Office Expense" or "Accountable Plan Reimbursement." | D11: INDIVIDUAL: Tax-free reimbursement to SH. NOT reported on W-2. NOT income. SH must reduce personal Sch A mortgage interest & property tax deductions by amounts reimbursed (no double-dip). | E11: DR: 6955 · Home Office Reimb CR: 1000 · Cash Based on actual expenses × office % (e.g., 150 sf / 2,500 sf = 6%) | F11: Pg 1 Ln 18 (Other deductions) or Pg 1 Ln 19 NOT on Form 8829 | G11: WTB: New row ~r120 No M-1 adj needed K: Flows thru OBI 7203: Lower Ln 4 | H11: • Written Accountable Plan document • Home office measurements (sq ft) • Total home sq ft • Expense receipts: mortgage int, prop tax, insurance, utilities, repairs, HOA, depreciation • Expense report submitted to corp • Reimbursement check/records | I11: Must be Accountable Plan (business purpose, substantiation, return excess). S-corp SHs CANNOT use Form 8829 or simplified method ($5/sf). Must use actual expense method. Savings often modest ($200-$350/yr per WCG CPAs) because mortgage int & prop tax are already on Sch A. Bigger savings if renting (rent not on Sch A).
A12: 2.2 | B12: Key requirements & calculation | C12: Accountable Plan must be written and adopted by the board. Must meet 3 requirements: 1. Business connection 2. Adequate accounting (expense reports) 3. Return of excess amounts Without this = taxable compensation. | D12: SH must have exclusive-use home office space. Must be principal place of business OR used for admin/management. Calculate: office sf ÷ total sf × eligible expenses. Reduce Sch A items accordingly. | E12: Example calculation: 150 sf ÷ 2,500 sf = 6% Mortgage int: $20K × 6% = $1,200 Prop tax: $8K × 6% = $480 Insurance: $2K × 6% = $120 Utilities: $4K × 6% = $240 Depr: $10K × 6% = $600 Total reimb: $2,640 | F12: Pg 1 deduction (entity) SH: Reduce Sch A by reimb'd amounts | G12: WTB: Deduction row No M-1 adj K: Lower OBI Sch L: Lower cash | H12: Same as 2.1 above. Also: photos of office space, dedicated use documentation | I12: BONUS: Having a home office can make the commute from home → regular office a deductible business mile (Rev Rul 99-7). This secondary benefit often exceeds the direct home office savings. Track mileage!
A13: STRATEGY 3: KIDS ON PAYROLL — Family Employment / Income Shifting
A14: 3.1 | B14: Overview: Hire owner's children to do legitimate work. Shifts income from parent's high bracket to child's $0/low bracket. Standard deduction ($14,600 for 2024) shelters income. | C14: ENTITY: Wages to children = deductible on Pg 1 Ln 8. Reduces OBI. IMPORTANT: S-Corp / C-Corp must pay FICA (SS+Medicare) and FUTA on child wages — the FICA exemption for kids <18 ONLY applies to sole props & spousal partnerships. | D14: CHILD: Reports wages on their own 1040. Standard deduction ($14,600) shelters most/all income. Child can fund Roth IRA with earned income (up to $7,000/yr). PARENT: No direct 1040 effect — benefit is lower K-1 income from reduced OBI. | E14: DR: 6015 · Wages - Children CR: 2020 · Payroll Liabilities 1000 · Cash W-2 issued to child Payroll taxes apply (S-Corp) | F14: Pg 1 Ln 8 (Salaries/Wages) Form 941 (quarterly) W-2 to child W-3 annual | G14: WTB: Add to deductions Pg 1 Ln 8 K Ln 1: Lower OBI 7203: Lower basis incr No M-1 adj | H14: • Written job description • Time sheets / work log • W-4 from child • I-9 employment verification • Payroll records / pay stubs • W-2 issued • Work product samples • Comparable wage research | I14: MODERATE SCRUTINY. Work must be REAL and AGE-APPROPRIATE. Keep time sheets. Document work product. Wage must be "reasonable" for the work done — a 12-year-old cannot earn $50K for filing papers. Good tasks: social media, cleaning, data entry, modeling/photography, inventory. S-Corp loses the FICA exemption (<18) — still saves income tax via income shifting.
A15: 3.2 | B15: Entity vs. Sole Prop difference (CRITICAL) | C15: S-CORP / C-CORP: • FICA (SS+Medicare) applies to ALL child wages regardless of age • FUTA applies if child ≥21 • Employer pays 7.65% FICA + employee pays 7.65% • Total payroll tax cost: ~15.3% of wages • Still saves income tax via shifting | D15: SOLE PROP / SPOUSAL PARTNERSHIP: • Child <18: NO FICA (SS+Medicare) • Child <21: NO FUTA • MASSIVE payroll tax savings • If considering this strategy heavily, may be worth having a sole prop management company or disregarded LLC pay the kids | E15: Entity structure matters: S-Corp pays child $12K/yr: Income tax saved: $12K × 32% = $3,840 FICA cost: $12K × 15.3% = $1,836 Net savings: ~$2,004 Sole prop pays child $12K: Income tax saved: $3,840 SE tax saved: $12K × 15.3% = $1,836 FICA cost: $0 (exempt) Net savings: ~$5,676 | F15: Same as 3.1 | G15: Same as 3.1 | H15: Same as 3.1 | I15: PRO TIP: Some firms use a sole-prop management company owned by the parent to hire the kids — gets the FICA exemption while the S-Corp pays a management fee to the sole prop. IRS has not challenged this structure directly, but it requires real substance. The management co must do real management work.
A16: 3.3 | B16: Child's Roth IRA funding (bonus strategy) | C16: No entity-level effect — this is on the child's personal side. | D16: Child with earned income can contribute to Roth IRA (up to $7,000 for 2024 or earned income, whichever is less). Grows tax-free FOREVER. A 14-year-old contributing $7K/yr for 4 years = $28K → ~$500K+ by age 65 at 8% return. Parent can "gift" the Roth contribution money back to the child. | E16: No entity AJE. Child opens Roth IRA at Fidelity/Schwab. Custodial account if <18. | F16: Child's 1040 Form 5498 (IRA) | G16: N/A — individual side | H16: • Brokerage account opening docs • Child's W-2 (proves earned income) • Contribution records | I16: This is the real long-term wealth builder. The income tax savings from 3.1 are good, but the Roth IRA compounding is the real play. Kids don't need the cash — parent can match-fund the Roth contribution separately.
A17: STRATEGY 4: S-CORP ELECTION / CONVERSION — Self-Employment Tax Savings
A18: 4.1 | B18: Overview: Convert from Sole Prop / Partnership → S-Corp election. Only W-2 wages are subject to FICA. Distributions are FICA-free. SE tax savings = 15.3% on distribution portion. | C18: ENTITY: New 1120-S return filed instead of Sch C or 1065. Must pay "reasonable compensation" as W-2 wages first. Remaining profit distributed as FICA-free distributions. Entity now has payroll obligations (941, W-2, W-3). | D18: INDIVIDUAL: No more SE tax on Sch C. Instead: W-2 wages (FICA applies) + K-1 distribution income (NO FICA). Net savings depends on salary vs distribution split. SH-employee also gets above-the-line deductions (§199A QBI on distribution portion). | E18: This is a STRUCTURAL change, not an AJE on an existing return. New entity = new return. Prior Sch C income → now 1120-S Pg 1 + K-1. | F18: Form 2553 (S election) 1120-S (new return) K-1 to each SH Form 941 (payroll) W-2 / W-3 | G18: Entire WTB workbook applies to new entity. WTB: Salary on Pg 1 Ln 7-8 K Ln 1: OBI after salary K Ln 16d: Distributions 7203: Full basis tracking | H18: • Form 2553 (filed by 3/15) • Articles of incorporation • EIN application • Payroll setup (ADP, Gusto) • Reasonable comp analysis • Prior Sch C / 1065 P&L • Asset transfer documentation | I18: IRS KEY RISK: "Reasonable compensation" — must pay adequate W-2 salary before distributions. $0 salary with large distributions = audit red flag. See Watson v. Commissioner. Use 3rd party salary data (BLS, PayScale, Robert Half). Document comp analysis in workpapers. Rule of thumb: salary should be ~100% of what you'd pay someone to do your job, but this is NOT a fixed rule.
A19: 4.2 | B19: Savings calculation example | C19: Example: Net profit = $200K SCHEDULE C (before): SE tax: $200K × 15.3% = $30,600 (actually: $200K × 92.35% × 15.3% = $28,256 after deduction) S-CORP (after): Salary: $80K → FICA: $80K × 15.3% = $12,240 Distribution: $120K → FICA: $0 SE tax savings: ~$16,016/year | D19: Additional individual benefits: • §199A QBI deduction applies to K-1 pass-through income (not salary) • Higher K-1 = higher QBI = bigger 20% deduction • But: salary too low means lower Social Security benefit in retirement • And: S-corp has ongoing compliance costs ($2K-5K/yr for accounting/payroll) | E19: No AJE — structural. Break-even analysis: SE tax savings must exceed additional S-Corp costs: • Payroll service: $500-2K/yr • Tax prep (1120-S): $1-3K/yr • State fees: varies • Reasonable comp study: $500-1K Typically worth it if net profit consistently >$50-60K | F19: Same as 4.1 | G19: Same as 4.1 | H19: Same as 4.1 Plus: reasonable comp study from BLS/PayScale data | I19: TIMING: Form 2553 due by 3/15 for calendar year. Late elections possible via Rev Proc 2013-30 (reasonable cause). Watch for state implications — some states don't recognize S-corp or impose entity-level taxes (CA $800 min, NYC UBT). Built-in gains tax if converting C-corp → S-corp with appreciated assets.
A20: STRATEGY 5: OFFICER SALARY OPTIMIZATION — Reasonable Compensation
A21: 5.1 | B21: Overview: Set officer salary at defensible "reasonable compensation" level — not too low (audit risk) and not too high (excess FICA). This IS an entity-level adjustment. | C21: ENTITY: Officer comp = Pg 1 Ln 7. Must file Form 1125-E if gross receipts ≥$500K. Comp is deductible, reduces OBI. W-2 issued. Payroll taxes paid by entity (employer share 7.65%). | D21: INDIVIDUAL: SH receives W-2. Subject to regular income tax + employee FICA (7.65%). Remaining profit = K-1 distribution income (no FICA). Goal: minimize total FICA while maintaining defensible salary. | E21: Salary is already on PBC P&L (if properly booked). AJE only needed if: • Salary is being CHANGED from book amount • Year-end bonus adjustment • Reclassifying distributions as salary (IRS audit) | F21: Pg 1 Ln 7 (Officer comp) Form 1125-E W-2 / W-3 Form 941 K Ln 16d (distributions) | G21: WTB: r19-20 (officer comp) Pg 1 Ln 7-8 K Ln 1: OBI after salary K Ln 16d: Distributions 7203: Basis tracking M-2: AAA computation | H21: • W-2s for all officers • Reasonable comp analysis (3 methods below) • Form 1125-E • Board resolution setting comp • Job descriptions • Time commitment documentation | I21: THREE APPROACHES to reasonable comp: 1. Comparable salary data (BLS, PayScale, Robert Half, Salary.com) 2. Independent investor test (what would investor pay for these services?) 3. Cost savings approach (what would it cost to replace this person?) Document the analysis. Keep in workpapers. IRS will ask for it on audit. Watson v. US (8th Cir 2012) is the landmark case.
A22: 5.2 | B22: Desert Peak example — current vs. optimized | C22: CURRENT (Desert Peak): Principal Shareholder: $95,000 salary —: $65,000 salary Total officer comp: $160,000 Distributions: $300,000 OBI: $963,200 FICA on salary: $160K × 15.3% = $24,480 | D22: ANALYSIS QUESTIONS: • Is $95K reasonable for a President of a $2.3M consulting firm? May be LOW. • Is $65K reasonable for a VP? Depends on role. • IRS factors: time spent, duties, industry comparable, company size/revenue. • If IRS says salary too low, they reclassify distributions → wages + penalties + back FICA. | E22: If adjusting salary: DR: 6000 · Officer Comp CR: 2020 · Payroll Liabilities 1000 · Cash Increasing salary: • Increases Pg 1 Ln 7 • Increases FICA cost • Decreases OBI (K Ln 1) • Decreases distributions | F22: Same as 5.1 | G22: WTB r19: Principal Shareholder comp WTB r20: — comp WTB r136: OBI changes K Ln 1: OBI changes All downstream recalcs | H22: • Salary.com report for "Consulting Firm President" • BLS data for management consulting industry • Robert Half salary guide | I22: DANGER ZONE: With $2.3M gross receipts and $963K OBI, officer comp of $160K is only ~7% of revenue and ~17% of OBI. This WILL draw scrutiny. Consider increasing salary or documenting why the current level is reasonable (e.g., limited hours, other employees do the work, etc.).
A23: ADDITIONAL STRATEGIES — Quick Reference (Common Client Requests)
A24: 6.1 | B24: Retirement plan contributions (SEP, SIMPLE, Solo 401k) | C24: ENTITY: Employer contributions = Pg 1 Ln 17 deduction. Reduces OBI. Employee salary deferrals reduce W-2 Box 1 but stay on Box 3/5 (still subject to FICA). | D24: SH: Employer contribution = tax-free until withdrawal. Employee deferral = pre-tax (traditional) or post-tax (Roth). Solo 401k allows up to $23,500 employee + 25% comp employer (2025). | E24: DR: 6040 · Retirement Contrib CR: 1000 · Cash / Plan Account Usually already on PBC. No special AJE unless contribution is made after year-end (due by filing deadline). | F24: Pg 1 Ln 17 Form 5500 (if applicable) W-2 Box 12 (employee) K-1 (employer portion) | G24: WTB: Deduction row Pg 1 Ln 17 K Ln 1: Lower OBI No M-1 adj | H24: • Plan document • Adoption agreement • Contribution records • Form 5500 (if >$250K) • Employee census data | I24: S-corp officer comp drives contribution limits. Higher salary = higher employer contribution limit. Balance FICA savings (lower salary) vs retirement contribution capacity (higher salary). SEP-IRA: up to 25% of W-2 comp. Solo 401k more flexible.
A25: 6.2 | B25: Accountable Plan — cell phone, internet, vehicle, education, travel | C25: ENTITY: All reimbursements under Accountable Plan = deductible on Pg 1. NOT wages. No payroll tax. Must meet 3 requirements: business connection, substantiation, return excess. | D25: SH: Tax-free reimbursements. Not on W-2. Cell phone, internet (business %), vehicle (actual or mileage), continuing education, professional development, work-related travel. SH keeps personal deductions intact. | E25: DR: Various expense accounts CR: 1000 · Cash Reimburse actual documented expenses only. No flat stipends (that's a Nonaccountable Plan = taxable). | F25: Pg 1 Ln 18/19 Not on W-2 No 1099 | G25: WTB: Deduction rows No M-1 adj K: Lower OBI Sch L: Lower cash | H25: • Written Accountable Plan • Board resolution adopting plan • Expense reports with receipts • Mileage logs (if vehicle) • Business purpose documentation | I25: This replaces the employee business expense deduction (Form 2106) killed by TCJA. SH-employees have NO other way to deduct these expenses post-2017. Accountable Plan is the ONLY mechanism. Every S-corp should have one.
A26: 6.3 | B26: >2% SH health insurance / ICHRA / QSEHRA | C26: ENTITY: Premium paid by corp added to SH W-2 Box 1 (NOT Box 12 Code DD). Deducted as part of officer comp on Pg 1 Ln 7-8. M-1 addback if also booked as separate expense (see AJE-06). ICHRA/QSEHRA: corp reimburses SH for individual policy. | D26: SH: Deducts health insurance premium on 1040 Schedule 1, Line 17 (above-the-line). Net effect: deduction shifts from entity → personal. SH still gets the deduction. ICHRA allows tax-free reimbursement of individual health premiums. | E26: DR: 6031 · Officer Health Ins CR: 1000 · Cash Then add to W-2 Box 1: DR: 6031 · SH Health (W-2) CR: 2020 · Payroll Liab M-1 addback: See AJE-06 | F26: W-2 Box 1 (included) Pg 1 Ln 7-8 (part of comp) M-1 Ln 3b (addback) K Ln 16c (nondeductible) SH 1040 Sch 1 Ln 17 | G26: WTB r91: SH health ins M-1 Ln 3b: Addback K Ln 16c: Nondeductible 7203 Ln 13: Basis decrease AJE-06: Existing entry | H26: • Health insurance policy/invoice • Premium payment records • ICHRA/QSEHRA plan document • W-2 showing inclusion in Box 1 | I26: Already captured in WTB r91 and AJE-06. The strategy is making sure it's structured correctly: corp pays premium → added to W-2 → SH deducts on personal. If not on W-2, SH loses the above-the-line deduction. ICHRA is newer and more flexible — allows SH to pick their own policy and get reimbursed.
A27: 6.4 | B27: §199A Qualified Business Income (QBI) deduction — 20% pass-through deduction | C27: ENTITY: Must report QBI, W-2 wages, and UBIA on K-1 (Box 17 codes V, W, X). QBI = OBI (usually). W-2 wages = from payroll records (Form W-3). UBIA = unadjusted basis of qualified property from fixed asset schedule. | D27: SH: Takes 20% deduction of QBI on personal 1040 (§199A). Subject to limitations: • If taxable income >$191,950 (single) / $383,900 (MFJ): W-2 wage / UBIA test applies • SSTB (specified service) phase-out above thresholds • Deduction = LESSER of 20% QBI or 50% W-2 wages (or 25% W-2 + 2.5% UBIA) | E27: No AJE — reporting only. Entity reports on K-1: Box 17V: QBI amount Box 17W: W-2 wages Box 17X: UBIA SH uses Form 8995 or 8995-A on personal return. | F27: K-1 Box 17 V/W/X SH: Form 8995/8995-A 1040 Ln 13 | G27: K tab: Ln 17d/17e/17f DOC-10 in AJE tab WTB r136: OBI = QBI 7203: Not direct, but QBI drives basis indirectly | H27: • W-3 (total W-2 wages) • Fixed asset schedule (UBIA) • Payroll records • SH taxable income estimate (for limitation testing) | I27: EXPIRING: §199A sunsets after 12/31/2025 under current law (TCJA). If not extended, this deduction disappears for 2026+. Congress may extend. Officer salary interacts: higher salary = lower QBI but higher W-2 wages for the limitation test. Model both scenarios.
A28: 6.5 | B28: Cost segregation study (accelerate depreciation on real property) | C28: ENTITY: Reclassify building components (HVAC, electrical, flooring, etc.) from 39/27.5-yr property to 5/7/15-yr property. Eligible for bonus depreciation. Massive acceleration of depreciation deduction on Pg 1. | D28: SH: Larger depreciation = lower K-1 income = lower taxes now. Creates timing difference (more depr now, less later). May create a loss that's limited by basis (7203), at-risk (§465), or passive activity (§469) rules. | E28: DR: Accumulated Depreciation CR: Depreciation Expense (reclassification of prior years) Current year: DR: Depreciation Expense CR: Accumulated Depreciation (larger current-year deduction) Form 3115 required for change in accounting method. | F28: Form 4562 (depreciation) Form 3115 (method change) Pg 1 Ln 14 M-1 Ln 6a | G28: WTB r109: MACRS M-1 Ln 6a: Larger tax depr Sch L Ln 10a/10b: Adjusted K Ln 1: Lower OBI 7203: Lower basis increase | H28: • Cost segregation study report (from qualified engineer) • Form 3115 (accounting change) • Updated depreciation schedule • Building purchase documents | I28: Only applies if entity owns real property. Cost seg study = $5K-15K but can generate $50K-200K+ in accelerated deductions for a $1M+ building. Form 3115 catch-up adjustment = §481(a) adjustment (often fully deductible in year of change). Bonus depreciation phasing down: 0% (2025), 20% (2026), 0% (2027+).
A29: 6.6 | B29: Charitable giving strategies (bunching, DAF, CRT) | C29: ENTITY: Charitable contributions are already separately stated on K Ln 12a (see AJE-09). Entity reports the contribution; SH deducts on personal Sch A. No entity-level deduction. | D29: SH: "Bunching" — contribute 2-3 years of charitable giving into a Donor Advised Fund (DAF) in one year to exceed standard deduction, then take standard deduction in off years. CRT for large appreciated asset sales. S-corp distributes appreciated stock → SH donates → avoids cap gains. | E29: No entity AJE beyond existing AJE-09. DAF contribution: Entity pays → K Ln 12a SH claims on Sch A If SH contributes personally → no entity involvement at all. | F29: K Ln 12a / K-1 Box 12A SH: Sch A (itemized) Form 8283 (noncash >$500) | G29: WTB r114: Charity AJE-09: Existing K Ln 12a: Already there 7203 Ln 15: Basis decrease | H29: • Donation receipts • DAF account statements • Written acknowledgment (>$250) • Form 8283 (noncash >$500) • Appraisal (noncash >$5,000) | I29: Bunching strategy works best for clients near the standard deduction threshold. If they're always itemizing or never itemizing, bunching has less impact. DAF gives immediate deduction, grants to charity can be made over many years. Sunset alert: SALT cap ($10K) may change, affecting itemization math.
B31: STRATEGY IMPACT MAP — WHERE EACH HITS THE RETURN
B32: Strategy | C32: Pg 1 OBI | D32: M-1 Adj | E32: Sch K | F32: Sch L | G32: M-2 AAA | H32: 7203 | I32: SH 1040
B33: Augusta Rule | C33: ↓ Lower | D33: None | E33: K1: Lower OBI | F33: ↓ Cash | G33: ↓ Lower | H33: ↓ Lower incr | I33: Tax-free income
B34: Home Office | C34: ↓ Lower | D34: None | E34: K1: Lower OBI | F34: ↓ Cash | G34: ↓ Lower | H34: ↓ Lower incr | I34: Tax-free reimb
B35: Kids on Payroll | C35: ↓ Lower | D35: None | E35: K1: Lower OBI | F35: ↓ Cash | G35: ↓ Lower | H35: ↓ Lower incr | I35: Child files 1040
B36: S-Corp Conversion | C36: NEW RETURN | D36: N/A (new) | E36: All K items | F36: Full BS | G36: Full M-2 | H36: Full 7203 | I36: K-1 + W-2
B37: Officer Salary | C37: Pg 1 Ln 7 | D37: None | E37: K1: OBI adj | F37: Payroll liab | G37: AAA adj | H37: Basis adj | I37: W-2 + K-1 split
B38: Retirement Plan | C38: ↓ Pg 1 Ln 17 | D38: None | E38: K1: Lower OBI | F38: ↓ Cash | G38: ↓ Lower | H38: ↓ Lower incr | I38: Tax-deferred
B39: Accountable Plan | C39: ↓ Pg 1 Ln 18 | D39: None | E39: K1: Lower OBI | F39: ↓ Cash | G39: ↓ Lower | H39: ↓ Lower incr | I39: Tax-free reimb
B40: §199A QBI | C40: No change | D40: None | E40: K1 Box 17V/W/X | F40: No change | G40: No change | H40: No change | I40: 20% deduction
B41: Cost Segregation | C41: ↓ More depr | D41: ↑ Ln 6a larger | E41: K1: Lower OBI | F41: ↓ Net FA | G41: ↓ Lower | H41: ↓ Lower incr | I41: Lower K-1 income
A43: COLOR KEY: Blue background = entity-level adjustment (hits 1120-S/1065 return). Purple background = individual/SH-level only (hits 1040, not entity). Both = has components on both.
A44: For 1065 (partnerships): Same strategies apply. Replace 'officer salary' with 'guaranteed payments' (1065 Ln 10). Replace M-2 (AAA/OAA) with Partners' Capital Account analysis (Sch K-1 Item L). Replace 7203 with partner basis worksheet.
A45: DISCLAIMER: Tax strategies must be evaluated per-client. Not all strategies apply to every client. Some strategies interact (e.g., officer salary affects §199A, retirement contribution limits, and FICA). Model the full impact before implementing. Document everything.
